Workbook
Name Scenario: 'FE Assumptions'!#REF!
Name quantityDemanded: #REF!
Name demandSlope: #REF!
Name Scenario: #REF!
Name demandIntercept: #REF!
Name marketSize: #REF!

Sheet Index
B15: INDEX
B17: FINANCE | E17: MARKETING | H17: OPERATIONS
B18: FE ASSUMPTIONS | E18: MK ASSUMPTIONS | H18: OM ASSUMPTIONS
B19: FE STARTING DATA SET | E19: MK ACV DISTRIBUTION | H19: OM COST ANALYSIS
B20: FE INCOME STATEMENT | E20: MK DEMAND CURVE & PURCHASE INTENT | H20: OM CAPITAL EXPENDITURES
B21: FE BALANCE SHEET | E21: MK WEIGHTED PRICE CALCULATIONS | H21: OM INFORMATION SYSTEMS EXPENSES
B22: FE COMPARABLE COMPANIES ANALYSIS | E22: MK SALES PROJECTIONS | H22: OM DIRECT MATERIALS & DIRECT LABOR
B23: FE CASH FLOW | E23: MK IMC SCHEDULE | H23: OM INVENTORY
H24: OM DEMAND AND LEAD TIME
H25: OM G&A EXPENSES
H26: OM PROCESS FLOW
H27: OM CAPACITY ANALYSIS
H28: OM G&A EXPENSES
H29: OM MOH EXPENSES
H30: OM LOCATION ANALYSIS
H31: OM STARTUP COSTS

Sheet FE Assumptions
A1: ASSUMPTIONS
A2: IN US DOLLARS ($) | B2: START-UP | C2: YEAR 1 | D2: YEAR 2 | E2: YEAR 3 | F2: YEAR 4 | G2: YEAR 5 | I2: Link To
A5: INITIAL STARTUP COSTS (START-UP COLUMN ONLY)
A7: INITIAL INVESTMENT IN FIXED ASSETS
A8: Long Term Balance Sheet Items (Can be depreciated - includes IS equip & Factory/office buildout costs) | B8: ='OM Capital Expenditures'!D49+'OM IS Expenses'!C33+'OM Startup Costs'!C18 -> 263922.25 | I8: OM
A10: INITIAL INVESTMENT IN NET WORKING CAPITAL
A11: Cash (Additional Cash required in addition to Start Up costs) | B11: 0 | I11: FE
A12: Raw Materials & Work in Process, Start-Up Period Only (Put Years 1-5 in table Below) | B12: ='OM Startup Costs'!C29+'OM Startup Costs'!C30 -> 30321.778 | I12: OM
A13: Finished Goods Start-up Period Only (Put Years 1-5 in table Below) | B13: ='OM Startup Costs'!C31 -> 2341.5562 | I13: OM
A15: INITIAL OPERATING EXPENSES
A16: Product Development (Prototype, engineer, etc.) | B16: ='OM Startup Costs'!C12 -> 55000 | I16: OM
A17: Pre-Marketing Expenses (Marketing expenses before Year 1) See Sales Projection Tutorial | B17: ='MK IMC Schedule'!O7 -> 40242.05 | I17: MK
A18: All Other (Miscellaneous non depreciated expenses, additional salaries, Rent etc.) | B18: ='OM Startup Costs'!C25 -> 42362.288 | I18: MK, OM
A19: Subtotal Start Up Operating Expenses | B19: =SUM(B16:B18) -> 137604.34
A21: OPERATING INFORMATION (YEARS 1-5)
A23: UNITS SOLD
A24: Units into independent retailers | C24: ='MK ACV Distribution'!C8 -> 40473.718 | D24: ='MK ACV Distribution'!C15 -> 57320.774 | E24: ='MK ACV Distribution'!C22 -> 57689.2 | F24: ='MK ACV Distribution'!C29 -> 70876.639 | G24: ='MK ACV Distribution'!C36 -> 86809.709 | I24: MK
A25: Units online | C25: ='MK ACV Distribution'!D8 -> 6745.6196 | D25: ='MK ACV Distribution'!D15 -> 23883.656 | E25: ='MK ACV Distribution'!D22 -> 38459.467 | F25: ='MK ACV Distribution'!D29 -> 47251.093 | G25: ='MK ACV Distribution'!D36 -> 65107.282 | I25: MK
A26: Units into chain retailer | E26: ='MK ACV Distribution'!E22 -> 9614.8667 | F26: ='MK ACV Distribution'!E29 -> 23625.546 | G26: ='MK ACV Distribution'!E36 -> 57873.139 | I26: MK
A27: Units into mass merchants | F27: ='MK ACV Distribution'!F29 -> 17719.16 | G27: ='MK ACV Distribution'!F36 -> 28936.57 | I27: MK
A28: TOTAL UNITS SOLD | C28: =SUM(C24:C27) -> 47219.337 | D28: =SUM(D24:D27) -> 81204.43 | E28: =SUM(E24:E27) -> 105763.53 | F28: =SUM(F24:F27) -> 159472.44 | G28: =SUM(G24:G27) -> 238726.7
A30: WEIGHTED AVERAGE MANUFACTURER SELLING PRICE
A31: To independent retailers | C31: ='MK Weighted Price Calculations'!D7 -> 31.5 | D31: ='MK Weighted Price Calculations'!D16 -> 31.5 | E31: ='MK Weighted Price Calculations'!D25 -> 31.5 | F31: ='MK Weighted Price Calculations'!D34 -> 31.5 | G31: ='MK Weighted Price Calculations'!D43 -> 31.5 | I31: MK
A32: For online sales | C32: ='MK Weighted Price Calculations'!D6 -> 35 | D32: ='MK Weighted Price Calculations'!D15 -> 35 | E32: ='MK Weighted Price Calculations'!D24 -> 35 | F32: ='MK Weighted Price Calculations'!D33 -> 35 | G32: ='MK Weighted Price Calculations'!D42 -> 35 | I32: MK
A33: To chain retailer | C33: 0 | D33: 0 | E33: ='MK Weighted Price Calculations'!D26 -> 28.35 | F33: ='MK Weighted Price Calculations'!D35 -> 28.35 | G33: ='MK Weighted Price Calculations'!D44 -> 28.35 | I33: MK
A34: To mass merchants | C34: 0 | D34: 0 | E34: 0 | F34: ='MK Weighted Price Calculations'!D36 -> 22.68 | G34: ='MK Weighted Price Calculations'!D45 -> 22.68 | I34: MK
A35: AVERAGE WEIGHTED MANUFACTURER'S AVERAGE SELLING PRICE TO CHANNEL | C35: ='MK Weighted Price Calculations'!C10 -> 34.5 | D35: ='MK Weighted Price Calculations'!C19 -> 33.970588 | E35: ='MK Weighted Price Calculations'!C28 -> 33.122727 | F35: ='MK Weighted Price Calculations'!C37 -> 31.608889 | G35: ='MK Weighted Price Calculations'!C46 -> 30.94
A37: COST OF GOODS SOLD
A38: Variable Cost Per Unit ($/Unit) (Total Direct Cost = Direct Labor + Direct Materials ) | C38: ='OM Direct Materials & Direct La'!D14+('OM Direct Materials & Direct La'!F33+'OM Direct Materials & Direct La'!F34) -> 10.187934 | D38: ='OM Direct Materials & Direct La'!E14+'OM Direct Materials & Direct La'!F51+'OM Direct Materials & Direct La'!F52 -> 10.324093 | E38: ='OM Direct Materials & Direct La'!F14+'OM Direct Materials & Direct La'!F68+'OM Direct Materials & Direct La'!F69 -> 10.708818 | F38: ='OM Direct Materials & Direct La'!G14+'OM Direct Materials & Direct La'!F85+'OM Direct Materials & Direct La'!F86 -> 10.104934 | G38: ='OM Direct Materials & Direct La'!H14+'OM Direct Materials & Direct La'!F102+'OM Direct Materials & Direct La'!F103 -> 10.035576 | I38: OM
A39: Total Outbound Freight ($) (The gross amount, Not Per Unit) | C39: ='OM Location Analysis '!C64 -> 7254.9139 | D39: ='OM Location Analysis '!D64 -> 15413.413 | E39: ='OM Location Analysis '!E64 -> 22117.312 | F39: ='OM Location Analysis '!F64 -> 31571.436 | G39: ='OM Location Analysis '!G64 -> 46900.59 | I39: OM
A40: Total Variable Costs Including Freight ($) | C40: =(C38*C28)+C39 -> 488322.42 | D40: =(D38*D28)+D39 -> 853775.5 | E40: =(E38*E28)+E39 -> 1154719.8 | F40: =(F38*F28)+F39 -> 1643029.9 | G40: =(G38*G28)+G39 -> 2442660.6
A41: Fixed Production Costs ($) (Total MOH per year) | C41: ='OM MOH Expenses'!C15 -> 192923.91 | D41: ='OM MOH Expenses'!D15 -> 248628.14 | E41: ='OM MOH Expenses'!E15 -> 290008.74 | F41: ='OM MOH Expenses'!F15 -> 376145.86 | G41: ='OM MOH Expenses'!G15 -> 501523.09 | I41: OM | K41: COGS Sensitivity
A42: Total Cost of Goods Sold | C42: =C40+C41 -> 681246.33 | D42: =D40+D41 -> 1102403.6 | E42: =E40+E41 -> 1444728.5 | F42: =F40+F41 -> 2019175.7 | G42: =G40+G41 -> 2944183.6 | K42: 1
A43: Per Unit | C43: =C42/C28 -> 14.427274 | D43: =D42/D28 -> 13.575659 | E43: =E42/E28 -> 13.659987 | F43: =F42/F28 -> 12.661597 | G43: =G42/G28 -> 12.332863
A45: SELLING, GENERAL, AND ADMINISTRATIVE EXPENSES
A46: Production costs not included in Cost of Good sold (if any, you may not have any) | I46: OM
A47: Fixed Administrative Costs | C47: ='OM G&A Expenses'!F18 -> 628381.34 | D47: ='OM G&A Expenses'!F39 -> 668845.24 | E47: ='OM G&A Expenses'!F62 -> 849961.52 | F47: ='OM G&A Expenses'!F86 -> 1026543.7 | G47: ='OM G&A Expenses'!F113 -> 1381304.5 | I47: OM
A48: Marketing Expenses (Push and Pull) Excluding Manufacturers Reps ($) | C48: ='MK IMC Schedule'!O31 -> 268280.33 | D48: ='MK IMC Schedule'!O55 -> 344232.76 | E48: ='MK IMC Schedule'!O79 -> 396844.43 | F48: ='MK IMC Schedule'!O103 -> 503401.33 | G48: ='MK IMC Schedule'!O127 -> 631633 | I48: MK
A49: Manufacturer's Sales Reps Commission Expense (10% - excludes Online Units) | C49: =C24*C35*'Starting Data Set'!D22 -> 139634.33 | D49: =D24*D35*'Starting Data Set'!E22 -> 194722.04 | E49: =(E24+E26)*E35*'Starting Data Set'!F22 -> 222929.42 | F49: =(F24+F26+F27)*F35*'Starting Data Set'!G22 -> 354719.2 | G49: =(G24+G26+G27)*G35*'Starting Data Set'!H22 -> 537178.48 | I49: MK
A50: INFORMATION SYSTEMS EXPENSES | C50: ='OM IS Expenses'!D13+'OM IS Expenses'!D27+'OM IS Expenses'!D29+'OM IS Expenses'!D30 -> 34683.4 | D50: ='OM IS Expenses'!E13+'OM IS Expenses'!E27+'OM IS Expenses'!E29+'OM IS Expenses'!E30 -> 35453.77 | E50: ='OM IS Expenses'!F13+'OM IS Expenses'!F27+'OM IS Expenses'!F29+'OM IS Expenses'!F30 -> 37881.039 | F50: ='OM IS Expenses'!G13+'OM IS Expenses'!G27+'OM IS Expenses'!G29+'OM IS Expenses'!G30 -> 46926.761 | G50: ='OM IS Expenses'!H13+'OM IS Expenses'!H27+'OM IS Expenses'!H29+'OM IS Expenses'!H30 -> 49966.074
A51: TOTAL SELLING, GENERAL, AND ADMINISTRATIVE | C51: =SUM(C46:C50) -> 1070979.4 | D51: =SUM(D46:D50) -> 1243253.8 | E51: =SUM(E46:E50) -> 1507616.4 | F51: =SUM(F46:F50) -> 1931591 | G51: =SUM(G46:G50) -> 2600082.1 | I51: OM
A52: PER UNIT | C52: =C51/C28 -> 22.680949 | D52: =D51/D28 -> 15.310172 | E52: =E51/E28 -> 14.254596 | F52: =F51/F28 -> 12.112381 | G52: =G51/G28 -> 10.891459
A53: BALANCE SHEET INFORMATION (YEARS 1-5)
A54: ASSUMPTIONS
A55: Accounts Receivable (Days AR Outstanding) - Online Sales Channel | B55: 5 Days | C55: Given Assumption, no further research required
A56: Accounts Receivable (Days AR Outstanding) - All other Sales Channels | B56: 45 Days | C56: Given Assumption, no further research required
A57: Accounts Payable (Days Payable Outstanding) - US Sourced Vendors | B57: 30 Days | C57: Given Assumption, no further research required
A58: Accounts Payable (Days Payable Outstanding) - Non-US Sourced Vendors | B58: 0 Days | C58: Given Assumption, no further research required
A59: INVENTORY, NET WORIKNG CAPITAL
A60: Raw Materials & Work in Process (Time 0 is above in Start Up Section) | C60: ='OM Inventory'!C46+'OM Inventory'!D46 -> 92355.69 | D60: ='OM Inventory'!C53+'OM Inventory'!D53 -> 127815.22 | E60: ='OM Inventory'!C60+'OM Inventory'!D60 -> 160107.99 | F60: ='OM Inventory'!C67+'OM Inventory'!D67 -> 210899.58 | G60: ='OM Inventory'!C74+'OM Inventory'!D74 -> 268129.3 | I60: OM
A61: Finished Goods (Time 0 is above in Start Up Section) | C61: ='OM Inventory'!E46 -> 28099.493 | D61: ='OM Inventory'!E53 -> 45471.047 | E61: ='OM Inventory'!E60 -> 68815.421 | F61: ='OM Inventory'!E67 -> 96177.534 | G61: ='OM Inventory'!E74 -> 140237.58 | I61: OM
A62: Total Inventories | C62: =SUM(C60:C61) -> 120455.18 | D62: =SUM(D60:D61) -> 173286.27 | E62: =SUM(E60:E61) -> 228923.41 | F62: =SUM(F60:F61) -> 307077.12 | G62: =SUM(G60:G61) -> 408366.89
A63: Additional Investment in Fixed Assets, more capacity or replacement | D63: ='OM Capital Expenditures'!E49 -> 8292.1994 | E63: ='OM Capital Expenditures'!F49 -> 15013.686 | F63: ='OM Capital Expenditures'!G49 -> 7646.5788 | G63: ='OM Capital Expenditures'!H49 -> 13307.389 | I63: OM
A65: OTHER INFORMATION
A67: DISCOUNT RATE | B67: ='FE Comparable Companies Analysi'!C20 -> 0.2090185 | I67: FE
A68: COMMISSION PAID TO MANUFACTURING REPRESENTATIVES | B68: 0.1 | I68: MK
A70: FEDERAL TAX RATE | B70: 0.27 | I70: FE
A71: CASH AS A PERCENTAGE OF SALES | B71: 0.05 | I71: FE

Sheet Starting Data Set
B3: STARTING DATA SET
C4: START-UP | D4: YEAR 1 | E4: YEAR 2 | F4: YEAR 3 | G4: YEAR 4 | H4: YEAR 5
A7: Gross Capital Expenditure ($/per year) | C7: ='FE Assumptions'!B8 -> 263922.25 | D7: ='OM Capital Expenditures'!E49 -> 8292.1994 | E7: ='OM Capital Expenditures'!F49 -> 15013.686 | F7: ='OM Capital Expenditures'!G49 -> 7646.5788 | G7: ='OM Capital Expenditures'!H49 -> 13307.389 | H7: ='OM Capital Expenditures'!I49 -> 15393.662
A9: Cash Balance as a percent of Sales (%) ($10K required for startup) | C9: ='FE Assumptions'!B11 -> 0 | D9: ='FE Assumptions'!$B$71 -> 0.05 | E9: ='FE Assumptions'!$B$71 -> 0.05 | F9: ='FE Assumptions'!$B$71 -> 0.05 | G9: ='FE Assumptions'!$B$71 -> 0.05 | H9: ='FE Assumptions'!$B$71 -> 0.05
A10: Accounts Receivable Days (DSO) | D10: 45 | E10: 45 | F10: 45 | G10: 45 | H10: 45
A11: Accounts Payable Days (DPO) | D11: 30 | E11: 30 | F11: 30 | G11: 30 | H11: 30
A12: Total Days Inventory on Hand (DOH, includes RM, FPI & WIP. $25K required for start-up.) | C12: ='FE Assumptions'!B11+'FE Assumptions'!B12+'FE Assumptions'!B13 -> 32663.334 | D12: 45 | E12: 44 | F12: 44 | G12: 43 | H12: 41
A15: Sales ($) | D15: ='FE Assumptions'!C28*'FE Assumptions'!C35 -> 1629067.1 | E15: ='FE Assumptions'!D28*'FE Assumptions'!D35 -> 2758562.2 | F15: ='FE Assumptions'!E28*'FE Assumptions'!E35 -> 3503176.7 | G15: ='FE Assumptions'!F28*'FE Assumptions'!F35 -> 5040746.6 | H15: ='FE Assumptions'!G28*'FE Assumptions'!G35 -> 7386204.1
A16: Variable Costs ($) | D16: ='FE Assumptions'!C40 -> 488322.42 | E16: ='FE Assumptions'!D40 -> 853775.5 | F16: ='FE Assumptions'!E40 -> 1154719.8 | G16: ='FE Assumptions'!F40 -> 1643029.9 | H16: ='FE Assumptions'!G40 -> 2442660.6
A17: Fixed Production Costs ($) | D17: ='FE Assumptions'!C41 -> 192923.91 | E17: ='FE Assumptions'!D41 -> 248628.14 | F17: ='FE Assumptions'!E41 -> 290008.74 | G17: ='FE Assumptions'!F41 -> 376145.86 | H17: ='FE Assumptions'!G41 -> 501523.09
A18: Initial Startup Expenses ($) | C18: ='FE Assumptions'!B19 -> 137604.34
A19: Administrative Overhead/Salaries ($) | D19: ='FE Assumptions'!C47 -> 628381.34 | E19: ='FE Assumptions'!D47 -> 668845.24 | F19: ='FE Assumptions'!E47 -> 849961.52 | G19: ='FE Assumptions'!F47 -> 1026543.7 | H19: ='FE Assumptions'!G47 -> 1381304.5
A20: General Operating Expenses not already part of CoGS ($) | D20: ='FE Assumptions'!C50 -> 34683.4 | E20: ='FE Assumptions'!D50 -> 35453.77 | F20: ='FE Assumptions'!E50 -> 37881.039 | G20: ='FE Assumptions'!F50 -> 46926.761 | H20: ='FE Assumptions'!G50 -> 49966.074
A21: Marketing Expenses Excluding Mfg. Reps. Commission ($) | D21: ='FE Assumptions'!C48 -> 268280.33 | E21: ='FE Assumptions'!D48 -> 344232.76 | F21: ='FE Assumptions'!E48 -> 396844.43 | G21: ='FE Assumptions'!F48 -> 503401.33 | H21: ='FE Assumptions'!G48 -> 631633
A22: Manufacturing Reps Commission as percent of Sales (%) | C22: =C18+C12+C7 -> 434189.92 | D22: 0.1 | E22: =D22 -> 0.1 | F22: =E22 -> 0.1 | G22: =F22 -> 0.1 | H22: =G22 -> 0.1
A23: Annual Depreciation ($) | D23: ='OM Capital Expenditures'!E72 -> 12180.851 | E23: ='OM Capital Expenditures'!F72 -> 14263.03 | F23: ='OM Capital Expenditures'!G72 -> 18180.892 | G23: ='OM Capital Expenditures'!H72 -> 20182.206 | H23: ='OM Capital Expenditures'!I72 -> 23109.548
A24: State and Federal Income Tax Rate (%) | C24: ='FE Assumptions'!$B$70 -> 0.27 | D24: ='FE Assumptions'!$B$70 -> 0.27 | E24: ='FE Assumptions'!$B$70 -> 0.27 | F24: ='FE Assumptions'!$B$70 -> 0.27 | G24: ='FE Assumptions'!$B$70 -> 0.27 | H24: ='FE Assumptions'!$B$70 -> 0.27
A26: Discount Rate | C26: ='FE Assumptions'!B67 -> 0.2090185
A28: Terminal Value: Assumes Year 6 FCF is 2% higher than Year 5 and is a declining perpetuity thereafter.
B29: Perpetuity Decline Rate (%): | C29: -0.2

Sheet FE Income Statement
A2: INCOME STATEMENT
A3: *IN US DOLLARS ($) | B3: START-UP | C3: YEAR 1 | D3: YEAR 2 | E3: YEAR 3 | F3: YEAR 4 | G3: YEAR 5
A5: ONLINE REVENUE | C5: ='FE Assumptions'!C25*'FE Assumptions'!C32 -> 236096.69 | D5: ='FE Assumptions'!D25*'FE Assumptions'!D32 -> 835927.95 | E5: ='FE Assumptions'!E25*'FE Assumptions'!E32 -> 1346081.3 | F5: ='FE Assumptions'!F25*'FE Assumptions'!F32 -> 1653788.2 | G5: ='FE Assumptions'!G25*'FE Assumptions'!G32 -> 2278754.9
A6: INDEPENDENT RETAILER REVENUE | C6: ='FE Assumptions'!C24*'FE Assumptions'!C31 -> 1274922.1 | D6: ='FE Assumptions'!D24*'FE Assumptions'!D31 -> 1805604.4 | E6: ='FE Assumptions'!E24*'FE Assumptions'!E31 -> 1817209.8 | F6: ='FE Assumptions'!F24*'FE Assumptions'!F31 -> 2232614.1 | G6: ='FE Assumptions'!G24*'FE Assumptions'!G31 -> 2734505.8
A7: CHAIN RETAILER REVENUE | C7: ='FE Assumptions'!C26*'FE Assumptions'!C33 -> 0 | D7: ='FE Assumptions'!D26*'FE Assumptions'!D33 -> 0 | E7: ='FE Assumptions'!E26*'FE Assumptions'!E33 -> 272581.47 | F7: ='FE Assumptions'!F26*'FE Assumptions'!F33 -> 669784.24 | G7: ='FE Assumptions'!G26*'FE Assumptions'!G33 -> 1640703.5
A8: MASS MERCHANT REVENUE | C8: ='FE Assumptions'!C27*'FE Assumptions'!C34 -> 0 | D8: ='FE Assumptions'!D27*'FE Assumptions'!D34 -> 0 | E8: ='FE Assumptions'!E27*'FE Assumptions'!E34 -> 0 | F8: ='FE Assumptions'!F27*'FE Assumptions'!F34 -> 401870.54 | G8: ='FE Assumptions'!G27*'FE Assumptions'!G34 -> 656281.4
A9: TOTAL REVENUE | C9: ='MK Sales Projections'!C16*$I$10 -> 1629067.1 | D9: ='MK Sales Projections'!D16*$I$10 -> 2758562.2 | E9: ='MK Sales Projections'!E16*$I$10 -> 3503176.7 | F9: ='MK Sales Projections'!F16*$I$10 -> 5040746.6 | G9: ='MK Sales Projections'!G16*$I$10 -> 7386204.1 | I9: Total Revenue Sensitivity
A10: DIRECT MATERIALS COST | C10: =('OM Direct Materials & Direct La'!$F$33)*'FE Assumptions'!C28 -> 315897.37 | D10: ='OM Direct Materials & Direct La'!F51*'FE Assumptions'!D28 -> 543257.64 | E10: ='OM Direct Materials & Direct La'!F68*'FE Assumptions'!E28 -> 707558.04 | F10: ='OM Direct Materials & Direct La'!F85*'FE Assumptions'!F28 -> 1066870.6 | G10: ='OM Direct Materials & Direct La'!F102*'FE Assumptions'!G28 -> 1597081.6 | I10: 1
A11: PER UNIT | C11: =C10/'FE Assumptions'!C28 -> 6.69 | D11: =D10/'FE Assumptions'!D28 -> 6.69 | E11: =E10/'FE Assumptions'!E28 -> 6.69 | F11: =F10/'FE Assumptions'!F28 -> 6.69 | G11: =G10/'FE Assumptions'!G28 -> 6.69
A12: DIRECT LABOR COST | C12: =C13*'FE Assumptions'!C28 -> 133580.41 | D12: =D13*'FE Assumptions'!D28 -> 240778.69 | E12: =E13*'FE Assumptions'!E28 -> 354288.64 | F12: =F13*'FE Assumptions'!F28 -> 437900.76 | G12: =G13*'FE Assumptions'!G28 -> 638970.19
A13: PER UNIT | C13: ='OM Direct Materials & Direct La'!D14 -> 2.8289344 | D13: ='OM Direct Materials & Direct La'!E14 -> 2.965093 | E13: ='OM Direct Materials & Direct La'!F14 -> 3.3498185 | F13: ='OM Direct Materials & Direct La'!G14 -> 2.7459338 | G13: ='OM Direct Materials & Direct La'!H14 -> 2.6765761
A14: INBOUND FREIGHT COST | C14: =C15*'FE Assumptions'!C28 -> 31589.737 | D14: =D15*'FE Assumptions'!D28 -> 54325.764 | E14: =E15*'FE Assumptions'!E28 -> 70755.804 | F14: =F15*'FE Assumptions'!F28 -> 106687.06 | G14: =G15*'FE Assumptions'!G28 -> 159708.16
A15: PER UNIT | C15: ='OM Direct Materials & Direct La'!F34 -> 0.669 | D15: ='OM Direct Materials & Direct La'!F52 -> 0.669 | E15: ='OM Direct Materials & Direct La'!F69 -> 0.669 | F15: ='OM Direct Materials & Direct La'!F86 -> 0.669 | G15: ='OM Direct Materials & Direct La'!F103 -> 0.669
A16: OUTBOUND FREIGHT COST | C16: =C17*'FE Assumptions'!C28 -> 7254.9139 | D16: =D17*'FE Assumptions'!D28 -> 15413.413 | E16: =E17*'FE Assumptions'!E28 -> 22117.312 | F16: =F17*'FE Assumptions'!F28 -> 31571.436 | G16: =G17*'FE Assumptions'!G28 -> 46900.59
A17: PER UNIT | C17: ='OM Location Analysis '!C65 -> 0.15364286 | D17: ='OM Location Analysis '!D65 -> 0.18981 | E17: ='OM Location Analysis '!E65 -> 0.2091204 | F17: ='OM Location Analysis '!F65 -> 0.19797425 | G17: ='OM Location Analysis '!G65 -> 0.19646144
A18: MANUFACTURING OVERHEAD COST | C18: ='Starting Data Set'!D17 -> 192923.91 | D18: ='Starting Data Set'!E17 -> 248628.14 | E18: ='Starting Data Set'!F17 -> 290008.74 | F18: ='Starting Data Set'!G17 -> 376145.86 | G18: ='Starting Data Set'!H17 -> 501523.09
A19: PER UNIT | C19: =C18/'FE Assumptions'!C28 -> 4.085697 | D19: =D18/'FE Assumptions'!D28 -> 3.0617559 | E19: =E18/'FE Assumptions'!E28 -> 2.7420485 | F19: =F18/'FE Assumptions'!F28 -> 2.3586888 | G19: =G18/'FE Assumptions'!G28 -> 2.1008253
A20: TOTAL COST OF GOODS SOLD | C20: =C10+C12+C14+C16+C18 -> 681246.33 | D20: =D10+D12+D14+D16+D18 -> 1102403.6 | E20: =E10+E12+E14+E16+E18 -> 1444728.5 | F20: =F10+F12+F14+F16+F18 -> 2019175.7 | G20: =G10+G12+G14+G16+G18 -> 2944183.6
A21: PER UNIT | C21: =C20/'FE Assumptions'!$C$28 -> 14.427274 | D21: =D20/'FE Assumptions'!D28 -> 13.575659 | E21: =E20/'FE Assumptions'!E28 -> 13.659987 | F21: =F20/'FE Assumptions'!F28 -> 12.661597 | G21: =G20/'FE Assumptions'!G28 -> 12.332863
A22: GROSS PROFIT | C22: =C9-C20 -> 947820.81 | D22: =D9-D20 -> 1656158.6 | E22: =E9-E20 -> 2058448.1 | F22: =F9-F20 -> 3021570.9 | G22: =G9-G20 -> 4442020.4
A23: PER UNIT | C23: =C22/'FE Assumptions'!C28 -> 20.072726 | D23: =D22/'FE Assumptions'!D28 -> 20.394929 | E23: =E22/'FE Assumptions'!E28 -> 19.46274 | F23: =F22/'FE Assumptions'!F28 -> 18.947292 | G23: =G22/'FE Assumptions'!G28 -> 18.607137
A24: ONE-TIME START-UP EXPENSE | B24: ='Starting Data Set'!C18 -> 137604.34
A25: ADMINISTRATIVE OVERHEAD | C25: ='Starting Data Set'!D19 -> 628381.34 | D25: ='Starting Data Set'!E19 -> 668845.24 | E25: ='Starting Data Set'!F19 -> 849961.52 | F25: ='Starting Data Set'!G19 -> 1026543.7 | G25: ='Starting Data Set'!H19 -> 1381304.5
A26: PER UNIT | C26: =C25/'FE Assumptions'!C28 -> 13.307712 | D26: =D25/'FE Assumptions'!D28 -> 8.2365611 | E26: =E25/'FE Assumptions'!E28 -> 8.0364327 | F26: =F25/'FE Assumptions'!F28 -> 6.4371229 | G26: =G25/'FE Assumptions'!G28 -> 5.7861334
A27: GENERAL OPERATING EXPENSES (INFORMATION SYSTEMS) | C27: ='Starting Data Set'!D20 -> 34683.4 | D27: ='Starting Data Set'!E20 -> 35453.77 | E27: ='Starting Data Set'!F20 -> 37881.039 | F27: ='Starting Data Set'!G20 -> 46926.761 | G27: ='Starting Data Set'!H20 -> 49966.074
A28: PER UNIT | C28: =C27/'FE Assumptions'!C28 -> 0.73451687 | D28: =D27/'FE Assumptions'!D28 -> 0.43659897 | E28: =E27/'FE Assumptions'!E28 -> 0.35816729 | F28: =F27/'FE Assumptions'!F28 -> 0.29426252 | G28: =G27/'FE Assumptions'!G28 -> 0.20930241
A29: TOTAL GENERAL & ADMINISTRATIVE EXPENSES | C29: =C25+C27 -> 663064.74 | D29: =D25+D27 -> 704299.01 | E29: =E25+E27 -> 887842.56 | F29: =F25+F27 -> 1073470.4 | G29: =G25+G27 -> 1431270.6
A30: PER UNIT | C30: =C29/'FE Assumptions'!C28 -> 14.042229 | D30: =D29/'FE Assumptions'!D28 -> 8.67316 | E30: =E29/'FE Assumptions'!E28 -> 8.3946 | F30: =F29/'FE Assumptions'!F28 -> 6.7313854 | G30: =G29/'FE Assumptions'!G28 -> 5.9954358
A31: MARKETING EXPENSES (IMC SCHEDULE) | C31: ='Starting Data Set'!D21 -> 268280.33 | D31: ='Starting Data Set'!E21 -> 344232.76 | E31: ='Starting Data Set'!F21 -> 396844.43 | F31: ='Starting Data Set'!G21 -> 503401.33 | G31: ='Starting Data Set'!H21 -> 631633
A32: PER UNIT | C32: =C31/'FE Assumptions'!C28 -> 5.6815777 | D32: =D31/'FE Assumptions'!D28 -> 4.2390885 | E32: =E31/'FE Assumptions'!E28 -> 3.7521858 | F32: =F31/'FE Assumptions'!F28 -> 3.1566667 | G32: =G31/'FE Assumptions'!G28 -> 2.6458415
A33: MANUFACTURER'S SALES COMMISSION | C33: ='Starting Data Set'!D22*'FE Income Statement'!C9 -> 162906.71 | D33: ='Starting Data Set'!E22*'FE Income Statement'!D9 -> 275856.22 | E33: ='Starting Data Set'!F22*'FE Income Statement'!E9 -> 350317.67 | F33: ='Starting Data Set'!G22*'FE Income Statement'!F9 -> 504074.66 | G33: ='Starting Data Set'!H22*'FE Income Statement'!G9 -> 738620.41
A34: TOTAL SALES & MARKETING EXPENSE | C34: =C31+C33 -> 431187.05 | D34: =D31+D33 -> 620088.99 | E34: =E31+E33 -> 747162.1 | F34: =F31+F33 -> 1007476 | G34: =G31+G33 -> 1370253.4
A35: PER UNIT | C35: =C34/'FE Assumptions'!C28 -> 9.1315777 | D35: =D34/'FE Assumptions'!D28 -> 7.6361473 | E35: =E34/'FE Assumptions'!E28 -> 7.0644585 | F35: =F34/'FE Assumptions'!F28 -> 6.3175556 | G35: =G34/'FE Assumptions'!G28 -> 5.7398415
A36: DEPRECIATION | C36: ='Starting Data Set'!D23 -> 12180.851 | D36: ='Starting Data Set'!E23 -> 14263.03 | E36: ='Starting Data Set'!F23 -> 18180.892 | F36: ='Starting Data Set'!G23 -> 20182.206 | G36: ='Starting Data Set'!H23 -> 23109.548
A38: Earnings Before Tax | B38: =B22-B24 -> -137604.34 | C38: =C22-C29-C34-C36 -> -158611.84 | D38: =D22-D29-D34-D36 -> 317507.57 | E38: =E22-E29-E34-E36 -> 405262.6 | F38: =F22-F29-F34-F36 -> 920442.21 | G38: =G22-G29-G34-G36 -> 1617386.9
A39: TAXES | B39: =IF(B38>0,B38*'Starting Data Set'!C24,0) -> 0 | C39: =IF(C38>0,C38*'Starting Data Set'!D24,0) -> 0 | D39: =IF(D38>0,D38*'Starting Data Set'!E24,0) -> 85727.045 | E39: =IF(E38>0,E38*'Starting Data Set'!F24,0) -> 109420.9 | F39: =IF(F38>0,F38*'Starting Data Set'!G24,0) -> 248519.4 | G39: =IF(G38>0,G38*'Starting Data Set'!H24,0) -> 436694.45
A40: PER UNIT | C40: =C39/'FE Assumptions'!C28 -> 0 | D40: =D39/'FE Assumptions'!D28 -> 1.0556942 | E40: =E39/'FE Assumptions'!E28 -> 1.0345806 | F40: =F39/'FE Assumptions'!F28 -> 1.5583846 | G40: =G39/'FE Assumptions'!G28 -> 1.8292652
A42: NET INCOME | B42: =B38-B39 -> -137604.34 | C42: =C38-C39 -> -158611.84 | D42: =D38-D39 -> 231780.53 | E42: =E38-E39 -> 295841.7 | F42: =F38-F39 -> 671922.81 | G42: =G38-G39 -> 1180692.4
A43: PER UNIT | C43: =C42/'FE Assumptions'!C28 -> -3.3590441 | D43: =D42/'FE Assumptions'!D28 -> 2.8542843 | E43: =E42/'FE Assumptions'!E28 -> 2.7971994 | F43: =F42/'FE Assumptions'!F28 -> 4.2134103 | G43: =G42/'FE Assumptions'!G28 -> 4.9457912
C44: =C45-C20 -> 0 | D44: =D45-D20 -> 85727.045 | E44: =E45-E20 -> 109420.9 | F44: =F45-F20 -> 248519.4 | G44: =G45-G20 -> 436694.45
A45: Statement of Retained Earnings | C45: =C9-C29-C34-C42-C36 -> 681246.33 | D45: =D9-D29-D34-D42-D36 -> 1188130.7 | E45: =E9-E29-E34-E42-E36 -> 1554149.4 | F45: =F9-F29-F34-F42-F36 -> 2267695.1 | G45: =G9-G29-G34-G42-G36 -> 3380878.1
A46: NET INCOME | B46: =B42 -> -137604.34 | C46: =C42 -> -158611.84 | D46: =D42 -> 231780.53 | E46: =E42 -> 295841.7 | F46: =F42 -> 671922.81 | G46: =G42 -> 1180692.4
A47: Less cash returned to investors (Dividends) | B47: =IF('FE Cash Flow'!D11>0,'FE Cash Flow'!D11,0) -> 0 | C47: =IF('FE Cash Flow'!E11>0,'FE Cash Flow'!E11,0) -> 0 | D47: =IF('FE Cash Flow'!F11>0,'FE Cash Flow'!F11,0) -> 0 | E47: =IF('FE Cash Flow'!G11>0,'FE Cash Flow'!G11,0) -> 94205.519 | F47: =IF('FE Cash Flow'!H11>0,'FE Cash Flow'!H11,0) -> 303263.15 | G47: =IF('FE Cash Flow'!I11>0,'FE Cash Flow'!I11,0) -> 655417.94
A48: Increase (Decrease) in Retained Earnings | B48: =B46-B47 -> -137604.34 | C48: =C46-C47 -> -158611.84 | D48: =D46-D47 -> 231780.53 | E48: =E46-E47 -> 201636.18 | F48: =F46-F47 -> 368659.66 | G48: =G46-G47 -> 525274.47
A50: Income Statement Financial Ratios - To be Calculated
A51: COGS % Sales | C51: =C20/C9 -> 0.41818186 | D51: =D20/D9 -> 0.39962979 | E51: =E20/E9 -> 0.41240527 | F51: =F20/F9 -> 0.40057077 | G51: =G20/G9 -> 0.39860578
A52: Gross Margin % Sales | C52: =C22/C9 -> 0.58181814 | D52: =D22/D9 -> 0.60037021 | E52: =E22/E9 -> 0.58759473 | F52: =F22/F9 -> 0.59942923 | G52: =G22/G9 -> 0.60139422
A53: SG&A % Sales | C53: =(C25+C27)/C9 -> 0.40702113 | D53: =(D25+D27)/D9 -> 0.2553138 | E53: =(E25+E27)/E9 -> 0.25343928 | F53: =(F25+F27)/F9 -> 0.21295862 | G53: =(G25+G27)/G9 -> 0.19377621
A54: Marketing Expenses % Sales | C54: =(SUM(C31:C33)/C9) -> 0.2646869 | D54: =(SUM(D31:D33)/D9) -> 0.22478856 | E54: =(SUM(E31:E33)/E9) -> 0.21328238 | F54: =(SUM(F31:F33)/F9) -> 0.19986705 | G54: =(SUM(G31:G33)/G9) -> 0.1855156
A55: Net Income % Sales | C55: =C42/C9 -> -0.097363597 | D55: =D42/D9 -> 0.084022222 | E55: =E42/E9 -> 0.084449551 | F55: =F42/F9 -> 0.13329827 | G55: =G42/G9 -> 0.15985104
C57: =C9/1000 -> 1629.0671 | D57: =D9/1000 -> 2758.5622 | E57: =E9/1000 -> 3503.1767 | F57: =F9/1000 -> 5040.7466 | G57: =G9/1000 -> 7386.2041
D58: =D57/C57-1 -> 0.69333859 | E58: =E57/D57-1 -> 0.26992845 | F58: =F57/E57-1 -> 0.43890732 | G58: =G57/F57-1 -> 0.46529963 | H58: =average(D58:G58) -> 0.4668685
D59: 1 | E59: =C53 -> 0.40702113
D60: 2 | E60: =D53 -> 0.2553138
D61: 3 | E61: =E53 -> 0.25343928
D62: 4 | E62: =F53 -> 0.21295862
D63: 5 | E63: =G53 -> 0.19377621

Sheet FE Balance Sheet
B2: BALANCE SHEET
B3: *IN US DOLLARS ($) | C3: START-UP | D3: YEAR 1 | E3: YEAR 2 | F3: YEAR 3 | G3: YEAR 4 | H3: YEAR 5 | I3: Comments For Future Buildout
B4: Current Assets
B5: Cash reserves | C5: ='Starting Data Set'!C9 -> 0 | D5: ='Starting Data Set'!D9*'FE Income Statement'!C9 -> 81453.357 | E5: ='Starting Data Set'!E9*'FE Income Statement'!D9 -> 137928.11 | F5: ='Starting Data Set'!F9*'FE Income Statement'!E9 -> 175158.83 | G5: ='Starting Data Set'!G9*'FE Income Statement'!F9 -> 252037.33 | H5: ='Starting Data Set'!H9*'FE Income Statement'!G9 -> 369310.2 | I5: FE assumptions
B6: Accounts Receivable | D6: =('Starting Data Set'!D10/365)*'FE Income Statement'!C9 -> 200843.89 | E6: =('Starting Data Set'!E10/365)*'FE Income Statement'!D9 -> 340096.72 | F6: =('Starting Data Set'!F10/365)*'FE Income Statement'!E9 -> 431898.49 | G6: =('Starting Data Set'!G10/365)*'FE Income Statement'!F9 -> 621461.91 | H6: =('Starting Data Set'!H10/365)*'FE Income Statement'!G9 -> 910627.9 | I6: FE assumptions
B8: Raw Materials & Work in Process Inventory | D8: ='FE Assumptions'!C60 -> 92355.69 | E8: ='FE Assumptions'!D60 -> 127815.22 | F8: ='FE Assumptions'!E60 -> 160107.99 | G8: ='FE Assumptions'!F60 -> 210899.58 | H8: ='FE Assumptions'!G60 -> 268129.3
B9: Finished Goods Inventory | D9: ='FE Assumptions'!C61 -> 28099.493 | E9: ='FE Assumptions'!D61 -> 45471.047 | F9: ='FE Assumptions'!E61 -> 68815.421 | G9: ='FE Assumptions'!F61 -> 96177.534 | H9: ='FE Assumptions'!G61 -> 140237.58
B10: Total Inventory | C10: ='Starting Data Set'!C12 -> 32663.334 | D10: =SUM(D8:D9) -> 120455.18 | E10: =SUM(E8:E9) -> 173286.27 | F10: =SUM(F8:F9) -> 228923.41 | G10: =SUM(G8:G9) -> 307077.12 | H10: =SUM(H8:H9) -> 408366.89 | I10: OM worksheets. By the end of the semester you must separate this line into FPI and RM+WIP
B11: Current Assets | C11: =SUM(C5:C10) -> 32663.334 | D11: =SUM(D5:D10) -> 523207.62 | E11: =SUM(E5:E10) -> 824597.37 | F11: =SUM(F5:F10) -> 1064904.1 | G11: =SUM(G5:G10) -> 1487653.5 | H11: =SUM(H5:H10) -> 2096671.9
B12: Fixed Assets
B13: Gross Fixed Assets | C13: ='Starting Data Set'!C7 -> 263922.25 | D13: =C13+'Starting Data Set'!D7 -> 272214.45 | E13: =D13+'Starting Data Set'!E7 -> 287228.14 | F13: =E13+'Starting Data Set'!F7 -> 294874.71 | G13: =F13+'Starting Data Set'!G7 -> 308182.1 | H13: =G13+'Starting Data Set'!H7 -> 323575.76 | I13: OM asset schedule
B14: Accumulated Depreciation (cumulative) | D14: ='Starting Data Set'!D23 -> 12180.851 | E14: =D14+'Starting Data Set'!E23 -> 26443.882 | F14: =E14+'Starting Data Set'!F23 -> 44624.773 | G14: =F14+'Starting Data Set'!G23 -> 64806.979 | H14: =G14+'Starting Data Set'!H23 -> 87916.527 | I14: FE Income Statement
B15: Net Fixed Assets | C15: =C13-C14 -> 263922.25 | D15: =D13-D14 -> 260033.6 | E15: =E13-E14 -> 260784.25 | F15: =F13-F14 -> 250249.94 | G15: =G13-G14 -> 243375.12 | H15: =H13-H14 -> 235659.24
B17: TOTAL ASSETS | C17: =C11+C15 -> 296585.58 | D17: =D11+D15 -> 783241.21 | E17: =E11+E15 -> 1085381.6 | F17: =F11+F15 -> 1315154.1 | G17: =G11+G15 -> 1731028.6 | H17: =H11+H15 -> 2332331.1
B19: Current Liabilities
B20: Accounts Payable | D20: ='Starting Data Set'!D11*'FE Income Statement'!C20*(1/365) -> 55992.849 | E20: ='Starting Data Set'!E11*'FE Income Statement'!D20*(1/365) -> 90608.518 | F20: ='Starting Data Set'!F11*'FE Income Statement'!E20*(1/365) -> 118744.81 | G20: ='Starting Data Set'!G11*'FE Income Statement'!F20*(1/365) -> 165959.65 | H20: ='Starting Data Set'!H11*'FE Income Statement'!G20*(1/365) -> 241987.7 | I20: FE assumptions
B21: Current Liabilities | C21: =C20 | D21: =D20 -> 55992.849 | E21: =E20 -> 90608.518 | F21: =F20 -> 118744.81 | G21: =G20 -> 165959.65 | H21: =H20 -> 241987.7
B22: Equity
B23: Paid in Capital (cumulative) | C23: =IF('FE Cash Flow'!D15<0,'FE Cash Flow'!D15,0)*-1 -> 434189.92 | D23: =C23+IF('FE Cash Flow'!E15<0,'FE Cash Flow'!E15,0)*-1 -> 1023464.5 | E23: =D23+IF('FE Cash Flow'!F15<0,'FE Cash Flow'!F15,0)*-1 -> 1059208.7 | F23: =E23+IF('FE Cash Flow'!G15<0,'FE Cash Flow'!G15,0)*-1 -> 1059208.7 | G23: =F23+IF('FE Cash Flow'!H15<0,'FE Cash Flow'!H15,0)*-1 -> 1059208.7 | H23: =G23+IF('FE Cash Flow'!I15<0,'FE Cash Flow'!I15,0)*-1 -> 1059208.7 | I23: See FE Cash Flow Tab for any year with Negative FCF
B24: Retained Earnings (cumulative) | C24: ='FE Income Statement'!B48 -> -137604.34 | D24: =C24+'FE Income Statement'!C46-'FE Income Statement'!C47 -> -296216.17 | E24: =D24+'FE Income Statement'!D46-'FE Income Statement'!D47 -> -64435.644 | F24: =E24+'FE Income Statement'!E46-'FE Income Statement'!E47 -> 137200.53 | G24: =F24+'FE Income Statement'!F46-'FE Income Statement'!F47 -> 505860.2 | H24: =G24+'FE Income Statement'!G46-'FE Income Statement'!G47 -> 1031134.7 | I24: See FE Income Statement Tab for changes in Retained Earnings
B25: Total Equity | C25: =C23+C24 -> 296585.58 | D25: =D23+D24 -> 727248.37 | E25: =E23+E24 -> 994773.1 | F25: =F23+F24 -> 1196409.3 | G25: =G23+G24 -> 1565068.9 | H25: =H23+H24 -> 2090343.4
B27: TOTAL LIABILTIES AND EQUITY | C27: =C25+C21 -> 296585.58 | D27: =D25+D21 -> 783241.21 | E27: =E25+E21 -> 1085381.6 | F27: =F25+F21 -> 1315154.1 | G27: =G25+G21 -> 1731028.6 | H27: =H25+H21 -> 2332331.1
B30: Check Total Assets - Total Liabilities & Equity | C30: =C17-C27 -> 0 | D30: =D17-D27 -> 0 | E30: =E17-E27 -> 0 | F30: =F17-F27 -> 0 | G30: =G17-G27 -> -2.3283064e-10 | H30: =H17-H27 -> -4.6566129e-10 | I30: <<Do not delete or hide this line - you may move.
B32: NET WORKING CAPITAL BALANCE | C32: =C11-C21 -> 32663.334 | D32: =D11-D21 -> 467214.77 | E32: =E11-E21 -> 733988.85 | F32: =F11-F21 -> 946159.34 | G32: =G11-G21 -> 1321693.8 | H32: =H11-H21 -> 1854684.2 | I32: link to FE Cash Flow schedule
B34: BALANCE SHEET FINANCIAL RATIOS
B35: DAYS SALES OUTSTANDING (ONLINE) | D35: 5 | E35: 5 | F35: 5 | G35: 5 | H35: 5
B36: DAYS SALES OUTSTANDING (ALL OTHER RETAIL) | D36: =(D6/'FE Income Statement'!C9)*365 -> 45 | E36: =(E6/'FE Income Statement'!D9)*365 -> 45 | F36: =(F6/'FE Income Statement'!E9)*365 -> 45 | G36: =(G6/'FE Income Statement'!F9)*365 -> 45 | H36: =(H6/'FE Income Statement'!G9)*365 -> 45 | I36: These should be calculated Outputs
B37: DAYS INVENTORY OUTSTANDING | D37: =(D10/'FE Income Statement'!C20)*365 -> 64.537804 | E37: =(E10/'FE Income Statement'!D20)*365 -> 57.374165 | F37: =(F10/'FE Income Statement'!E20)*365 -> 57.83581 | G37: =(G10/'FE Income Statement'!F20)*365 -> 55.509358 | H37: =(H10/'FE Income Statement'!G20)*365 -> 50.626568 | I37: These should be calculated Outputs
B38: DAYS PAYABLE OUTSTANDING | D38: ='Starting Data Set'!D11 -> 30 | E38: ='Starting Data Set'!E11 -> 30 | F38: ='Starting Data Set'!F11 -> 30 | G38: ='Starting Data Set'!G11 -> 30 | H38: ='Starting Data Set'!H11 -> 30

Sheet FE Comparable Companies Analysi
B2: COMPS ANALYSIS
B4: COMPANY INFO | E4: VALUATION METRICS | H4: OPERATING METRICS | L4: MARGINS | O4: MULTIPLES & VALUATION | S4: WORKING CAPITAL RATIOS | W4: RETURN METRICS
B5: NAME | C5: TICKER | D5: WEIGHT | E5: ENTERPRISE VALUE | F5: EQUITY VALUE | G5: BETA | H5: REVENUE | I5: GROSS PROFIT | J5: EBITDA | K5: NET INCOME | L5: GROSS MARGIN | M5: EBITDA MARGIN | N5: NET MARGIN | O5: EV/REVENUE | P5: EV/EBITDA | Q5: P/E | R5: WACC | S5: DSO | T5: DIO | U5: DPO | V5: CCC | W5: ROE | X5: ROA | Y5: ROIC
B6: XPLORA | C6: XPLRA | D6: 0.1 | E6: 2772 | F6: 2180 | G6: 0.18 | H6: 754.5 | I6: 376.4 | J6: =E6/P6 -> 10.051855 | K6: -5.51 | L6: =I6/H6 -> 0.49887343 | M6: =J6/H6 -> 0.013322538 | N6: =K6/H6 -> -0.0073028496 | O6: =E6/H6 -> 3.6739563 | P6: 275.77 | Q6: 0 | R6: 0.0657 | S6: 17.86 | T6: 85.69 | U6: 52.4 | V6: =S6+T6-U6 -> 51.15 | W6: -0.0176 | X6: -0.0107 | Y6: -0.0118
B7: MIPS | C7: MIPS AB | D7: 0.3 | E7: =H7*O7 -> 7384.839 | F7: =I7*P7 -> 16682.685 | G7: 1.9 | H7: 456.7 | I7: 330.94 | J7: 18.627 | K7: 13.332 | L7: =I7/H7 -> 0.72463324 | M7: =J7/H7 -> 0.040786074 | N7: =K7/H7 -> 0.02919203 | O7: 16.17 | P7: 50.41 | Q7: 64.47 | R7: 0.117 | S7: 94.65 | T7: 16.52 | U7: 107.76 | V7: =S7+T7-U7 -> 3.41 | W7: 0.2249 | X7: 0.1968 | Y7: 0.2073
B8: RIDEFOX | C8: FOXF | D8: 0.35 | E8: 1230 | F8: 590.24 | G8: 1.5 | H8: =$E$8/O8 -> 1464.2857 | I8: 423.576 | J8: =E8/P8 -> 173.72881 | K8: 6.512 | L8: =I8/H8 -> 0.28927141 | M8: =J8/H8 -> 0.11864407 | N8: =K8/H8 -> 0.0044472195 | O8: 0.84 | P8: 7.08 | Q8: 11.97 | R8: 0.1054 | S8: 44.64 | T8: 143.87 | U8: 51.64 | V8: =S8+T8-U8 -> 136.87 | W8: 0.0054 | X8: 0.0029 | Y8: 0.0254
B9: THULE GROUP | C9: THULE | D9: 0.25 | E9: 3036 | F9: 2679 | G9: 1.37 | H9: 902.142 | I9: 385.214 | J9: 171.427 | K9: 106.09 | L9: =I9/H9 -> 0.4269993 | M9: =J9/H9 -> 0.19002219 | N9: =K9/H9 -> 0.11759789 | O9: =$E$9/H9 -> 3.3653239 | P9: =E9/J9 -> 17.710162 | Q9: 25.45 | R9: 0.0977 | S9: 39.23 | T9: 137.02 | U9: 56.49 | V9: =S9+T9-U9 -> 119.76 | W9: 0.152 | X9: 0.0908 | Y9: 0.12
B10: MEAN | E10: =AVERAGE(E6:E9) -> 3605.7097 | F10: =AVERAGE(F6:F9) -> 5532.9814 | G10: =AVERAGE(G6:G9) -> 1.2375 | H10: =AVERAGE(H6:H9) -> 894.40693 | I10: =AVERAGE(I6:I9) -> 379.0325 | J10: =AVERAGE(J6:J9) -> 93.458667 | K10: =AVERAGE(K6:K9) -> 30.106 | L10: =AVERAGE(L6:L9) -> 0.48494434 | ... Y10: =AVERAGE(Y6:Y9) -> 0.085225
B11: MEDIAN | E11: =MEDIAN(E6:E9) -> 2904 | F11: =MEDIAN(F6:F9) -> 2429.5 | G11: =MEDIAN(G6:G9) -> 1.435 | H11: =MEDIAN(H6:H9) -> 828.321 | I11: =MEDIAN(I6:I9) -> 380.807 | J11: =MEDIAN(J6:J9) -> 95.027 | K11: =MEDIAN(K6:K9) -> 9.922 | L11: =MEDIAN(L6:L9) -> 0.46293636 | ... Y11: =MEDIAN(Y6:Y9) -> 0.0727
B12: WEIGHTED AVERAGE | E12: =SUMPRODUCT($D$6:$D$9,E6:E9) -> 3682.1517 | F12: =SUMPRODUCT($D$6:$D$9,F6:F9) -> 6099.1396 | G12: =SUMPRODUCT($D$6:$D$9,G6:G9) -> 1.4555 | H12: =SUMPRODUCT($D$6:$D$9,H6:H9) -> 950.4955 | I12: =SUMPRODUCT($D$6:$D$9,I6:I9) -> 381.4771 | J12: =SUMPRODUCT($D$6:$D$9,J6:J9) -> 110.25512 | K12: =SUMPRODUCT($D$6:$D$9,K6:K9) -> 32.2503 | L12: =SUMPRODUCT($D$6:$D$9,L6:L9) -> 0.47527213 | ... Y12: =SUMPRODUCT($D$6:$D$9,Y6:Y9) -> 0.0999
B14: CAPITAL ASSET PRICING MODEL
B16: COMPARABLE BETA | C16: =G12 -> 1.4555
B17: RISK-FREE RATE | C17: 0.0415
B18: EQUITY RISK PREMIUM | C18: 0.067
B19: SMALL-CAP PREMIUM | C19: 0.07
B20: COST OF EQUITY | C20: =(C17+(C16*C18))+C19 -> 0.2090185

Sheet FE Cash Flow
B2: STATEMENT OF CASH FLOWS
B3: *IN US DOLLARS ($) | D3: START-UP | E3: YEAR 1 | F3: YEAR 2 | G3: YEAR 3 | H3: YEAR 4 | I3: YEAR 5 | J3: Notes
B6: NET INCOME | D6: ='FE Income Statement'!B42 -> -137604.34 | E6: ='FE Income Statement'!C42 -> -158611.84 | F6: ='FE Income Statement'!D42 -> 231780.53 | G6: ='FE Income Statement'!E42 -> 295841.7 | H6: ='FE Income Statement'!F42 -> 671922.81 | I6: ='FE Income Statement'!G42 -> 1180692.4 | J6: Income Statement
B7: ADD BACK DEPRECIATION | D7: ='FE Income Statement'!B36 | E7: ='FE Income Statement'!C36 -> 12180.851 | F7: ='FE Income Statement'!D36 -> 14263.03 | G7: ='FE Income Statement'!E36 -> 18180.892 | H7: ='FE Income Statement'!F36 -> 20182.206 | I7: ='FE Income Statement'!G36 -> 23109.548 | J7: Income Statement
B8: (-) CHANGE IN FIXED ASSETS | D8: ='Starting Data Set'!C7 -> 263922.25 | E8: ='Starting Data Set'!D7 -> 8292.1994 | F8: ='Starting Data Set'!E7 -> 15013.686 | G8: ='Starting Data Set'!F7 -> 7646.5788 | H8: ='Starting Data Set'!G7 -> 13307.389 | I8: ='Starting Data Set'!H7 -> 15393.662 | J8: OM asset planning, FE Balance Sheet
B9: (+/-) CASH IMPACT OF THE CHANGE IN NWC | D9: ='FE Balance Sheet'!C32 -> 32663.334 | E9: ='FE Balance Sheet'!D32-'FE Balance Sheet'!C32 -> 434551.43 | F9: ='FE Balance Sheet'!E32-'FE Balance Sheet'!D32 -> 266774.08 | G9: ='FE Balance Sheet'!F32-'FE Balance Sheet'!E32 -> 212170.49 | H9: ='FE Balance Sheet'!G32-'FE Balance Sheet'!F32 -> 375534.48 | I9: ='FE Balance Sheet'!H32-'FE Balance Sheet'!G32 -> 532990.36 | J9: Balance Sheet
B11: NET FREE CASH FLOW | D11: =D6+D7-D8-D9 -> -434189.92 | E11: =E6+E7-E8-E9 -> -589274.62 | F11: =F6+F7-F8-F9 -> -35744.206 | G11: =G6+G7-G8-G9 -> 94205.519 | H11: =H6+H7-H8-H9 -> 303263.15 | I11: =I6+I7-I8-I9 -> 655417.94 | J11: Cash Flow: If positive, treat as a dividend,
K12: if negative, treat as additional paid-in capital.
B13: TERMINAL VALUE OF BUSINESS | H13: Terminal Value | I13: =(I11*(1.05^2))/('Starting Data Set'!C26-'Starting Data Set'!C29) -> 1766664 | J13: See Note on Terminal Value on "Starting Data Set" Tab
B15: TOTAL CASH FLOW | D15: =D11 -> -434189.92 | E15: =E11 -> -589274.62 | F15: =F11 -> -35744.206 | G15: =G11 -> 94205.519 | H15: =H11 -> 303263.15 | I15: =I11+I13 -> 2422082 | J15: =I11*(1.02) -> 668526.3 | K15: =J15*(1.02) -> 681896.82
B17: CASH BREAKEVEN? | D17: =IF(D15<0,"NO","YES") -> NO | E17: =IF(E15<0,"NO","YES") -> NO | F17: =IF(F15<0,"NO","YES") -> NO | G17: =IF(G15<0,"NO","YES") -> YES | H17: =IF(H15<0,"NO","YES") -> YES | I17: =IF(I15<0,"NO","YES") -> YES
B18: YEAR | D18: 0 | E18: =IF(E15<0,D18+1,D18+ABS(E15/D15)) -> 1 | F18: =IF(F15<0,E18+1,E18+ABS(F15/E15)) -> 2 | G18: =IF(G15<0,F18+1,(ABS(F15/G15)+F18)) -> 2.3794279 | H18: =G18 -> 2.3794279 | I18: =H18 -> 2.3794279
B20: PAYBACK PERIOD | D20: =D11 -> -434189.92 | E20: =D20+E15 -> -1023464.5 | F20: =E20+F15 -> -1059208.7 | G20: =F20+G15 -> -965003.23 | H20: =G20+H15 -> -661740.08 | I20: =H20+I15 -> 1760341.9
B21: YEAR | D21: 0 | E21: 1 | F21: 2 | G21: 3 | H21: 4 | I21: =H21+(ABS(H20)/I20) -> 4.3759157
B24: NET PRESENT VALUE (INCLUDING TV) | D24: {=NPV('Starting Data Set'!C26,'FE Cash Flow'!E15:I15)+D15} -> 186812.16 | J24: (requires Total cash-flows and a discount rate)
B26: INTERNAL RATE OF RETURN (INCLUDING TV) | D26: =IRR(D15:I15) -> 0.26183911 | J26: (requires Total cash-flows)

Sheet MK Assumptions
B2: MARKETING ASSUMPTIONS | E2: YEAR 1 | G2: ACV | H2: % of Sales | K2: Influencer Type | L2: Following Lower bound | M2: Following Upper Bound | N2: Payment Lower Bound | O2: Payment Upper Bound
E3: Online | G3: 0.12 | H3: =G3/G5 -> 0.85714286 | K3: nano | L3: 0 | M3: 15000 | N3: 500 | O3: 2000
B4: SEGMENT ASSUMPTIONS | E4: Independent | G4: 0.02 | H4: =G4/G5 -> 0.14285714 | K4: micro | L4: 15000 | M4: 75000 | N4: 1000 | O4: 8000
B5: Segment Size | C5: 13412762 | E5: Total ACV | G5: =C9 -> 0.14 | H5: =SUM(H3:H4) -> 1 | K5: Mid-Tier | L5: 75000 | M5: 250000 | N5: 5000 | O5: 20000
B6: Segment Growth Rate | C6: 0.0125 | K6: macro | L6: 250000 | M6: 1000000 | N6: 20000 | O6: 45000
E7: YEAR 2 | G7: ACV | H7: % of Sales | K7: mega | L7: 1000000 | M7: 1000000000 | N7: 45000 | O7: 50000000
B8: ACV GUIDELINES | E8: Online | G8: 0.12 | H8: =G8/G10 -> 0.70588235
B9: Year 1 | C9: 0.14 | E9: Independent | G9: =G10-G8 -> 0.05 | H9: =G9/G10 -> 0.29411765
B10: Year 2 | C10: 0.17 | E10: Total ACV | G10: =C10 -> 0.17 | H10: =SUM(H8:H9) -> 1
B11: Year 3 | C11: 0.22
B12: Year 4 | C12: 0.27 | E12: YEAR 3 | G12: ACV | H12: % of Sales
B13: Year 5 | C13: 0.33 | E13: Online | G13: 0.12 | H13: =G13/$G$16 -> 0.54545455
E14: Independent | G14: 0.08 | H14: =G14/$G$16 -> 0.36363636
B15: RETAILER MARGINS | E15: Chain | G15: =G16-G14-G13 -> 0.02 | H15: =G15/$G$16 -> 0.090909091
B16: Online | C16: 0.5 | E16: Total ACV | G16: =C11 -> 0.22 | H16: =SUM(H13:H15) -> 1
B17: Independent Retailer | C17: 0.45
B18: Chain Retailer | C18: 0.45 | E18: YEAR 4 | G18: ACV | H18: % of Sales
B19: Mass Merchant | C19: 0.4 | E19: Online | G19: 0.12 | H19: =G19/$G$23 -> 0.44444444
E20: Independent | G20: 0.08 | H20: =G20/$G$23 -> 0.2962963
B21: UNITS LOST TO COMPETITION | E21: Chain | G21: =G23-G22-G20-G19 -> 0.04 | H21: =G21/$G$23 -> 0.14814815
B22: Year 1 | C22: 0 | E22: Mass Merchant | G22: 0.03 | H22: =G22/$G$23 -> 0.11111111
B23: Year 2 | C23: 0 | E23: Total ACV | G23: =C12 -> 0.27 | H23: =SUM(H19:H22) -> 1
B24: Year 3 | C24: 0.2
B25: Year 4 | C25: 0.3 | E25: YEAR 5 | G25: ACV | H25: % of Sales
B26: Year 5 | C26: 0.35 | E26: Online | G26: 0.12 | H26: =G26/$G$30 -> 0.36363636
E27: Independent | G27: 0.09 | H27: =G27/$G$30 -> 0.27272727
B28: DISTRIBUTION | C28: RETAIL SELLING PRICE | E28: Chain | G28: =G30-G29-G27-G26 -> 0.08 | H28: =G28/$G$30 -> 0.24242424
B29: Online | C29: 70 | E29: Mass Merchant | G29: 0.04 | H29: =G29/$G$30 -> 0.12121212
B30: Independent | C30: 70 | E30: Total ACV | G30: =C13 -> 0.33 | H30: =SUM(H26:H29) -> 1
B31: Chain | C31: =C30*(1-0.1) -> 63
B32: Mass Merchant | C32: =C31*(1-0.1) -> 56.7

Sheet MK ACV Distribution
B2: RETAILER DISTRIBUTION (ACV)
J3: ACV Sensitivity
B4: YEAR 1 TOTAL ACV | C4: ='MK Assumptions'!C9*J4 -> 0.14 | J4: 1
C5: ONLINE | D5: INDEPENDENT RETAILER | E5: CHAIN RETAILER | F5: MASS MERCHANT
B6: % OF ACV | C6: ='MK Assumptions'!G3 -> 0.12 | D6: ='MK Assumptions'!G4 -> 0.02
B7: % OF SALES | C7: ='MK Assumptions'!H3 -> 0.85714286 | D7: ='MK Assumptions'!H4 -> 0.14285714 | H7: TOTAL UNITS | J7: ERROR CHECK
B8: YEAR 1 UNITS | C8: ='MK Sales Projections'!C14*'MK ACV Distribution'!C7 -> 40473.718 | D8: =D7*'MK Sales Projections'!C14 -> 6745.6196 | H8: =SUM(C8:F8) -> 47219.337 | J8: ='MK Sales Projections'!C14 -> 47219.337
B11: YEAR 2 TOTAL ACV | C11: ='MK Assumptions'!C10*J4 -> 0.17
C12: ONLINE | D12: INDEPENDENT RETAILER | E12: CHAIN RETAILER | F12: MASS MERCHANT
B13: % OF ACV | C13: ='MK Assumptions'!G8 -> 0.12 | D13: ='MK Assumptions'!G9 -> 0.05
B14: % OF SALES | C14: ='MK Assumptions'!H8 -> 0.70588235 | D14: ='MK Assumptions'!H9 -> 0.29411765 | H14: TOTAL UNITS | J14: ERROR CHECK
B15: YEAR 1 UNITS | C15: =C14*'MK Sales Projections'!$D$14 -> 57320.774 | D15: =D14*'MK Sales Projections'!$D$14 -> 23883.656 | H15: =SUM(C15:F15) -> 81204.43 | J15: ='MK Sales Projections'!D14 -> 81204.43
B18: YEAR 3 TOTAL ACV | C18: ='MK Assumptions'!C11*J4 -> 0.22
C19: ONLINE | D19: INDEPENDENT RETAILER | E19: CHAIN RETAILER | F19: MASS MERCHANT
B20: % OF ACV | C20: ='MK Assumptions'!G13 -> 0.12 | D20: ='MK Assumptions'!G14 -> 0.08 | E20: ='MK Assumptions'!G15 -> 0.02
B21: % OF SALES | C21: ='MK Assumptions'!H13 -> 0.54545455 | D21: ='MK Assumptions'!H14 -> 0.36363636 | E21: ='MK Assumptions'!H15 -> 0.090909091 | H21: TOTAL UNITS | J21: ERROR CHECK
B22: YEAR 1 UNITS | C22: =C21*'MK Sales Projections'!$E$14 -> 57689.2 | D22: =D21*'MK Sales Projections'!$E$14 -> 38459.467 | E22: =E21*'MK Sales Projections'!$E$14 -> 9614.8667 | H22: =SUM(C22:F22) -> 105763.53 | J22: ='MK Sales Projections'!E14 -> 105763.53
B25: YEAR 4 TOTAL ACV | C25: ='MK Assumptions'!C12*J4 -> 0.27
C26: ONLINE | D26: INDEPENDENT RETAILER | E26: CHAIN RETAILER | F26: MASS MERCHANT
B27: % OF ACV | C27: ='MK Assumptions'!G19 -> 0.12 | D27: ='MK Assumptions'!G20 -> 0.08 | E27: ='MK Assumptions'!G21 -> 0.04 | F27: ='MK Assumptions'!G22 -> 0.03
B28: % OF SALES | C28: ='MK Assumptions'!H19 -> 0.44444444 | D28: ='MK Assumptions'!H20 -> 0.2962963 | E28: ='MK Assumptions'!H21 -> 0.14814815 | F28: ='MK Assumptions'!H22 -> 0.11111111 | H28: TOTAL UNITS | J28: ERROR CHECK
B29: YEAR 1 UNITS | C29: =C28*'MK Sales Projections'!$F$14 -> 70876.639 | D29: =D28*'MK Sales Projections'!$F$14 -> 47251.093 | E29: =E28*'MK Sales Projections'!$F$14 -> 23625.546 | F29: =F28*'MK Sales Projections'!$F$14 -> 17719.16 | H29: =SUM(C29:F29) -> 159472.44 | J29: ='MK Sales Projections'!F14 -> 159472.44
B32: YEAR 5 TOTAL ACV | C32: ='MK Assumptions'!C26*J4 -> 0.35
C33: ONLINE | D33: INDEPENDENT RETAILER | E33: CHAIN RETAILER | F33: MASS MERCHANT
B34: % OF ACV | C34: ='MK Assumptions'!G26 -> 0.12 | D34: ='MK Assumptions'!G27 -> 0.09 | E34: ='MK Assumptions'!G28 -> 0.08 | F34: ='MK Assumptions'!G29 -> 0.04
B35: % OF SALES | C35: ='MK Assumptions'!H26 -> 0.36363636 | D35: ='MK Assumptions'!H27 -> 0.27272727 | E35: ='MK Assumptions'!H28 -> 0.24242424 | F35: ='MK Assumptions'!H29 -> 0.12121212 | H35: TOTAL UNITS | J35: ERROR CHECK
B36: YEAR 1 UNITS | C36: =C35*'MK Sales Projections'!$G$14 -> 86809.709 | D36: =D35*'MK Sales Projections'!$G$14 -> 65107.282 | E36: =E35*'MK Sales Projections'!$G$14 -> 57873.139 | F36: =F35*'MK Sales Projections'!$G$14 -> 28936.57 | H36: =SUM(C36:F36) -> 238726.7 | J36: ='MK Sales Projections'!G14 -> 238726.7

Sheet MK Demand Curve & Purchase Inte
B2: PURCHASE INTENT
B4: PIVOT TABLE FOR PURCHASE INTENT
B5: PURCHASE INTENT | C5: 55 | D5: 60 | E5: 70 | F5: 80 | G5: 85 | H5: GRAND TOTAL
B6: DEFINITELY BUY | C6: 10 | D6: 9 | E6: 6 | F6: 9 | G6: 9 | H6: 43
B7: PROBABLY BUY | C7: 7 | D7: 8 | E7: 6 | F7: 9 | G7: 5 | H7: 35
B8: MAYBE BUY | C8: 3 | D8: 6 | E8: 6 | F8: 3 | G8: 4 | H8: 22
B9: PROBABLY NOT BUY | C9: 1 | D9: 1 | E9: 3 | F9: 2 | G9: 5 | H9: 12
B10: DEFINITELY NOT BUY | C10: 1 | D10: 1 | E10: 3 | F10: 1 | G10: 1 | H10: 7
B11: GRAND TOTAL | C11: 22 | D11: 25 | E11: 24 | F11: 24 | G11: 24 | H11: 119
B13: CUMULATIVE PURCHASE INTENT
B14: PURCHASE INTENT | C14: 55 | D14: 60 | E14: 70 | F14: 80 | G14: 85
B15: CUMULATIVE NUMBER AT PROBABLY BUY | C15: 35 | D15: 28 | E15: 20 | F15: 14 | G15: 5
B16: ADJUSTED NUMBER AT PROBABLY BUY | C16: =C15*0.3 -> 10.5 | D16: =D15*0.3 -> 8.4 | E16: =E15*0.3 -> 6 | F16: =F15*0.3 -> 4.2 | G16: =G15*0.3 -> 1.5
B17: CUMULATIVE NUMBER AT DEFINITELY BUY | C17: 43 | D17: 33 | E17: 24 | F17: 18 | G17: 9
B18: ADJUSTED NUMBER AT DEFINITELY BUY | C18: =C17*0.8 -> 34.4 | D18: =D17*0.8 -> 26.4 | E18: =E17*0.8 -> 19.2 | F18: =F17*0.8 -> 14.4 | G18: =G17*0.8 -> 7.2
B19: SUM OF PURCHASE INTENT | C19: 44.9 | D19: 34.8 | E19: 25.2 | F19: 18.6 | G19: 8.7
B20: TOTAL SAMPLE SIZE | C20: 119 | D20: 119 | E20: 119 | F20: 119 | G20: 119
B21: ADJUSTMENT FOR TOTAL SAMPLE SIZE | C21: =C19/C20 -> 0.37731092 | D21: =D19/D20 -> 0.29243697 | E21: =E19/E20 -> 0.21176471 | F21: =F19/F20 -> 0.15630252 | G21: =G19/G20 -> 0.073109244
B23: PRICE | C23: CUMULATIVE PURCHASE INTENT
B24: 55 | C24: =C21 -> 0.37731092
B25: 60 | C25: =D21 -> 0.29243697
B26: 70 | C26: =E21 -> 0.21176471
B27: 80 | C27: =F21 -> 0.15630252
B28: 85 | C28: =G21 -> 0.073109244
B30: SLOPE OF CUMULATIVE P.I. | C30: INTERCEPT
B31: -0.009114415 | C31: 0.86019392

Sheet MK Sales Projections
B2: BASES MODEL (YEARS 1-5)
B4: BASES FORECAST | C4: YEAR 1 | D4: YEAR 2 | E4: YEAR 3 | F4: YEAR 4 | G4: YEAR 5
B5: TARGET MARKET SIZE | C5: ='MK Assumptions'!C5*I6 -> 13412762 | D5: =(C5*(1+'MK Assumptions'!$C$6)-'MK Sales Projections'!C14)*$I$6 -> 13533202 | E5: =(D5*(1+'MK Assumptions'!$C$6)-'MK Sales Projections'!D14)*$I$6 -> 13621163 | F5: =(E5*(1+'MK Assumptions'!$C$6)-'MK Sales Projections'!E14)*$I$6 -> 13685664 | G5: =(F5*(1+'MK Assumptions'!$C$6)-'MK Sales Projections'!F14)*$I$6 -> 13697262 | I5: Target Market Size Sensitivity
B6: ADJUSTED Purchase Intent @ $ Average Weighted Retail Price | C6: =('MK Weighted Price Calculations'!C11*'MK Demand Curve & Purchase Inte'!B31)+'MK Demand Curve & Purchase Inte'!C31 -> 0.22218487 | D6: =('MK Weighted Price Calculations'!C20*'MK Demand Curve & Purchase Inte'!B31)+'MK Demand Curve & Purchase Inte'!C31 -> 0.22218487 | E6: =('MK Weighted Price Calculations'!C29*'MK Demand Curve & Purchase Inte'!B31)+'MK Demand Curve & Purchase Inte'!C31 -> 0.22798496 | F6: =('MK Weighted Price Calculations'!C38*'MK Demand Curve & Purchase Inte'!B31)+'MK Demand Curve & Purchase Inte'!C31 -> 0.24510594 | G6: =('MK Weighted Price Calculations'!C47*'MK Demand Curve & Purchase Inte'!B31)+'MK Demand Curve & Purchase Inte'!C31 -> 0.2523453 | I6: 1
B7: Awareness | C7: ='MK IMC Schedule'!P24*I9 -> 0.11317725 | D7: ='MK IMC Schedule'!P48*I9 -> 0.15886043 | E7: ='MK IMC Schedule'!P72*I9 -> 0.19350977 | F7: ='MK IMC Schedule'!P96*I9 -> 0.2515383 | G7: ='MK IMC Schedule'!P120*I9 -> 0.32199172
B8: ACV | C8: ='MK Assumptions'!C9 -> 0.14 | D8: ='MK Assumptions'!C10 -> 0.17 | E8: ='MK Assumptions'!C11 -> 0.22 | F8: ='MK Assumptions'!C12 -> 0.27 | G8: ='MK Assumptions'!C13 -> 0.33 | I8: Awareness Sensitivity
B9: Units at Trial | C9: 1 | D9: 1 | E9: 1 | F9: 1 | G9: 1 | I9: 1
B10: TRIAL UNITS | C10: =C5*C6*C7*C8*C9 -> 47219.337 | D10: =D5*D6*D7*D8*D9 -> 81204.43 | E10: =E5*E6*E7*E8*E9 -> 132204.42 | F10: =F5*F6*F7*F8*F9 -> 227817.77 | G10: =G5*G6*G7*G8*G9 -> 367271.84
B11: Repeat Units | C11: 0 | D11: 0 | E11: 0 | F11: 0 | G11: 0
B12: BASES Sales Units (before competition) | C12: =C10*$I$13 -> 47219.337 | D12: =D10*$I$13 -> 81204.43 | E12: =E10*$I$13 -> 132204.42 | F12: =F10*$I$13 -> 227817.77 | G12: =G10*$I$13 -> 367271.84 | I12: BASES Sales Units Sensitivity
B13: Competition Adjustment (units lost to competition) | C13: 0 | D13: 0 | E13: 0.2 | F13: 0.3 | G13: 0.35 | I13: 1
B14: TOTAL UNITS | C14: =C12*(1-C13) -> 47219.337 | D14: =D12*(1-D13) -> 81204.43 | E14: =E12*(1-E13) -> 105763.53 | F14: =F12*(1-F13) -> 159472.44 | G14: =G12*(1-G13) -> 238726.7
B15: Average WEIGHTED manufacturer's selling price to channel | C15: ='MK Weighted Price Calculations'!C10 -> 34.5 | D15: ='MK Weighted Price Calculations'!C19 -> 33.970588 | E15: ='MK Weighted Price Calculations'!C28 -> 33.122727 | F15: ='MK Weighted Price Calculations'!C37 -> 31.608889 | G15: ='MK Weighted Price Calculations'!C46 -> 30.94
B16: MANUFACTURER SALES ($) | C16: =C15*C14 -> 1629067.1 | D16: =D15*D14 -> 2758562.2 | E16: =E15*E14 -> 3503176.7 | F16: =F15*F14 -> 5040746.6 | G16: =G15*G14 -> 7386204.1
B17: YEAR 5 TOTAL VARIABLE COST | G17: ='FE Assumptions'!G38 -> 10.035576
B18: YEAR 5 IMC COST | G18: ='MK IMC Schedule'!O127 -> 631633
B19: ESTIMATED PRODUCT LIFE CYCLE IN YEARS | G19: 7
D24: YEAR | E24: Revenue | F24: Awareness | G24: All-Commodity Volume | H24: Purchase Intent
D25: 1 | E25: =C16 -> 1629067.1 | F25: =C8 -> 0.14 | G25: =C8 -> 0.14 | H25: =C6 -> 0.22218487
D26: 2 | E26: =D16 -> 2758562.2 | F26: =D8 -> 0.17 | G26: =D8 -> 0.17 | H26: =D6 -> 0.22218487
D27: 3 | E27: =E16 -> 3503176.7 | F27: =E8 -> 0.22 | G27: =E8 -> 0.22 | H27: =E6 -> 0.22798496
D28: 4 | E28: =F16 -> 5040746.6 | F28: =F8 -> 0.27 | G28: =F8 -> 0.27 | H28: =F6 -> 0.24510594
D29: 5 | E29: =G16 -> 7386204.1 | F29: =G8 -> 0.33 | G29: =G8 -> 0.33 | H29: =G6 -> 0.2523453
D32: Year | E32: 1 | F32: 2 | G32: 3 | H32: 4 | I32: 5
D33: Revenue | E33: =E25 -> 1629067.1 | F33: =E26 -> 2758562.2 | G33: =E27 -> 3503176.7 | H33: =E28 -> 5040746.6 | I33: =E29 -> 7386204.1
D34: Purchase Intent | E34: =H25 -> 0.22218487 | F34: =H26 -> 0.22218487 | G34: =H27 -> 0.22798496 | H34: =H28 -> 0.24510594 | I34: =H29 -> 0.2523453
D35: Awareness | E35: =C7 -> 0.11317725 | F35: =D7 -> 0.15886043 | G35: =E7 -> 0.19350977 | H35: =F7 -> 0.2515383 | I35: =G7 -> 0.32199172
D36: All-Commodity Volume | E36: =C8 -> 0.14 | F36: =D8 -> 0.17 | G36: =E8 -> 0.22 | H36: =F8 -> 0.27 | I36: =G8 -> 0.33
D37: Units Lost to Competition | E37: =C13 -> 0 | F37: =D13 -> 0 | G37: =E13 -> 0.2 | H37: =F13 -> 0.3 | I37: =G13 -> 0.35

Sheet MK Weighted Price Calculations
B2: WEIGHTED PRICE CALCULATIONS
B4: AVERAGE WEIGHTED MANUFACTURER's SELLING PRICE (YEAR 1)
C5: % MANU TOTAL UNITS | D5: MANU. SELLING PRICE | E5: RETAILER MARGIN | F5: RETAIL SELLING PRICE
B6: UNITS ONLINE | C6: ='MK Assumptions'!H3 -> 0.85714286 | D6: =F6*E6 -> 35 | E6: ='MK Assumptions'!$C$16 -> 0.5 | F6: ='MK Assumptions'!C29 -> 70
B7: UNITS INTO INDEPENDENT RETAILERS | C7: ='MK Assumptions'!H4 -> 0.14285714 | D7: =F7*E7 -> 31.5 | E7: ='MK Assumptions'!$C$17 -> 0.45 | F7: ='MK Assumptions'!C30 -> 70
B8: UNITS INTO CHAIN RETAILERS | C8: 0 | D8: =F8*E8 -> 0 | E8: ='MK Assumptions'!$C$18 -> 0.45 | F8: 0
B9: UNITS INTO MASS MERCHANTS | C9: 0 | D9: =F9*E9 -> 0 | E9: ='MK Assumptions'!$C$19 -> 0.4 | F9: 0
B10: AVERAGE WEIGHTED MANUFACTURING PRICE | C10: =(C6*D6)+(C7*D7) -> 34.5
B11: AVERAGE WEIGHTED RETAIL PRICE | C11: =(C6*F6)+(C7*F7) -> 70
B13: AVERAGE WEIGHTED MANUFACTURER's SELLING PRICE (YEAR 2)
C14: % MANU TOTAL UNITS | D14: MANU. SELLING PRICE | E14: RETAILER MARGIN | F14: RETAIL SELLING PRICE
B15: UNITS ONLINE | C15: ='MK Assumptions'!H8 -> 0.70588235 | D15: =F15*E15 -> 35 | E15: ='MK Assumptions'!$C$16 -> 0.5 | F15: ='MK Assumptions'!C29 -> 70
B16: UNITS INTO INDEPENDENT RETAILERS | C16: ='MK Assumptions'!H9 -> 0.29411765 | D16: =F16*E16 -> 31.5 | E16: ='MK Assumptions'!$C$17 -> 0.45 | F16: ='MK Assumptions'!C30 -> 70
B17: UNITS INTO CHAIN RETAILERS | C17: 0 | D17: =F17*E17 -> 0 | E17: ='MK Assumptions'!$C$18 -> 0.45 | F17: 0
B18: UNITS INTO MASS MERCHANTS | C18: 0 | D18: =F18*E18 -> 0 | E18: ='MK Assumptions'!$C$19 -> 0.4 | F18: 0
B19: AVERAGE WEIGHTED MANUFACTURING PRICE | C19: =(C15*D15)+(C16*D16) -> 33.970588
B20: AVERAGE WEIGHTED RETAIL PRICE | C20: =(C15*F15)+(C16*F16) -> 70
B22: AVERAGE WEIGHTED MANUFACTURER's SELLING PRICE (YEAR 2)
C23: % MANU TOTAL UNITS | D23: MANU. SELLING PRICE | E23: RETAILER MARGIN | F23: RETAIL SELLING PRICE
B24: UNITS ONLINE | C24: ='MK Assumptions'!H13 -> 0.54545455 | D24: =F24*E24 -> 35 | E24: ='MK Assumptions'!$C$16 -> 0.5 | F24: ='MK Assumptions'!C29 -> 70
B25: UNITS INTO INDEPENDENT RETAILERS | C25: ='MK Assumptions'!H14 -> 0.36363636 | D25: =F25*E25 -> 31.5 | E25: ='MK Assumptions'!$C$17 -> 0.45 | F25: ='MK Assumptions'!C30 -> 70
B26: UNITS INTO CHAIN RETAILERS | C26: ='MK Assumptions'!H15 -> 0.090909091 | D26: =F26*E26 -> 28.35 | E26: ='MK Assumptions'!$C$18 -> 0.45 | F26: ='MK Assumptions'!C31 -> 63
B27: UNITS INTO MASS MERCHANTS | C27: 0 | D27: =F27*E27 -> 0 | E27: ='MK Assumptions'!$C$19 -> 0.4 | F27: 0
B28: AVERAGE WEIGHTED MANUFACTURING PRICE | C28: =(C24*D24)+(C25*D25)+(C26*D26) -> 33.122727
B29: AVERAGE WEIGHTED RETAIL PRICE | C29: =(C24*F24)+(C25*F25)+(C26*F26) -> 69.363636
B31: AVERAGE WEIGHTED MANUFACTURER's SELLING PRICE (YEAR 1)
C32: % MANU TOTAL UNITS | D32: MANU. SELLING PRICE | E32: RETAILER MARGIN | F32: RETAIL SELLING PRICE
B33: UNITS ONLINE | C33: ='MK Assumptions'!H19 -> 0.44444444 | D33: =F33*E33 -> 35 | E33: ='MK Assumptions'!$C$16 -> 0.5 | F33: ='MK Assumptions'!C29 -> 70
B34: UNITS INTO INDEPENDENT RETAILERS | C34: ='MK Assumptions'!H20 -> 0.2962963 | D34: =F34*E34 -> 31.5 | E34: ='MK Assumptions'!$C$17 -> 0.45 | F34: ='MK Assumptions'!C30 -> 70
B35: UNITS INTO CHAIN RETAILERS | C35: ='MK Assumptions'!H21 -> 0.14814815 | D35: =F35*E35 -> 28.35 | E35: ='MK Assumptions'!$C$18 -> 0.45 | F35: ='MK Assumptions'!C31 -> 63
B36: UNITS INTO MASS MERCHANTS | C36: ='MK Assumptions'!H22 -> 0.11111111 | D36: =F36*E36 -> 22.68 | E36: ='MK Assumptions'!$C$19 -> 0.4 | F36: ='MK Assumptions'!C32 -> 56.7
B37: AVERAGE WEIGHTED MANUFACTURING PRICE | C37: =(C33*D33)+(C34*D34)+(C35*D35)+(C36*D36) -> 31.608889
B38: AVERAGE WEIGHTED RETAIL PRICE | C38: =(C33*F33)+(C34*F34)+(C35*F35)+(C36*F36) -> 67.485185
B40: AVERAGE WEIGHTED MANUFACTURER's SELLING PRICE (YEAR 1)
C41: % MANU TOTAL UNITS | D41: MANU. SELLING PRICE | E41: RETAILER MARGIN | F41: RETAIL SELLING PRICE
B42: UNITS ONLINE | C42: ='MK Assumptions'!H26 -> 0.36363636 | D42: =F42*E42 -> 35 | E42: ='MK Assumptions'!$C$16 -> 0.5 | F42: ='MK Assumptions'!C29 -> 70
B43: UNITS INTO INDEPENDENT RETAILERS | C43: ='MK Assumptions'!H27 -> 0.27272727 | D43: =F43*E43 -> 31.5 | E43: ='MK Assumptions'!$C$17 -> 0.45 | F43: ='MK Assumptions'!C30 -> 70
B44: UNITS INTO CHAIN RETAILERS | C44: ='MK Assumptions'!H28 -> 0.24242424 | D44: =F44*E44 -> 28.35 | E44: ='MK Assumptions'!$C$18 -> 0.45 | F44: ='MK Assumptions'!C31 -> 63
B45: UNITS INTO MASS MERCHANTS | C45: ='MK Assumptions'!H29 -> 0.12121212 | D45: =F45*E45 -> 22.68 | E45: ='MK Assumptions'!$C$19 -> 0.4 | F45: ='MK Assumptions'!C32 -> 56.7
B46: AVERAGE WEIGHTED MANUFACTURING PRICE | C46: =(C42*D42)+(C43*D43)+(C44*D44)+(C45*D45) -> 30.94
B47: AVERAGE WEIGHTED RETAIL PRICE | C47: =(C42*F42)+(C43*F43)+(C44*F44)+(C45*F45) -> 66.690909

Sheet MK IMC Schedule
B2: IMC SCHEDULE (YEARS 1-5)
B4: WEBSITE | C4: JAN | D4: FEB | E4: MAR | F4: APR | G4: MAY | H4: JUN | I4: JUL | J4: AUG | K4: SEP | L4: OCT | M4: NOV | N4: DEC | O4: TOTAL COST | P4: AWARENESS | Q4: CPM/CPC
B5: Website | O5: ='OM IS Expenses'!C26*12 -> 300
B6: Production Costs | O6: =O7-O5 -> 39942.05
B7: TOTAL IMC BUDGET | O7: =0.15*O31 -> 40242.05
P10: SEGMENT SIZE | Q10: ='MK Sales Projections'!C5 -> 13412762
B11: YEAR 1 | C11: JAN | D11: FEB | E11: MAR | F11: APR | G11: MAY | H11: JUN | I11: JUL | J11: AUG | K11: SEP | L11: OCT | M11: NOV | N11: DEC | O11: TOTAL COST | P11: AWARENESS | Q11: CPM/CPC | S11: OUT OF HOME ADVERTISING (YEAR 1)
B12: PULL | S12: CITIES | T12: COST PER AD | U12: ADS PER CITY | V12: TIMES PER YEAR | W12: AWARENESS RATE PER $1000
B13: Paid Media | S13: NEW YORK CITY | T13: 1050 | U13: 9 | V13: 4 | W13: 0.0004
B14: Social Media | O14: =T22 -> 5000 | P14: =X22 -> 0.0051205947 | Q14: 9.1 | S14: WASHINGTON D.C. | T14: 555
B15: Youtube Ads | O15: =T23 -> 5000 | P15: =X23 -> 0.004853897 | Q15: 9.6 | S15: BOSTON | T15: 555
B16: Google Search | O16: =T24 -> 10000 | P16: =(O16/Q16)/Q10 -> 0.00074555859 | Q16: 1 | S16: SAN FRANCISCO | T16: 2745
B17: Influencer Marketing | O17: =W29 -> 8137.3333 | P17: =X29 -> 0.01 | S17: MINNEAPOLIS | T17: 1804
B18: OOH Advertising | O18: =5*T18*U13*V13*0.75 -> 181143 | P18: =O18/1000*W13 -> 0.0724572 | S18: AVERAGE COST PER AD | T18: =AVERAGE(T13:T17) -> 1341.8
B19: Owned Media
B20: Website | O20: 2000 | P20: 0 | S20: PAID MEDIA (YEAR 1)
B21: Earned Media | S21: MEDIA TYPE | T21: BUDGET | U21: TARGETED IMPRESSIONS | V21: AD IMPACT TARGET IMPRESSIONS | W21: PEOPLE AWARE | X21: AWARENESS
B22: Social Media Amp & WOM | O22: 0 | P22: 0.01 | S22: SOCIAL MEDIA | T22: 5000 | U22: =(T22/Q14)*U25 -> 549450.55 | V22: =U22*V25 -> 274725.27 | W22: =V22/W25 -> 68681.319 | X22: =W22/$Q$10 -> 0.0051205947
B23: Public Relations | O23: 5000 | P23: 0.01 | S23: YOUTUBE | T23: 5000 | U23: =T23/Q15*U25 -> 520833.33 | V23: =U23*V25 -> 260416.67 | W23: =V23/W25 -> 65104.167 | X23: =W23/$Q$10 -> 0.004853897
B24: TOTAL PULL | O24: =SUM(O14:O23) -> 216280.33 | P24: =SUM(P14:P23) -> 0.11317725 | S24: GOOGLE DESKTOP | T24: 10000
B25: PUSH | T25: CPM STRATEGY | U25: 1000 | V25: 0.5 | W25: 4
B26: Outdoor Demo Trade Show | O26: 16000
B27: Life Time Sea Otter Classic Trade Show | O27: 16000 | S27: INFLUENCER MARKETING (YEAR 1)
B28: Safe Routes Partnership | O28: 0 | S28: INFLUENCER | T28: FOLLOWING | U28: INFLUENCER TYPE | V28: PAYMENTS BASED ON SIZE | W28: TOTAL INLUENCER SPEND | X28: AWARENESS (GIVEN)
B29: TOTAL PUSH | O29: =SUM(O26:O28) -> 32000 | S29: TwoWheelingTots | T29: 7900 | U29: Nano | V29: ='MK Assumptions'!N$3+(T29-'MK Assumptions'!L$3)*(('MK Assumptions'!O$3-'MK Assumptions'!N$3)/('MK Assumptions'!M$3-'MK Assumptions'!L$3)) -> 1290 | W29: =SUM(V29:V33) -> 8137.3333 | X29: 0.01
B30: Production Costs | O30: 20000 | S30: RascalRides | T30: 2090 | U30: Nano | V30: ='MK Assumptions'!N$3+(T30-'MK Assumptions'!L$3)*(('MK Assumptions'!O$3-'MK Assumptions'!N$3)/('MK Assumptions'!M$3-'MK Assumptions'!L$3)) -> 709
B31: TOTAL IMC BUDGET | O31: =O30+O29+O24 -> 268280.33 | S31: KellyJaneCollinge | T31: 13400 | U31: Nano | V31: ='MK Assumptions'!N$3+(T31-'MK Assumptions'!L$3)*(('MK Assumptions'!O$3-'MK Assumptions'!N$3)/('MK Assumptions'!M$3-'MK Assumptions'!L$3)) -> 1840
N32: PERCENTAGE OF SALES | O32: =O31/'MK Sales Projections'!C16 -> 0.16468341 | S32: TheMultiDad | T32: 16600 | U32: Micro | V32: ='MK Assumptions'!N$4+(T32-'MK Assumptions'!L$4)*(('MK Assumptions'!O$4-'MK Assumptions'!N$4)/('MK Assumptions'!M$4-'MK Assumptions'!L$4)) -> 1186.6667
S33: DadBodCycling | T33: 33100 | U33: Micro | V33: ='MK Assumptions'!N$4+(T33-'MK Assumptions'!L$4)*(('MK Assumptions'!O$4-'MK Assumptions'!N$4)/('MK Assumptions'!M$4-'MK Assumptions'!L$4)) -> 3111.6667
P34: SEGMENT SIZE | Q34: ='MK Sales Projections'!D5 -> 13533202
B35: YEAR 2 | C35: JAN | D35: FEB | E35: MAR | F35: APR | G35: MAY | H35: JUN | I35: JUL | J35: AUG | K35: SEP | L35: OCT | M35: NOV | N35: DEC | O35: TOTAL COST | P35: AWARENESS | Q35: CPM | S35: OUT OF HOME ADVERTISING (YEAR 2)
B36: PULL | S36: CITIES | T36: COST PER AD | U36: ADS PER CITY | V36: TIMES PER YEAR | W36: AWARENESS RATE PER $1000
B37: Paid Media | S37: NEW YORK CITY | T37: 1050 | U37: 9 | V37: 4 | W37: 0.0004
B38: Social Media | O38: =T46 -> 10000 | P38: =X46 -> 0.010241189 | Q38: 9.1 | S38: SAN FRANCISCO | T38: 2475
B39: Youtube Ads | O39: =T47 -> 10000 | P39: =X47 -> 0.0097077941 | Q39: 9.6 | S39: WASHINGTON DC | T39: 555
B40: Google Search | O40: =T48 -> 20000 | P40: =(O40/Q40)/Q34 -> 0.0014778468 | Q40: 1 | S40: MINNEAPOLIS | T40: 1804
B41: Influencer Marketing | O41: =W53 -> 14148.762 | P41: =X53 -> 0.02 | S41: AUSTIN | T41: 535
B42: OOH Advertising | O42: =5*T42*U37*V37 -> 231084 | P42: =O42/1000*W37 -> 0.0924336 | S42: AVERAGE COST PER AD | T42: =AVERAGE(T37:T41) -> 1283.8
B43: Owned Media
B44: Website | O44: 2000 | P44: 0 | S44: PAID MEDIA (YEAR 2)
B45: Earned Media | S45: MEDIA TYPE | T45: BUDGET | U45: TARGETED IMPRESSIONS | V45: AD IMPACT TARGET IMPRESSIONS | W45: PEOPLE AWARE | X45: AWARENESS
B46: Social Media Amp & WOM | O46: 0 | P46: 0.015 | S46: SOCIAL MEDIA | T46: 10000 | U46: =(T46/Q38)*U49 -> 1098901.1 | V46: =U46*V49 -> 549450.55 | W46: =V46/W49 -> 137362.64 | X46: =W46/$Q$10 -> 0.010241189
B47: Public Relations | O47: 5000 | P47: 0.01 | S47: YOUTUBE | T47: 10000 | U47: =T47/Q39*U49 -> 1041666.7 | V47: =U47*V49 -> 520833.33 | W47: =V47/W49 -> 130208.33 | X47: =W47/$Q$10 -> 0.0097077941
B48: TOTAL PULL | O48: =SUM(O38:O47) -> 292232.76 | P48: =SUM(P38:P47) -> 0.15886043 | S48: GOOGLE DESKTOP | T48: 20000
B49: PUSH | T49: CPM STRATEGY | U49: 1000 | V49: 0.5 | W49: 4
B50: Outdoor Demo Trade Show | O50: 16000
B51: Life Time Sea Otter Classic Trade Show | O51: 16000 | S51: INFLUENCER MARKETING (YEAR 2)
B52: Safe Routes Partnership | O52: 0 | S52: INFLUENCER | T52: Following | U52: Influencer Type | V52: PAYMENTS BASED ON SIZE | W52: TOTAL INLUENCER SPEND | X52: AWARENESS (GIVEN)
B53: TOTAL PUSH | O53: =SUM(O50:O52) -> 32000 | S53: TwoWheelingTots | T53: 7900 | U53: Nano | V53: ='MK Assumptions'!N$3+(T53-'MK Assumptions'!L$3)*(('MK Assumptions'!O$3-'MK Assumptions'!N$3)/('MK Assumptions'!M$3-'MK Assumptions'!L$3)) -> 1290 | W53: =SUM(V53:V58) -> 14148.762 | X53: 0.02
B54: Production Costs | O54: 20000 | S54: RascalRides | T54: 2090 | U54: Nano | V54: ='MK Assumptions'!N$3+(T54-'MK Assumptions'!L$3)*(('MK Assumptions'!O$3-'MK Assumptions'!N$3)/('MK Assumptions'!M$3-'MK Assumptions'!L$3)) -> 709
B55: TOTAL IMC BUDGET | O55: =O54+O53+O48 -> 344232.76 | S55: KellyJaneCollinge | T55: 13400 | U55: Nano | V55: ='MK Assumptions'!N$3+(T55-'MK Assumptions'!L$3)*(('MK Assumptions'!O$3-'MK Assumptions'!N$3)/('MK Assumptions'!M$3-'MK Assumptions'!L$3)) -> 1840
N56: PERCENTAGE OF SALES | O56: =O55/'MK Sales Projections'!D16 -> 0.12478702 | S56: TheMultiDad | T56: 16600 | U56: Micro | V56: ='MK Assumptions'!N$4+(T56-'MK Assumptions'!L$4)*(('MK Assumptions'!O$4-'MK Assumptions'!N$4)/('MK Assumptions'!M$4-'MK Assumptions'!L$4)) -> 1186.6667
S57: DadBodCycling | T57: 33100 | U57: Micro | V57: ='MK Assumptions'!N$4+(T57-'MK Assumptions'!L$4)*(('MK Assumptions'!O$4-'MK Assumptions'!N$4)/('MK Assumptions'!M$4-'MK Assumptions'!L$4)) -> 3111.6667
P58: SEGMENT SIZE | Q58: ='MK Sales Projections'!E5 -> 13621163 | S58: AdamBlythe | T58: 86800 | U58: Mid-tier | V58: ='MK Assumptions'!N$5+(T58-'MK Assumptions'!L$5)*(('MK Assumptions'!O$5-'MK Assumptions'!N$5)/('MK Assumptions'!M$5-'MK Assumptions'!L$5)) -> 6011.4286
B59: YEAR 3 | C59: JAN | D59: FEB | E59: MAR | F59: APR | G59: MAY | H59: JUN | I59: JUL | J59: AUG | K59: SEP | L59: OCT | M59: NOV | N59: DEC | O59: TOTAL COST | P59: AWARENESS | Q59: CPM | S59: OUT OF HOME ADVERTISING (YEAR 3)
B60: PULL | S60: CITIES | T60: COST PER AD | U60: ADS PER CITY | V60: TIMES PER YEAR | W60: AWARENESS RATE PER $1000
B61: Paid Media | S61: NEW YORK CITY | T61: 1050 | U61: 8 | V61: 4 | W61: 0.0004
B62: Social Media | O62: =T70 -> 20000 | P62: =X70 -> 0.020482379 | Q62: 9.1 | S62: SAN FRANCISCO | T62: 2745
B63: Youtube Ads | O63: =T71 -> 20000 | P63: =X71 -> 0.019415588 | Q63: 9.6 | S63: MINNEAPOLIS | T63: 1804
B64: Google Search | O64: =T72 -> 40000 | P64: =(O64/Q64)/Q58 -> 0.0029366068 | Q64: 1 | S64: CHICAGO | T64: 1010
B65: Influencer Marketing | O65: =W77 -> 31156.429 | P65: =X77 -> 0.03 | S65: DENVER | T65: 475
B66: OOH Advertising | O66: =5*T66*U61*V61 -> 226688 | P66: =O66/1000*W61 -> 0.0906752 | S66: AVERAGE COST PER AD | T66: =AVERAGE(T61:T65) -> 1416.8
B67: Owned Media
B68: Website | O68: 2000 | P68: 0 | S68: PAID MEDIA (YEAR 3)
B69: Earned Media | S69: MEDIA TYPE | T69: BUDGET | U69: TARGETED IMPRESSIONS | V69: AD IMPACT TARGET IMPRESSIONS | W69: PEOPLE AWARE | X69: AWARENESS
B70: Social Media Amp & WOM | O70: 0 | P70: 0.02 | S70: SOCIAL MEDIA | T70: 20000 | U70: =(T70/Q62)*U73 -> 2197802.2 | V70: =U70*V73 -> 1098901.1 | W70: =V70/W73 -> 274725.27 | X70: =W70/$Q$10 -> 0.020482379
B71: Public Relations | O71: 5000 | P71: 0.01 | S71: YOUTUBE | T71: 20000 | U71: =T71/Q63*U73 -> 2083333.3 | V71: =U71*V73 -> 1041666.7 | W71: =V71/W73 -> 260416.67 | X71: =W71/$Q$10 -> 0.019415588
B72: TOTAL PULL | O72: =SUM(O62:O71) -> 344844.43 | P72: =SUM(P62:P71) -> 0.19350977 | S72: GOOGLE DESKTOP | T72: 40000
B73: PUSH | T73: CPM STRATEGY | U73: 1000 | V73: 0.5 | W73: 4
B74: Outdoor Demo Trade Show | O74: 16000
B75: Life Time Sea Otter Classic Trade Show | O75: 16000 | S75: INFLUENCER MARKETING (YEAR 3)
B76: Safe Routes Partnership | O76: 0 | S76: INFLUENCER | T76: Following | U76: Influencer Type | V76: PAYMENTS BASED ON SIZE | W76: TOTAL INLUENCER SPEND | X76: AWARENESS (GIVEN)
B77: TOTAL PUSH | O77: =SUM(O74:O76) -> 32000 | S77: EmilyBatty1 | T77: 311000 | U77: Macro | V77: ='MK Assumptions'!N$6+(T77-'MK Assumptions'!L$6)*(('MK Assumptions'!O$6-'MK Assumptions'!N$6)/('MK Assumptions'!M$6-'MK Assumptions'!L$6)) -> 22033.333 | W77: =SUM(V77:V79) -> 31156.429 | X77: 0.03
B78: Production Costs | O78: 20000 | S78: AdamBlythe | T78: 86800 | U78: Mid-tier | V78: ='MK Assumptions'!N$5+(T78-'MK Assumptions'!L$5)*(('MK Assumptions'!O$5-'MK Assumptions'!N$5)/('MK Assumptions'!M$5-'MK Assumptions'!L$5)) -> 6011.4286
B79: TOTAL IMC BUDGET | O79: =O78+O77+O72 -> 396844.43 | S79: DadBodCycling | T79: 33100 | U79: Micro | V79: ='MK Assumptions'!N$4+(T79-'MK Assumptions'!L$4)*(('MK Assumptions'!O$4-'MK Assumptions'!N$4)/('MK Assumptions'!M$4-'MK Assumptions'!L$4)) -> 3111.6667
N80: PERCENTAGE OF SALES | O80: =O79/'MK Sales Projections'!E16 -> 0.11328131
P82: SEGMENT SIZE | Q82: ='MK Sales Projections'!F5 -> 13685664
B83: YEAR 4 | C83: JAN | D83: FEB | E83: MAR | F83: APR | G83: MAY | H83: JUN | I83: JUL | J83: AUG | K83: SEP | L83: OCT | M83: NOV | N83: DEC | O83: TOTAL COST | P83: AWARENESS | Q83: CPM | S83: OUT OF HOME ADVERTISING (YEAR 4)
B84: PULL | S84: CITIES | T84: COST PER AD | U84: ADS PER CITY | V84: TIMES PER YEAR | W84: AWARENESS RATE PER $1000
B85: Paid Media | S85: NEW YORK CITY | T85: 1050 | U85: 8 | V85: 4 | W85: 0.0004
B86: Social Media | O86: =T94 -> 30000 | P86: =X94 -> 0.030723568 | Q86: 9.1 | S86: SAN FRANCISCO | T86: 2745
B87: Youtube Ads | O87: =T95 -> 30000 | P87: =X95 -> 0.029123382 | Q87: 9.6 | S87: MINNEAPOLIS | T87: 1804
B88: Google Search | O88: =T96 -> 60000 | P88: =(O88/Q88)/Q82 -> 0.0043841497 | Q88: 1 | S88: PHILADELPHIA | T88: 2700
B89: Influencer Marketing | O89: =W101 -> 43633.333 | P89: =X101 -> 0.04 | S89: DENVER | T89: 475
B90: OOH Advertising | O90: =5*T90*U85*V85 -> 280768 | P90: =O90/1000*W85 -> 0.1123072 | S90: AVERAGE COST PER AD | T90: =AVERAGE(T85:T89) -> 1754.8
B91: Owned Media
B92: Website | O92: 2000 | P92: 0 | S92: PAID MEDIA (YEAR 4)
B93: Earned Media | S93: MEDIA TYPE | T93: BUDGET | U93: TARGETED IMPRESSIONS | V93: AD IMPACT TARGET IMPRESSIONS | W93: PEOPLE AWARE | X93: AWARENESS
B94: Social Media Amp & WOM | O94: 0 | P94: 0.025 | S94: SOCIAL MEDIA | T94: 30000 | U94: =(T94/Q86)*U97 -> 3296703.3 | V94: =U94*V97 -> 1648351.6 | W94: =V94/W97 -> 412087.91 | X94: =W94/$Q$10 -> 0.030723568
B95: Public Relations | O95: 5000 | P95: 0.01 | S95: YOUTUBE | T95: 30000 | U95: =T95/Q87*U97 -> 3125000 | V95: =U95*V97 -> 1562500 | W95: =V95/W97 -> 390625 | X95: =W95/$Q$10 -> 0.029123382
B96: TOTAL PULL | O96: =SUM(O86:O95) -> 451401.33 | P96: =SUM(P86:P95) -> 0.2515383 | S96: GOOGLE DESKTOP | T96: 60000
B97: PUSH | T97: CPM STRATEGY | U97: 1000 | V97: 0.5 | W97: 4
B98: Outdoor Demo Trade Show | O98: 16000
B99: Life Time Sea Otter Classic Trade Show | O99: 16000 | S99: INFLUENCER MARKETING (YEAR 4)
B100: Safe Routes Partnership | O100: 0 | S100: INFLUENCER | T100: Following | U100: Influencer Type | V100: PAYMENTS BASED ON SIZE | W100: TOTAL INLUENCER SPEND | X100: AWARENESS (GIVEN)
B101: TOTAL PUSH | O101: =SUM(O98:O100) -> 32000 | S101: EmilyBatty1 | T101: 311000 | U101: Macro | V101: ='MK Assumptions'!N$6+(T101-'MK Assumptions'!L$6)*(('MK Assumptions'!O$6-'MK Assumptions'!N$6)/('MK Assumptions'!M$6-'MK Assumptions'!L$6)) -> 22033.333 | W101: =SUM(V101:V102) -> 43633.333 | X101: 0.04
B102: Production Costs | O102: 20000 | S102: TedLegity | T102: 298000 | U102: Macro | V102: ='MK Assumptions'!N$6+(T102-'MK Assumptions'!L$6)*(('MK Assumptions'!O$6-'MK Assumptions'!N$6)/('MK Assumptions'!M$6-'MK Assumptions'!L$6)) -> 21600
B103: TOTAL IMC BUDGET | O103: =O102+O101+O96 -> 503401.33
N104: PERCENTAGE OF SALES | O104: =O103/'MK Sales Projections'!F16 -> 0.099866424
P106: SEGMENT SIZE | Q106: ='MK Sales Projections'!G5 -> 13697262
...

Sheet OM Assumptions
B2: OM ASSUMPTIONS | E2: SG&A
E3: Executive Salaries as a % of Manu. Sales | F3: 0.01
B4: DIRECT LABOR | E4: Labor Wage Growth Rate | F4: =C8 -> 0.03
B5: Work Days Per Year | C5: 250 | E5: Salesperson Commission Rate | F5: 0.01
B6: Work Hours per Day | C6: 8
B7: Work Hours per Year | C7: =C5*C6 -> 2000
B8: Direct Labor Rate Growth | C8: 0.03
B9: Employee Benefit Rate | C9: 0.3
E12: MANUFACTURING OVERHEAD & LOCATION ANALYSIS
E13: Warehouse Size (SQFT) YoY Growth Rate | F13: 0.01
B14: DIRECT MATERIALS | E14: Office Space (% of Total Warehouse Size) | F14: 0.05
B15: Inflation Rate | C15: 0.03 | E15: Monthly Rental Cost per Squarefoot | F15: 0.92
B16: Increase in Orders per Year | C16: 2 | E16: Rent Cost per SQFT Growth (2%) | F16: 0.02
B17: Fixed Cost per Order | C17: 40 | D17: Service Level Sensitivity | E17: Water Cost per Gallon | F17: 0.00305
B18: Target Service Level (Years 1 - 5) | C18: =95%*D18 -> 0.95 | D18: 1 | E18: Electicity Cost per KwH | F18: 0.14
B19: Service Level Z-Score (Years 1 - 5) | C19: =NORMINV(C18, 0, 1) -> 1.6448536 | E19: KwH Cost Growth Rate | F19: 0.02
B20: Holding Cost Rate | C20: 0.3
E21: Water Cost Per Gallon Growth Rate | F21: 0.02
E22: Gallons Used Per Year Growth Rate | F22: 0.05
B23: CAPITAL EXPENDITURES | E23: Service Cost per SQFT | F23: 30
B24: Finished Units per Industrial Shelf | C24: 9000 | E24: Inbound Freight Cost (% of Unit Cost) | F24: 0.1
E25: Indirect Materials (% of Direct Materials) | F25: 0.2289155
E26: Weight per Unit (incl. packaging) (lbs) | F26: 0.75
E27: Units per Pack | F27: 40
E28: Weight per Pack (lbs) | F28: =F26*F27 -> 30
E29: Case Cost per Pound | F29: 0.45
E30: Cost per 40 Unit Box (Independent Stores) | F30: =F29*F28 -> 13.5
E31: LTL Freight Cost per Pallet | F31: 246
B32: Finished Units per Wood Pallet | C32: 2000 | E32: Outbound Freight Rate Growth | F32: 0.02
B33: Finished Units per Utility Cart | C33: 3000
B34: Finished Units per Storage Bin | C34: 400 | E34: INVENTORY
B35: 20ft Shipping Conatiner Cubic Feet | C35: 1020 | E35: Order Cost | F35: 40
B36: Cubic Feet per Industrial Shelf | C36: =C24*'OM Inventory'!E113 -> 83.333333 | E36: Holding Cost Rate | F36: 0.3

Sheet OM Cost Analysis
B2: OM COST ANALYSIS
B4: TARGET COSTING | C4: YEAR 1 | D4: YEAR 2 | E4: YEAR 3 | F4: YEAR 4 | G4: YEAR 5
B5: RETAIL PRICE PER UNIT | C5: ='MK Weighted Price Calculations'!C11 -> 70 | D5: ='MK Weighted Price Calculations'!C20 -> 70 | E5: ='MK Weighted Price Calculations'!C29 -> 69.363636 | F5: ='MK Weighted Price Calculations'!C38 -> 67.485185 | G5: ='MK Weighted Price Calculations'!C47 -> 66.690909
B6: CHANNEL MARGIN PER UNIT | C6: =C5-C8 -> 35.5 | D6: =D5-D8 -> 36.029412 | E6: =E5-E8 -> 36.240909 | F6: =F5-F8 -> 35.876296 | G6: =G5-G8 -> 35.750909
B7: PERCENTAGE OF RETAIL PRICE (%) | C7: =C6/C5 -> 0.50714286 | D7: =D6/D5 -> 0.51470588 | E7: =E6/E5 -> 0.52247706 | F7: =F6/F5 -> 0.53161736 | G7: =G6/G5 -> 0.5360687
B8: MANUFACTURER'S PRICE PER UNIT | C8: ='FE Assumptions'!C35 -> 34.5 | D8: ='FE Assumptions'!D35 -> 33.970588 | E8: ='FE Assumptions'!E35 -> 33.122727 | F8: ='FE Assumptions'!F35 -> 31.608889 | G8: ='FE Assumptions'!G35 -> 30.94
B9: PERCENTAGE OF MANUFACTURER PRICE (%) | C9: =C8/C5 -> 0.49285714 | D9: =D8/D5 -> 0.48529412 | E9: =E8/E5 -> 0.47752294 | F9: =F8/F5 -> 0.46838264 | G9: =G8/G5 -> 0.4639313
B10: SALES & MARKETING EXPENSE PER UNIT | C10: ='FE Income Statement'!C35 -> 9.1315777 | D10: ='FE Income Statement'!D35 -> 7.6361473 | E10: ='FE Income Statement'!E35 -> 7.0644585 | F10: ='FE Income Statement'!F35 -> 6.3175556 | G10: ='FE Income Statement'!G35 -> 5.7398415
B11: PERCENTAGE OF MANUFACTURER PRICE (%) | C11: =C10/C8 -> 0.26468341 | D11: =D10/D8 -> 0.22478702 | E11: =E10/E8 -> 0.21328131 | F11: =F10/F8 -> 0.19986642 | G11: =G10/G8 -> 0.18551524
B12: GENERAL & ADMINISTRATIVE EXPENSE PER UNIT | C12: ='FE Income Statement'!C30+('FE Income Statement'!C36/'FE Assumptions'!C28) -> 14.300192 | D12: ='FE Income Statement'!D30+('FE Income Statement'!D36/'FE Assumptions'!D28) -> 8.8488035 | E12: ='FE Income Statement'!E30+('FE Income Statement'!E36/'FE Assumptions'!E28) -> 8.5665013 | F12: ='FE Income Statement'!F30+('FE Income Statement'!F36/'FE Assumptions'!F28) -> 6.8579415 | G12: ='FE Income Statement'!G30+('FE Income Statement'!G36/'FE Assumptions'!G28) -> 6.0922392
B13: PERCENTAGE OF MANUFACTURER PRICE (%) | C13: =C12/C8 -> 0.41449832 | D13: =D12/D8 -> 0.26048426 | E13: =E12/E8 -> 0.25862911 | F13: =F12/F8 -> 0.21696244 | G13: =G12/G8 -> 0.19690495
B14: TAX EXPENSE PER UNIT | C14: ='FE Income Statement'!C40 -> 0 | D14: ='FE Income Statement'!D40 -> 1.0556942 | E14: ='FE Income Statement'!E40 -> 1.0345806 | F14: ='FE Income Statement'!F40 -> 1.5583846 | G14: ='FE Income Statement'!G40 -> 1.8292652
B15: PERCENTAGE OF MANUFACTURER PRICE (%) | C15: =C14/C8 -> 0 | D15: =D14/D8 -> 0.031076712 | E15: =E14/E8 -> 0.031234765 | F15: =F14/F8 -> 0.049302101 | G15: =G14/G8 -> 0.059122988
B16: MARGINAL PROFIT PER UNIT | C16: ='FE Income Statement'!C43 -> -3.3590441 | D16: ='FE Income Statement'!D43 -> 2.8542843 | E16: ='FE Income Statement'!E43 -> 2.7971994 | F16: ='FE Income Statement'!F43 -> 4.2134103 | G16: ='FE Income Statement'!G43 -> 4.9457912
B17: PERCENTAGE OF MANUFACTURER PRICE (%) | C17: =C16/C8 -> -0.097363597 | D17: =D16/D8 -> 0.084022222 | E17: =E16/E8 -> 0.084449551 | F17: =F16/F8 -> 0.13329827 | G17: =G16/G8 -> 0.15985104
B18: FINAL CALCULATED COST OF GOODS SOLD | C18: =C8-C10-C12-C14-C16 -> 14.427274 | D18: =D8-D10-D12-D14-D16 -> 13.575659 | E18: =E8-E10-E12-E14-E16 -> 13.659987 | F18: =F8-F10-F12-F14-F16 -> 12.661597 | G18: =G8-G10-G12-G14-G16 -> 12.332863
B19: PERCENTAGE OF MANUFACTURER PRICE (%) | C19: =C18/C8 -> 0.41818186 | D19: =D18/D8 -> 0.39962979 | E19: =E18/E8 -> 0.41240527 | F19: =F18/F8 -> 0.40057077 | G19: =G18/G8 -> 0.39860578
B20: DIRECT MATERIALS COST PER UNIT | C20: ='FE Income Statement'!C11 -> 6.69 | D20: ='FE Income Statement'!D11 -> 6.69 | E20: ='FE Income Statement'!E11 -> 6.69 | F20: ='FE Income Statement'!F11 -> 6.69 | G20: ='FE Income Statement'!G11 -> 6.69
B21: PERCENTAGE OF COGS (%) | C21: =C20/C18 -> 0.46370505 | D21: =D20/D18 -> 0.49279376 | E21: =E20/E18 -> 0.48975155 | F21: =F20/F18 -> 0.52836937 | G21: =G20/G18 -> 0.54245312
B22: DIRECT LABOR COST PER UNIT | C22: ='FE Income Statement'!C13 -> 2.8289344 | D22: ='FE Income Statement'!D13 -> 2.965093 | E22: ='FE Income Statement'!E13 -> 3.3498185 | F22: ='FE Income Statement'!F13 -> 2.7459338 | G22: ='FE Income Statement'!G13 -> 2.6765761
B23: PERCENTAGE OF COGS (%) | C23: =C22/C18 -> 0.19608239 | D23: =D22/D18 -> 0.21841246 | E23: =E22/E18 -> 0.24522852 | F23: =F22/F18 -> 0.21687105 | G23: =G22/G18 -> 0.21702797
B24: MANUFACTURING OVERHEAD COST PER UNIT | C24: ='FE Income Statement'!C19 -> 4.085697 | D24: ='FE Income Statement'!D19 -> 3.0617559 | E24: ='FE Income Statement'!E19 -> 2.7420485 | F24: ='FE Income Statement'!F19 -> 2.3586888 | G24: ='FE Income Statement'!G19 -> 2.1008253
B25: PERCENTAGE OF COGS (%) | C25: =C24/C18 -> 0.28319258 | D25: =D24/D18 -> 0.22553277 | E25: =E24/E18 -> 0.2007358 | F25: =F24/F18 -> 0.18628684 | G25: =G24/G18 -> 0.17034368
B26: INBOUND FREIGHT COST PER UNIT | C26: ='FE Income Statement'!C15 -> 0.669 | D26: ='FE Income Statement'!D15 -> 0.669 | E26: ='FE Income Statement'!E15 -> 0.669 | F26: ='FE Income Statement'!F15 -> 0.669 | G26: ='FE Income Statement'!G15 -> 0.669
B27: PERCENTAGE OF COGS (%) | C27: =C26/C18 -> 0.046370505 | D27: =D26/D18 -> 0.049279376 | E27: =E26/E18 -> 0.048975155 | F27: =F26/F18 -> 0.052836937 | G27: =G26/G18 -> 0.054245312
B28: OUTBOUND FREIGHT COST PER UNIT | C28: ='FE Income Statement'!C17 -> 0.15364286 | D28: ='FE Income Statement'!D17 -> 0.18981 | E28: ='FE Income Statement'!E17 -> 0.2091204 | F28: ='FE Income Statement'!F17 -> 0.19797425 | G28: ='FE Income Statement'!G17 -> 0.19646144
B29: PERCENTAGE OF COGS (%) | C29: =C28/C18 -> 0.010649472 | D29: =D28/D18 -> 0.013981642 | E29: =E28/E18 -> 0.015308975 | F29: =F28/F18 -> 0.015635804 | G29: =G28/G18 -> 0.015929913
B30: ERROR CHECK | C30: =SUM(C20,C22,C24,C26,C28)=C18 -> TRUE | D30: =SUM(D20,D22,D24,D26,D28)=D18 -> TRUE | E30: =SUM(E20,E22,E24,E26,E28)=E18 -> TRUE | F30: =SUM(F20,F22,F24,F26,F28)=F18 -> TRUE | G30: =SUM(G20,G22,G24,G26,G28)=G18 -> TRUE

Sheet OM Capital Expenditures
B2: CAPITAL EXPENDITURES
B4: LONG-TERM CAPEX (10+ YEAR D&A)
B5: EQUIPMENT | C5: USEFUL LIFE (YEARS) | D5: START-UP | E5: AMOUNT IN YEAR 1 | F5: AMOUNT IN YEAR 2 | G5: AMOUNT IN YEAR 3 | H5: AMOUNT IN YEAR 4 | I5: AMOUNT IN YEAR 5
B6: Injection Molding Machine | C6: 10 | D6: 1 | E6: 1 | F6: 1 | G6: 1 | H6: 1 | I6: 1
B7: Custom Steel Molds | C7: 7 | D7: 1 | E7: 1 | F7: 1 | G7: 1 | H7: 1 | I7: 1
B8: Industrial Shelving/Storage | C8: 10 | D8: 3 | E8: ='MK Sales Projections'!C14/'OM Assumptions'!$C$24 -> 5.246593 | F8: ='MK Sales Projections'!D14/'OM Assumptions'!$C$24 -> 9.0227144 | G8: ='MK Sales Projections'!E14/'OM Assumptions'!$C$24 -> 11.751504 | H8: ='MK Sales Projections'!F14/'OM Assumptions'!$C$24 -> 17.71916 | I8: ='MK Sales Projections'!G14/'OM Assumptions'!$C$24 -> 26.525189
B9: Forklift | C9: 10 | D9: 1 | E9: 1 | F9: 1 | G9: 1 | H9: 1 | I9: 1
B10: Industrial Shipping Label Printer | C10: 7 | D10: 1 | E10: 1 | F10: 1 | G10: 1 | H10: 1 | I10: 1
B11: Wood Pallets | C11: 6 | D11: 10 | E11: ='MK Sales Projections'!C14/'OM Assumptions'!$C$32 -> 23.609669 | F11: ='MK Sales Projections'!D14/'OM Assumptions'!$C$32 -> 40.602215 | G11: ='MK Sales Projections'!E14/'OM Assumptions'!$C$32 -> 52.881767 | H11: ='MK Sales Projections'!F14/'OM Assumptions'!$C$32 -> 79.736219 | I11: ='MK Sales Projections'!G14/'OM Assumptions'!$C$32 -> 119.36335
B12: Industrial Scale | C12: 10 | D12: 2 | E12: 2 | F12: 2 | G12: 2 | H12: 2 | I12: 2
B13: 20ft Inventory Shipping Container | C13: 15 | D13: 1 | E13: 1 | F13: 1 | G13: 1 | H13: 1 | I13: 1
B15: SHORT-TERM CAPEX (5 YEAR D&A MAXIMUM)
B16: EQUIPMENT | C16: USEFUL LIFE (YEARS) | D16: START-UP | E16: AMOUNT IN YEAR 1 | F16: AMOUNT IN YEAR 2 | G16: AMOUNT IN YEAR 3 | H16: AMOUNT IN YEAR 4 | I16: AMOUNT IN YEAR 5
B17: Photocopier + Commercial Printer | C17: 5 | D17: 1 | E17: 1 | F17: 1 | G17: 1 | H17: 1 | I17: 1
B18: High-end Network Equipment (router, modem) | C18: 5 | D18: 2 | E18: 2 | F18: 2 | G18: 2 | H18: 2 | I18: 2
B19: Laptops | C19: 3 | D19: 2 | E19: 4 | F19: 9 | G19: 11 | H19: 13 | I19: 15
B20: Desktops | C20: 3 | D20: 7 | E20: 8 | F20: 8 | G20: 9 | H20: 9 | I20: 10
B21: Cell Phones | C21: 5 | D21: 5 | E21: =E20 -> 8 | F21: =F20 -> 8 | G21: =G20 -> 9 | H21: =H20 -> 9 | I21: =I20 -> 10
B22: POS Device | C22: 5 | D22: 1 | E22: 1 | F22: 1 | G22: 1 | H22: 1 | I22: 1
B23: Security Cameras & Equipment | C23: 5 | D23: 12 | E23: 12 | F23: 12 | G23: 12 | H23: 12 | I23: 12
B24: Soddering Equipment | C24: 5 | D24: 2 | E24: 2 | F24: 2 | G24: 2 | H24: 2 | I24: 2
B25: Moving Carts | C25: 5 | D25: 10 | E25: ='MK Sales Projections'!C14/'OM Assumptions'!$C$33 -> 15.739779 | F25: ='MK Sales Projections'!D14/'OM Assumptions'!$C$33 -> 27.068143 | G25: ='MK Sales Projections'!E14/'OM Assumptions'!$C$33 -> 35.254511 | H25: ='MK Sales Projections'!F14/'OM Assumptions'!$C$33 -> 53.157479 | I25: ='MK Sales Projections'!G14/'OM Assumptions'!$C$33 -> 79.575566
B26: Storage Bins | C26: 5 | D26: 50 | E26: ='MK Sales Projections'!C14/'OM Assumptions'!$C$34 -> 118.04834 | F26: ='MK Sales Projections'!D14/'OM Assumptions'!$C$34 -> 203.01107 | G26: ='MK Sales Projections'!E14/'OM Assumptions'!$C$34 -> 264.40883 | H26: ='MK Sales Projections'!F14/'OM Assumptions'!$C$34 -> 398.6811 | I26: ='MK Sales Projections'!G14/'OM Assumptions'!$C$34 -> 596.81675
B29: CAPITAL EXPENDITURE COST
B30: EQUIPMENT | C30: COST PER EQUIPMENT | D30: START-UP | E30: YEAR 1 CAPEX | F30: YEAR 2 CAPEX | G30: YEAR 3 CAPEX | H30: YEAR 4 CAPEX | I30: YEAR 5 CAPEX
B31: Injection Molding Machine | C31: 17500 | D31: =C31*D6 -> 17500 | E31: =C31*(E6-D6) -> 0 | F31: =D31*(F6-E6) -> 0 | G31: =E31*(G6-F6) -> 0 | H31: =F31*(H6-G6) -> 0 | I31: =G31*(I6-H6) -> 0
B32: Custom Steel Molds | C32: 9000 | D32: =$C32*D7 -> 9000 | E32: =C32*(E7-D7) -> 0 | F32: =D32*(F7-E7) -> 0 | G32: =E32*(G7-F7) -> 0 | H32: =F32*(H7-G7) -> 0 | I32: =G32*(I7-H7) -> 0
B33: Industrial Shelving/Storage | C33: 187.27 | D33: =$C33*D8 -> 561.81 | E33: =$C33*E8 -> 982.52948 | F33: =($C33*F8)-E33 -> 707.15425 | G33: =($C33*G8)-F33-E33 -> 511.02037 | H33: =($C33*H8)-G33-F33-E33 -> 1117.5629 | I33: =($C33*I8)-H33-G33-F33-E33 -> 1649.1051
B34: Forklift | C34: 25000 | D34: =$C34*D9 -> 25000 | E34: 0 | F34: 0 | G34: 0 | H34: 0 | I34: 0
B35: Industrial Shipping Label Printer | C35: 8495 | D35: =$C35*D10 -> 8495 | E35: 0 | F35: 0 | G35: 0 | H35: 0 | I35: 0
B36: Wood Pallets | C36: 25 | D36: =$C36*D11 -> 250 | E36: =$C36*(E11-D11) -> 340.24172 | F36: =$C36*(F11-E11) -> 424.81366 | G36: =$C36*(G11-F11) -> 306.9888 | H36: =$C36*(H11-G11) -> 671.36131 | I36: =$C36*(I11-H11) -> 990.67826
B37: Industrial Scale | C37: 698.97 | D37: =$C37*D12 -> 1397.94 | E37: 0 | F37: 0 | G37: 0 | H37: 0 | I37: 0
B38: 20ft Inventory Shipping Container | C38: 2299 | D38: =C38*D13 -> 2299 | E38: 0 | F38: 0 | G38: 0 | H38: 0 | I38: 0
B39: Photocopier + Commercial Printer | C39: 2000 | D39: =$C39*D17 -> 2000 | E39: 0 | F39: =$C39*F17 -> 2000 | G39: 0 | H39: =$C39*H17 -> 2000 | I39: 0
B40: High-end Network Equipment (router, modem) | C40: ='OM IS Expenses'!C19 -> 350 | D40: =$C40*D18 -> 700 | E40: 0 | F40: =$C40*F18 -> 700 | G40: 0 | H40: =$C40*H18 -> 700 | I40: 0
B41: Laptops (managers) | C41: ='OM IS Expenses'!K7 -> 1500 | D41: =$C41*D19 -> 3000 | E41: =$C41*(E19-D19) -> 3000 | F41: =$C41*(F19-E19) -> 7500 | G41: =$C41*(G19-F19) -> 3000 | H41: =$C41*(H19-G19) -> 3000 | I41: =$C41*(I19-H19) -> 3000
B42: Desktops | C42: ='OM IS Expenses'!K8 -> 1000 | D42: =$C42*D20 -> 7000 | E42: =$C42*(E20-D20) -> 1000 | F42: =$C42*(F20-E20) -> 0 | G42: =$C42*(G20-F20) -> 1000 | H42: =$C42*(H20-G20) -> 0 | I42: =$C42*(I20-H20) -> 1000
B43: Cell Phones | C43: ='OM IS Expenses'!K9 -> 168 | D43: =$C43*D21 -> 840 | E43: =$C43*(E21-D21) -> 504 | F43: =$C43*(F21-E21) -> 0 | G43: =$C43*(G21-F21) -> 168 | H43: =$C43*(H21-G21) -> 0 | I43: =$C43*(I21-H21) -> 168
B44: POS Device | C44: ='OM IS Expenses'!C20 -> 349 | D44: =$C44*D22 -> 349 | E44: =$C44*(E22-D22) -> 0 | F44: =$C44*(F22-E22) -> 0 | G44: =$C44*(G22-F22) -> 0 | H44: =$C44*(H22-G22) -> 0 | I44: =$C44*(I22-H22) -> 0
B45: Security Cameras & Equipment | C45: ='OM IS Expenses'!K10 -> 149.99 | D45: =$C45*D23 -> 1799.88 | E45: =$C45*(E23-D23) -> 0 | F45: =$C45*(F23-E23) -> 0 | G45: =$C45*(G23-F23) -> 0 | H45: =$C45*(H23-G23) -> 0 | I45: =$C45*(I23-H23) -> 0
B46: Sodering Equipment | C46: 98.87 | D46: =$C46*D24 -> 197.74 | E46: =$C46*(E24-D24) -> 0 | F46: =$C46*(F24-E24) -> 0 | G46: =$C46*(G24-F24) -> 0 | H46: =$C46*(H24-G24) -> 0 | I46: =$C46*(I24-H24) -> 0
B47: Moving Carts | C47: 145 | D47: =$C47*D25 -> 1450 | E47: =$C47*(E25-D25) -> 832.26797 | F47: =$C47*(F25-E25) -> 1642.6128 | G47: =$C47*(G25-F25) -> 1187.0234 | H47: =$C47*(H25-G25) -> 2595.9304 | I47: =$C47*(I25-H25) -> 3830.6226
B48: Storage Bins | C48: 24 | D48: =$C48*D26 -> 1200 | E48: =$C48*(E26-D26) -> 1633.1602 | F48: =$C48*(F26-E26) -> 2039.1055 | G48: =$C48*(G26-F26) -> 1473.5462 | H48: =$C48*(H26-G26) -> 3222.5343 | I48: =$C48*(I26-H26) -> 4755.2557 | K48: CapEx Sensitivity
C49: TOTAL CAPEX | D49: =SUM(D31:D48) * $K$49 -> 83040.37 | E49: =SUM(E31:E48) * $K$49 -> 8292.1994 | F49: =SUM(F31:F48) * $K$49 -> 15013.686 | G49: =SUM(G31:G48) * $K$49 -> 7646.5788 | H49: =SUM(H31:H48) * $K$49 -> 13307.389 | I49: =SUM(I31:I48) * $K$49 -> 15393.662 | K49: 1
B52: DEPRECIATION (STRAIGHT-LINE)
B53: EQUIPMENT | C53: USEFUL LIFE | D53: START-UP D&A | E53: YEAR 1 D&A | F53: YEAR 2 D&A | G53: YEAR 3 D&A | H53: YEAR 4 D&A | I53: YEAR 5 D&A
B54: Injection Molding Machine | C54: =C6 -> 10 | E54: =$D31/C54 -> 1750 | F54: =SUM($D31:E31)/$C54 -> 1750 | G54: =SUM($D31:F31)/$C54 -> 1750 | H54: =SUM($D31:G31)/$C54 -> 1750 | I54: =SUM($D31:H31)/$C54 -> 1750
B55: Custom Steel Molds | C55: =C7 -> 7 | E55: =$D32/C55 -> 1285.7143 | F55: =SUM($D32:E32)/$C55 -> 1285.7143 | G55: =SUM($D32:F32)/$C55 -> 1285.7143 | H55: =SUM($D32:G32)/$C55 -> 1285.7143 | I55: =SUM($D32:H32)/$C55 -> 1285.7143
B56: Industrial Shelving/Storage | C56: =C8 -> 10 | E56: =$D33/C56 -> 56.181 | F56: =SUM($D33:E33)/$C56 -> 154.43395 | G56: =SUM($D33:F33)/$C56 -> 225.14937 | H56: =SUM($D33:G33)/$C56 -> 276.25141 | I56: =SUM($D33:H33)/$C56 -> 388.00771
B57: Forklift | C57: =C9 -> 10 | E57: =$D34/C57 -> 2500 | F57: =SUM($D34:E34)/$C57 -> 2500 | G57: =SUM($D34:F34)/$C57 -> 2500 | H57: =SUM($D34:G34)/$C57 -> 2500 | I57: =SUM($D34:H34)/$C57 -> 2500
B58: Industrial Shipping Label Printer | C58: =C10 -> 7 | E58: =$D35/C58 -> 1213.5714 | F58: =SUM($D35:E35)/$C58 -> 1213.5714 | G58: =SUM($D35:F35)/$C58 -> 1213.5714 | H58: =SUM($D35:G35)/$C58 -> 1213.5714 | I58: =SUM($D35:H35)/$C58 -> 1213.5714
B59: Wood Pallets | C59: =C11 -> 6 | E59: =$D36/C59 -> 41.666667 | F59: =SUM($D36:E36)/$C59 -> 98.373619 | G59: =SUM($D36:F36)/$C59 -> 169.1759 | H59: =SUM($D36:G36)/$C59 -> 220.34069 | I59: =SUM($D36:H36)/$C59 -> 332.23425
B60: Industrial Scale | C60: =C12 -> 10 | E60: =$D37/C60 -> 139.794 | F60: =SUM($D37:E37)/$C60 -> 139.794 | G60: =SUM($D37:F37)/$C60 -> 139.794 | H60: =SUM($D37:G37)/$C60 -> 139.794 | I60: =SUM($D37:H37)/$C60 -> 139.794
B61: 20ft Inventory Shipping Container | C61: =C13 -> 15 | E61: =$D38/C61 -> 153.26667 | F61: =SUM($D38:E38)/$C61 -> 153.26667 | G61: =SUM($D38:F38)/$C61 -> 153.26667 | H61: =SUM($D38:G38)/$C61 -> 153.26667 | I61: =SUM($D38:H38)/$C61 -> 153.26667
B62: Photocopier + Commercial Printer | C62: =C17 -> 5 | E62: =$D39/C62 -> 400 | F62: =SUM($D39:E39)/$C62 -> 400 | G62: =SUM($D39:F39)/$C62 -> 800 | H62: =SUM($D39:G39)/$C62 -> 800 | I62: =SUM($D39:H39)/$C62 -> 1200
B63: High-end Network Equipment (router, modem) | C63: =C18 -> 5 | E63: =$D40/C63 -> 140 | F63: =SUM($D40:E40)/$C63 -> 140 | G63: =SUM($D40:F40)/$C63 -> 280 | H63: =SUM($D40:G40)/$C63 -> 280 | I63: =SUM($D40:H40)/$C63 -> 420
B64: Laptops (managers) | C64: =C19 -> 3 | E64: =$D41/C64 -> 1000 | F64: =SUM($D41:E41)/$C64 -> 2000 | G64: =SUM($D41:F41)/$C64 -> 4500 | H64: =SUM($D41:G41)/$C64 -> 5500 | I64: =SUM($D41:H41)/$C64 -> 6500
B65: Desktops | C65: =C20 -> 3 | E65: =$D42/C65 -> 2333.3333 | F65: =SUM($D42:E42)/$C65 -> 2666.6667 | G65: =SUM($D42:F42)/$C65 -> 2666.6667 | H65: =SUM($D42:G42)/$C65 -> 3000 | I65: =SUM($D42:H42)/$C65 -> 3000
B66: Cell Phones | C66: =C21 -> 5 | E66: =$D43/C66 -> 168 | F66: =SUM($D43:E43)/$C66 -> 268.8 | G66: =SUM($D43:F43)/$C66 -> 268.8 | H66: =SUM($D43:G43)/$C66 -> 302.4 | I66: =SUM($D43:H43)/$C66 -> 302.4
B67: POS Device | C67: =C22 -> 5 | E67: =$D44/C67 -> 69.8 | F67: =SUM($D44:E44)/$C67 -> 69.8 | G67: =SUM($D44:F44)/$C67 -> 69.8 | H67: =SUM($D44:G44)/$C67 -> 69.8 | I67: =SUM($D44:H44)/$C67 -> 69.8
B68: Security Cameras & Equipment | C68: =C23 -> 5 | E68: =$D45/C68 -> 359.976 | F68: =SUM($D45:E45)/$C68 -> 359.976 | G68: =SUM($D45:F45)/$C68 -> 359.976 | H68: =SUM($D45:G45)/$C68 -> 359.976 | I68: =SUM($D45:H45)/$C68 -> 359.976
B69: Soldering Equipment | C69: =C24 -> 5 | E69: =$D46/C69 -> 39.548 | F69: =SUM($D46:E46)/$C69 -> 39.548 | G69: =SUM($D46:F46)/$C69 -> 39.548 | H69: =SUM($D46:G46)/$C69 -> 39.548 | I69: =SUM($D46:H46)/$C69 -> 39.548
B70: Moving Carts | C70: =C25 -> 5 | E70: =$D47/C70 -> 290 | F70: =SUM($D47:E47)/$C70 -> 456.45359 | G70: =SUM($D47:F47)/$C70 -> 784.97615 | H70: =SUM($D47:G47)/$C70 -> 1022.3808 | I70: =SUM($D47:H47)/$C70 -> 1541.5669
B71: Storage Bins | C71: =C26 -> 5 | E71: =$D48/C71 -> 240 | F71: =SUM($D48:E48)/$C71 -> 566.63205 | G71: =SUM($D48:F48)/$C71 -> 974.45316 | H71: =SUM($D48:G48)/$C71 -> 1269.1624 | I71: =SUM($D48:H48)/$C71 -> 1913.6693
C72: TOTAL D&A | D72: =SUM(D54:D71) -> 0 | E72: =SUM(E54:E71) -> 12180.851 | F72: =SUM(F54:F71) -> 14263.03 | G72: =SUM(G54:G71) -> 18180.892 | H72: =SUM(H54:H71) -> 20182.206 | I72: =SUM(I54:I71) -> 23109.548

Sheet OM IS Expenses
B2: INFORMATION SYSTEMS EXPENSE | C2: Year 0 | D2: Year 1 | E2: Year 2 | F2: Year 3 | G2: Year 4 | H2: Year 5 | J2: INFORMATION SYSTEMS PARAMETERS
B3: SOFTWARE | J3: Licenscing Fee | K3: 600
B4: Implementation & Training | C4: 20000 | D4: - | E4: - | F4: - | G4: - | H4: - | J4: MS Office 365 | K4: 22
B5: Licensing | C5: - | D5: =(K3*1)*12 -> 7200 | E5: =((K3*1.05)*1)*12 -> 7560 | F5: =((K3*1.05^2)*1)*12 -> 7938 | G5: =((K3*1.05^3)*2)*12 -> 16669.8 | H5: =((K3*1.05^4)*2)*12 -> 17503.29
B6: Maintenence Fee (5%) | C6: - | D6: =D5*0.05 -> 360 | E6: =E5*0.05 -> 378 | F6: =F5*0.05 -> 396.9 | G6: =G5*0.05 -> 833.49 | H6: =H5*0.05 -> 875.1645 | J6: Credit Card Processing | K6: 29
B7: Personal Productivity Software (Backup,Cloud,Security) | C7: - | D7: =(K$4*'OM G&A Expenses'!D19)*12 -> 3168 | E7: =((K4*1.05)*'OM G&A Expenses'!D40)*12 -> 3326.4 | F7: =((K4*1.05^2)*'OM G&A Expenses'!D63)*12 -> 4365.9 | G7: =((K4*1.05^3)*'OM G&A Expenses'!D87)*12 -> 5195.421 | H7: =((K4*1.05^4)*'OM G&A Expenses'!D114)*12 -> 6738.7666 | J7: Laptop | K7: 1500
B8: Credit Card Processing | C8: =K6*2 -> 58 | D8: =K11*12 -> 359.4 | E8: =D8*1.05 -> 377.37 | F8: =E8*1.05 -> 396.2385 | G8: =F8*1.05 -> 416.05043 | H8: =G8*1.05 -> 436.85295 | J8: Desktop | K8: 1000
J9: Phones | K9: 168
B10: Systems & Network Admin | C10: - | D10: 20000 | E10: 20000 | F10: 20000 | G10: 20000 | H10: 20000 | J10: Security Camera | K10: 149.99
B11: VPN | C11: - | D11: 1000 | E11: 1000 | F11: 1000 | G11: 1000 | H11: 1000 | J11: Credit Card Software | K11: =29.95 -> 29.95
B12: Firewall security software | C12: - | D12: 400 | E12: 400 | F12: 400 | G12: 400 | H12: 400 | J12: POS Device | K12: =349 -> 349
B13: Total Software Expense | C13: =SUM(C4:C12) -> 20058 | D13: =SUM(D4:D12) -> 32487.4 | E13: =SUM(E4:E12) -> 33041.77 | F13: =SUM(F4:F12) -> 34497.039 | G13: =SUM(G4:G12) -> 44514.761 | H13: =SUM(H4:H12) -> 46954.074 | J13: Website | K13: 25
B14: HARDWARE | J14: Internet | K14: 50
B15: Laptops | C15: - | D15: =K7*SUM('OM G&A Expenses'!C19,'OM G&A Expenses'!C21) -> 7500 | E15: =K7*('OM G&A Expenses'!C42-'OM G&A Expenses'!C21) -> 1500 | F15: - | G15: =(K7*('OM G&A Expenses'!C89-'OM G&A Expenses'!C65))+D15 -> 9000 | H15: =(K7*('OM G&A Expenses'!C116-'OM G&A Expenses'!C89))+E15 -> 3000
B16: Desktops | C16: - | D16: =K8*('OM G&A Expenses'!C23) -> 7000 | E16: - | F16: - | G16: =(K8*('OM G&A Expenses'!C91-'OM G&A Expenses'!C67))+D16 -> 8000 | H16: =(K8*('OM G&A Expenses'!C118-'OM G&A Expenses'!C91)) -> 2000
B17: Printers | C17: 750 | D17: - | E17: - | F17: 750 | G17: - | H17: -
B18: Photocopiers | C18: 1500 | D18: - | E18: - | F18: - | G18: - | H18: -
B19: High End Networking Equipment (Modem, Router, etc.) | C19: 350 | D19: - | E19: - | F19: - | G19: - | H19: -
B20: Point of sales devices | C20: =K12 -> 349 | D20: - | E20: - | F20: - | G20: - | H20: -
B21: Phones | C21: - | D21: =K9*4 -> 672 | E21: =K9*2 -> 336 | F21: =K9*3 -> 504 | G21: - | H21: =K9*2 -> 336
B22: Security Camera (Equipment + Monitorting) | C22: =149.99*12 -> 1799.88 | D22: =47.99*12 -> 575.88 | E22: =47.99*12 -> 575.88 | F22: =47.99*12 -> 575.88 | G22: =47.99*12 -> 575.88 | H22: =47.99*12 -> 575.88
B23: Total Hardware Expense | C23: =SUM(C15:C22) -> 4748.88 | D23: =SUM(D15:D22) -> 15747.88 | E23: =SUM(E15:E22) -> 2411.88 | F23: =SUM(F15:F22) -> 1829.88 | G23: =SUM(G15:G22) -> 17575.88 | H23: =SUM(H15:H22) -> 5911.88
B24: ONGOING MAINTENANCE
B25: WEBSITE DEVELOPMENT | C25: Year 0 | D25: Year 1 | E25: Year 2 | F25: Year 3 | G25: Year 4 | H25: Year 5
B26: Setup Cost | C26: =K13 -> 25 | D26: - | E26: - | F26: - | G26: - | H26: -
B27: Maintenence Cost | C27: - | D27: =$K$13*12 -> 300 | E27: =$K$13*12 -> 300 | F27: =$K$13*12 -> 300 | G27: =$K$13*12 -> 300 | H27: =$K$13*12 -> 300
B28: INTERNET, PHONE PLAN, ETC> | C28: Year 0 | D28: Year 1 | E28: Year 2 | F28: Year 3 | G28: Year 4 | H28: bhggh
B29: Internet Plan | C29: =$K$14 -> 50 | D29: =$K$14*12 -> 600 | E29: =$K$14*12 -> 600 | F29: =$K$14*12 -> 600 | G29: =$K$14*12 -> 600 | H29: =$K$14*12 -> 600
B30: Phone Service Plan | C30: - | D30: =(27*4)*12 -> 1296 | E30: =(21*6)*12 -> 1512 | F30: =(23*9)*12 -> 2484 | G30: =(21*6)*12 -> 1512 | H30: =(22*8)*12 -> 2112
B32: Total IS Expenses | C32: Year 0 | D32: Year 1 | E32: Year 2 | F32: Year 3 | G32: Year 4 | H32: Year 5
C33: =SUM(C13,C23,C26,C27,C29,C30) -> 24881.88 | D33: =SUM(D13,D23,D26,D27,D29,D30) -> 50431.28 | E33: =SUM(E13,E23,E26,E27,E29,E30) -> 37865.65 | F33: =SUM(F13,F23,F26,F27,F29,F30) -> 39710.918 | G33: =SUM(G13,G23,G26,G27,G29,G30) -> 64502.641 | H33: =SUM(H13,H23,H26,H27,H29,H30) -> 55877.954

Sheet OM Raw Material Data
B2: PRIMARY SUPPLIER RAW MATERIAL DATA
B3: COMPONENT | C3: COUNTRY OF ORIGIN | D3: LEAD TIME (DAYS) | E3: PCS NEEDED PER 1 UNIT | F3: COST FOR 1 PC (OQ<1K PCS) | G3: COST PER UNIT (OQ <1K PCs) | H3: COST FOR 1 PC (OQ 1K-10K UNITS) | I3: COST PER UNIT (OQ 1K-10K PCs) | J3: COST FOR 1 PC (OQ 10K+ UNITS) | K3: COST PER UNIT (OQ 10K+ PCs)
B4: Telescope Pole | C4: USA | D4: 4 | E4: 1 | F4: 1.47 | G4: =E4*F4 -> 1.47 | H4: 0.85 | I4: =E4*H4 -> 0.85 | J4: 0.85 | K4: =J4*E4 -> 0.85
B5: Safety Flag | C5: China | D5: 29 | E5: 1 | F5: 0.88 | G5: =E5*F5 -> 0.88 | H5: 0.8 | I5: =E5*H5 -> 0.8 | J5: 0.68 | K5: =J5*E5 -> 0.68
B6: Bike Mount | C6: China | D6: 24 | E6: 1 | F6: 1.8 | G6: =E6*F6 -> 1.8 | H6: 1.8 | I6: =E6*H6 -> 1.8 | J6: 1.8 | K6: =J6*E6 -> 1.8
B7: Speaker | C7: China | D7: 23 | E7: 1 | F7: 1.5 | G7: =E7*F7 -> 1.5 | H7: 1.5 | I7: =E7*H7 -> 1.5 | J7: 1.5 | K7: =J7*E7 -> 1.5
B8: Battery Pack | C8: China | D8: 29 | E8: 1 | F8: 0.35 | G8: =E8*F8 -> 0.35 | H8: 0.22 | I8: =E8*H8 -> 0.22 | J8: 0.09 | K8: =J8*E8 -> 0.09
B9: Attachable Spoke Magnet | C9: China | D9: 29 | E9: 1 | F9: 0.8 | G9: =E9*F9 -> 0.8 | H9: 0.6 | I9: =E9*H9 -> 0.6 | J9: 0.6 | K9: =J9*E9 -> 0.6
B10: PCB | C10: China | D10: 23 | E10: 1 | F10: 0.5 | G10: =E10*F10 -> 0.5 | H10: 0.3 | I10: =E10*H10 -> 0.3 | J10: 0.1 | K10: =J10*E10 -> 0.1
B11: Wiring (meters) | C11: China | D11: 23 | E11: 0.5 | F11: 0.18 | G11: =E11*F11 -> 0.09 | H11: 0.15 | I11: =E11*H11 -> 0.075 | J11: 0.13 | K11: =E11*J11 -> 0.065
B12: Light | C12: China | D12: 23 | E12: 1 | F12: 0.32 | G12: =E12*F12 -> 0.32 | H12: 0.25 | I12: =E12*H12 -> 0.25 | J12: 0.11 | K12: =E12*J12 -> 0.11
B13: Assembly Screws | C13: China | D13: 23 | E13: 12 | F13: 0.02 | G13: =E13*F13 -> 0.24 | H13: 0.02 | I13: =E13*H13 -> 0.24 | J13: 0.02 | K13: =J13*E13 -> 0.24
B14: Hall Magnetic Sensor | C14: Malaysia | D14: 33 | E14: 1 | F14: 0.21 | G14: =E14*F14 -> 0.21 | H14: 0.18 | I14: =E14*H14 -> 0.18 | J14: 0.18 | K14: =J14*E14 -> 0.18
B15: Pellets (lbs) | C15: USA | D15: 4 | E15: 0.25 | F15: 1.5 | G15: =F15*E15 -> 0.375 | H15: 1.5 | I15: =H15*E15 -> 0.375 | J15: 1.5 | K15: =J15*E15 -> 0.375
B16: Custom Shells | C16: China | D16: 29 | E16: 1 | F16: 1 | G16: =F16*E16 -> 1 | H16: 0.5 | I16: =H16*E16 -> 0.5 | J16: 0.1 | K16: =J16*E16 -> 0.1
C17: AVERAGE LEAD TIME: | D17: =AVERAGE(D4:D16) -> 22.769231 | F17: TOTAL COST PER UNIT: | G17: =SUM(G4:G16) -> 9.535 | I17: =SUM(I4:I16) -> 7.69 | K17: =SUM(K4:K16) -> 6.69
B19: SECONDARY SUPPLIER IN THE EVENT OF EXTREME TARIFFS RAW MATERIAL DATA
B20: COMPONENT | C20: COUNTRY OF ORIGIN | D20: LEAD TIME (DAYS) | E20: PCS NEEDED PER 1 UNIT | F20: COST FOR 1 PC (OQ<1K PCS) | G20: COST PER UNIT (OQ <1K PCS) | H20: COST FOR 1 PC (OQ 1K-10K UNITS) | I20: COST PER UNIT (OQ 1K-10K Units) | J20: COST FOR 1 PC (OQ 10K+ UNITS) | K20: COST PER UNIT (OQ 10K+)
B21: Telescope Pole | C21: USA | D21: 4 | E21: 1 | F21: 1.47 | G21: =E21*F21 -> 1.47 | H21: 0.85 | I21: =E21*H21 -> 0.85 | J21: 0.85 | K21: =J21*E21 -> 0.85 | L21: USA
B22: Safety Flag | C22: USA | D22: 4 | E22: 1 | F22: 1.61 | G22: =E22*F22 -> 1.61 | H22: 1.61 | I22: =E22*H22 -> 1.61 | J22: 1.61 | K22: =J22*E22 -> 1.61 | L22: USA
B23: Bike Mount | C23: China | D23: 24 | E23: 1 | F23: 1.8 | G23: =E23*F23 -> 1.8 | H23: 1.8 | I23: =E23*H23 -> 1.8 | J23: 1.8 | K23: 1.8 | L23: China
B24: Speaker | C24: USA | D24: 4 | E24: 1 | F24: 1.45 | G24: =E24*F24 -> 1.45 | H24: 1.35 | I24: =E24*H24 -> 1.35 | J24: 1.35 | K24: =J24*E24 -> 1.35 | L24: USA
B25: Battery Pack | C25: USA | D25: 4 | E25: 1 | F25: 0.99 | G25: =E25*F25 -> 0.99 | H25: 0.69 | I25: =E25*H25 -> 0.69 | J25: 0.69 | K25: =J25*E25 -> 0.69 | L25: USA
B26: Attachable Spoke Magnet | C26: China | D26: 29 | E26: 1 | F26: 0.8 | G26: =E26*F26 -> 0.8 | H26: 0.6 | I26: =E26*H26 -> 0.6 | J26: 0.6 | K26: 0.6 | L26: China
B27: PCB | C27: China | D27: 23 | E27: 1 | F27: 0.5 | G27: =E27*F27 -> 0.5 | H27: 0.3 | I27: =E27*H27 -> 0.3 | J27: 0.1 | K27: 0.1 | L27: China
B28: Wiring (meters) | C28: USA | D28: 4 | E28: 0.5 | F28: 0.3 | G28: =E28*F28 -> 0.15 | H28: 0.3 | I28: =E28*H28 -> 0.15 | J28: 0.3 | K28: =E28*J28 -> 0.15 | L28: USA
B29: Light | C29: China | D29: 23 | E29: 1 | F29: 0.32 | G29: =E29*F29 -> 0.32 | H29: 0.25 | I29: =E29*H29 -> 0.25 | J29: 0.11 | K29: =E29*J29 -> 0.11 | L29: China
B30: Assembly Screws | C30: China | D30: 23 | E30: 12 | F30: 0.02 | G30: =E30*F30 -> 0.24 | H30: 0.02 | I30: =E30*H30 -> 0.24 | J30: 0.02 | K30: =J30*E30 -> 0.24 | L30: China
B31: Hall Magnetic Sensor | C31: Malaysia | D31: 33 | E31: 1 | F31: 0.21 | G31: =E31*F31 -> 0.21 | H31: 0.18 | I31: =E31*H31 -> 0.18 | J31: 0.18 | K31: =J31*E31 -> 0.18 | L31: Malaysia
B32: Pellets (lbs) | C32: USA | D32: 4 | E32: 0.25 | F32: 1.5 | G32: =F32*E32 -> 0.375 | H32: 1.5 | I32: =H32*E32 -> 0.375 | J32: 1.5 | K32: =J32*E32 -> 0.375 | L32: USA
B33: Custom Shells | C33: China | D33: 29 | E33: 1 | F33: 1 | G33: =F33*E33 -> 1 | H33: 0.5 | I33: =H33*E33 -> 0.5 | J33: 0.1 | K33: 0.1 | L33: China
C34: AVERAGE LEAD TIME | D34: =AVERAGE(D21:D33) -> 16 | F34: TOTAL COST PER UNIT: | G34: =SUM(G21:G33) -> 10.915 | I34: =SUM(I21:I33) -> 8.895 | K34: =SUM(K21:K33) -> 8.155
B36: YEAR 1 RAW MATERIAL INVENTORY (PRIMARY SUPPLIERS)
B37: COMPONENT | C37: CYCLE STOCK UNITS | D37: CYCLE STOCK VALUE | E37: SAFETY STOCK UNITS | F37: SAFETY STOCK VALUE | G37: TOTAL RM INVENTORY VALUE
B38: Telescope Pole | C38: ='OM Inventory'!$C$7*E4 -> 5902.4172 | D38: =C38*IF('OM Direct Materials & Direct La'!$H$23<1000,F4,IF('OM Direct Materials & Direct La'!$H$23>10000,J4,H4)) -> 5017.0546 | E38: ='OM Inventory'!$C$8*E4 -> 3253.6446 | F38: =E38*IF('OM Direct Materials & Direct La'!$H$23<1000,F4,IF('OM Direct Materials & Direct La'!$H$23>10000,J4,H4)) -> 2765.5979 | G38: =D38+F38 -> 7782.6525
B39: Safety Flag | C39: ='OM Inventory'!$C$7*E5 -> 5902.4172 | D39: =C39*IF('OM Direct Materials & Direct La'!$H$23<1000,F5,IF('OM Direct Materials & Direct La'!$H$23>10000,J5,H5)) -> 4013.6437 | E39: ='OM Inventory'!$C$8*E5 -> 3253.6446 | F39: =E39*IF('OM Direct Materials & Direct La'!$H$23<1000,F5,IF('OM Direct Materials & Direct La'!$H$23>10000,J5,H5)) -> 2212.4783 | G39: =D39+F39 -> 6226.122
B40: Bike Mount | C40: ='OM Inventory'!$C$7*E6 -> 5902.4172 | D40: =C40*IF('OM Direct Materials & Direct La'!$H$23<1000,F6,IF('OM Direct Materials & Direct La'!$H$23>10000,J6,H6)) -> 10624.351 | E40: ='OM Inventory'!$C$8*E6 -> 3253.6446 | F40: =E40*IF('OM Direct Materials & Direct La'!$H$23<1000,F6,IF('OM Direct Materials & Direct La'!$H$23>10000,J6,H6)) -> 5856.5602 | G40: =D40+F40 -> 16480.911
B41: Speaker | C41: ='OM Inventory'!$C$7*E7 -> 5902.4172 | D41: =C41*IF('OM Direct Materials & Direct La'!$H$23<1000,F7,IF('OM Direct Materials & Direct La'!$H$23>10000,J7,H7)) -> 8853.6257 | E41: ='OM Inventory'!$C$8*E7 -> 3253.6446 | F41: =E41*IF('OM Direct Materials & Direct La'!$H$23<1000,F7,IF('OM Direct Materials & Direct La'!$H$23>10000,J7,H7)) -> 4880.4669 | G41: =D41+F41 -> 13734.093
B42: Battery Pack | C42: ='OM Inventory'!$C$7*E8 -> 5902.4172 | D42: =C42*IF('OM Direct Materials & Direct La'!$H$23<1000,F8,IF('OM Direct Materials & Direct La'!$H$23>10000,J8,H8)) -> 531.21754 | E42: ='OM Inventory'!$C$8*E8 -> 3253.6446 | F42: =E42*IF('OM Direct Materials & Direct La'!$H$23<1000,F8,IF('OM Direct Materials & Direct La'!$H$23>10000,J8,H8)) -> 292.82801 | G42: =D42+F42 -> 824.04556
B43: Attachable Spoke Magnet | C43: ='OM Inventory'!$C$7*E9 -> 5902.4172 | D43: =C43*IF('OM Direct Materials & Direct La'!$H$23<1000,F9,IF('OM Direct Materials & Direct La'!$H$23>10000,J9,H9)) -> 3541.4503 | E43: ='OM Inventory'!$C$8*E9 -> 3253.6446 | F43: =E43*IF('OM Direct Materials & Direct La'!$H$23<1000,F9,IF('OM Direct Materials & Direct La'!$H$23>10000,J9,H9)) -> 1952.1867 | G43: =D43+F43 -> 5493.637
B44: PCB | C44: ='OM Inventory'!$C$7*E10 -> 5902.4172 | D44: =C44*IF('OM Direct Materials & Direct La'!$H$23<1000,F10,IF('OM Direct Materials & Direct La'!$H$23>10000,J10,H10)) -> 590.24172 | E44: ='OM Inventory'!$C$8*E10 -> 3253.6446 | F44: =E44*IF('OM Direct Materials & Direct La'!$H$23<1000,F10,IF('OM Direct Materials & Direct La'!$H$23>10000,J10,H10)) -> 325.36446 | G44: =D44+F44 -> 915.60617
B45: Wiring (meters) | C45: ='OM Inventory'!$C$7*E11 -> 2951.2086 | D45: =C45*IF('OM Direct Materials & Direct La'!$H$23<1000,F11,IF('OM Direct Materials & Direct La'!$H$23>10000,J11,H11)) -> 383.65712 | E45: ='OM Inventory'!$C$8*E11 -> 1626.8223 | F45: =E45*IF('OM Direct Materials & Direct La'!$H$23<1000,F11,IF('OM Direct Materials & Direct La'!$H$23>10000,J11,H11)) -> 211.4869 | G45: =D45+F45 -> 595.14401
B46: Light | C46: ='OM Inventory'!$C$7*E12 -> 5902.4172 | D46: =C46*IF('OM Direct Materials & Direct La'!$H$23<1000,F12,IF('OM Direct Materials & Direct La'!$H$23>10000,J12,H12)) -> 649.26589 | E46: ='OM Inventory'!$C$8*E12 -> 3253.6446 | F46: =E46*IF('OM Direct Materials & Direct La'!$H$23<1000,F12,IF('OM Direct Materials & Direct La'!$H$23>10000,J12,H12)) -> 357.9009 | G46: =D46+F46 -> 1007.1668
B47: Assembly Screws | C47: ='OM Inventory'!$C$7*E13 -> 70829.006 | D47: =C47*IF('OM Direct Materials & Direct La'!$H$23<1000,F13,IF('OM Direct Materials & Direct La'!$H$23>10000,J13,H13)) -> 1416.5801 | E47: ='OM Inventory'!$C$8*E13 -> 39043.735 | F47: =E47*IF('OM Direct Materials & Direct La'!$H$23<1000,F13,IF('OM Direct Materials & Direct La'!$H$23>10000,J13,H13)) -> 780.8747 | G47: =D47+F47 -> 2197.4548
B48: Hall Magnetic Sensor | C48: ='OM Inventory'!$C$7*E14 -> 5902.4172 | D48: =C48*IF('OM Direct Materials & Direct La'!$H$23<1000,F14,IF('OM Direct Materials & Direct La'!$H$23>10000,J14,H14)) -> 1062.4351 | E48: ='OM Inventory'!$C$8*E14 -> 3253.6446 | F48: =E48*IF('OM Direct Materials & Direct La'!$H$23<1000,F14,IF('OM Direct Materials & Direct La'!$H$23>10000,J14,H14)) -> 585.65602 | G48: =D48+F48 -> 1648.0911
B49: Pellets (lbs) | C49: ='OM Inventory'!$C$7*E15 -> 1475.6043 | D49: =C49*IF('OM Direct Materials & Direct La'!$H$23<1000,F15,IF('OM Direct Materials & Direct La'!$H$23>10000,J15,H15)) -> 2213.4064 | E49: ='OM Inventory'!$C$8*E15 -> 813.41115 | F49: =E49*IF('OM Direct Materials & Direct La'!$H$23<1000,F15,IF('OM Direct Materials & Direct La'!$H$23>10000,J15,H15)) -> 1220.1167 | G49: =D49+F49 -> 3433.5232
B50: Custom Shells | C50: ='OM Inventory'!$C$7*E16 -> 5902.4172 | D50: =C50*IF('OM Direct Materials & Direct La'!$H$23<1000,F16,IF('OM Direct Materials & Direct La'!$H$23>10000,J16,H16)) -> 590.24172 | E50: ='OM Inventory'!$C$8*E16 -> 3253.6446 | F50: =E50*IF('OM Direct Materials & Direct La'!$H$23<1000,F16,IF('OM Direct Materials & Direct La'!$H$23>10000,J16,H16)) -> 325.36446 | G50: =D50+F50 -> 915.60617
F51: TOTAL: | G51: =SUM(G37:G50) -> 61254.053
B53: YEAR 2 RAW MATERIAL INVENTORY (PRIMARY SUPPLIERS)
B54: COMPONENT | C54: CYCLE STOCK UNITS | D54: CYCLE STOCK VALUE | E54: SAFETY STOCK UNITS | F54: SAFETY STOCK VALUE | G54: TOTAL RM INVENTORY VALUE
B55: Telescope Pole | C55: ='OM Inventory'!$C$14*E4 -> 6767.0358 | D55: =C55*IF('OM Direct Materials & Direct La'!$H$41<1000,F4,IF('OM Direct Materials & Direct La'!$H$41>10000,J4,H4)) -> 5751.9804 | E55: ='OM Inventory'!$C$15*E4 -> 4665.8267 | F55: =E55*IF('OM Direct Materials & Direct La'!$H$41<1000,F4,IF('OM Direct Materials & Direct La'!$H$41>10000,J4,H4)) -> 3965.9527 | G55: =D55+F55 -> 9717.9332
B56: Safety Flag | C56: ='OM Inventory'!$C$14*E5 -> 6767.0358 | D56: =C56*IF('OM Direct Materials & Direct La'!$H$41<1000,F5,IF('OM Direct Materials & Direct La'!$H$41>10000,J5,H5)) -> 4601.5844 | E56: ='OM Inventory'!$C$15*E5 -> 4665.8267 | F56: =E56*IF('OM Direct Materials & Direct La'!$H$41<1000,F5,IF('OM Direct Materials & Direct La'!$H$41>10000,J5,H5)) -> 3172.7622 | G56: =D56+F56 -> 7774.3465
B57: Bike Mount | C57: ='OM Inventory'!$C$14*E6 -> 6767.0358 | D57: =C57*IF('OM Direct Materials & Direct La'!$H$41<1000,F6,IF('OM Direct Materials & Direct La'!$H$41>10000,J6,H6)) -> 12180.664 | E57: ='OM Inventory'!$C$15*E6 -> 4665.8267 | F57: =E57*IF('OM Direct Materials & Direct La'!$H$41<1000,F6,IF('OM Direct Materials & Direct La'!$H$41>10000,J6,H6)) -> 8398.4881 | G57: =D57+F57 -> 20579.153
B58: Speaker | C58: ='OM Inventory'!$C$14*E7 -> 6767.0358 | D58: =C58*IF('OM Direct Materials & Direct La'!$H$41<1000,F7,IF('OM Direct Materials & Direct La'!$H$41>10000,J7,H7)) -> 10150.554 | E58: ='OM Inventory'!$C$15*E7 -> 4665.8267 | F58: =E58*IF('OM Direct Materials & Direct La'!$H$41<1000,F7,IF('OM Direct Materials & Direct La'!$H$41>10000,J7,H7)) -> 6998.7401 | G58: =D58+F58 -> 17149.294
B59: Battery Pack | C59: ='OM Inventory'!$C$14*E8 -> 6767.0358 | D59: =C59*IF('OM Direct Materials & Direct La'!$H$41<1000,F8,IF('OM Direct Materials & Direct La'!$H$41>10000,J8,H8)) -> 609.03322 | E59: ='OM Inventory'!$C$15*E8 -> 4665.8267 | F59: =E59*IF('OM Direct Materials & Direct La'!$H$41<1000,F8,IF('OM Direct Materials & Direct La'!$H$41>10000,J8,H8)) -> 419.92441 | G59: =D59+F59 -> 1028.9576
B60: Attachable Spoke Magnet | C60: ='OM Inventory'!$C$14*E9 -> 6767.0358 | D60: =C60*IF('OM Direct Materials & Direct La'!$H$41<1000,F9,IF('OM Direct Materials & Direct La'!$H$41>10000,J9,H9)) -> 4060.2215 | E60: ='OM Inventory'!$C$15*E9 -> 4665.8267 | F60: =E60*IF('OM Direct Materials & Direct La'!$H$41<1000,F9,IF('OM Direct Materials & Direct La'!$H$41>10000,J9,H9)) -> 2799.496 | G60: =D60+F60 -> 6859.7175
B61: PCB | C61: ='OM Inventory'!$C$14*E10 -> 6767.0358 | D61: =C61*IF('OM Direct Materials & Direct La'!$H$41<1000,F10,IF('OM Direct Materials & Direct La'!$H$41>10000,J10,H10)) -> 676.70358 | E61: ='OM Inventory'!$C$15*E10 -> 4665.8267 | F61: =E61*IF('OM Direct Materials & Direct La'!$H$41<1000,F10,IF('OM Direct Materials & Direct La'!$H$41>10000,J10,H10)) -> 466.58267 | G61: =D61+F61 -> 1143.2863
B62: Wiring (meters) | C62: ='OM Inventory'!$C$14*E11 -> 3383.5179 | D62: =C62*IF('OM Direct Materials & Direct La'!$H$41<1000,F11,IF('OM Direct Materials & Direct La'!$H$41>10000,J11,H11)) -> 439.85733 | E62: ='OM Inventory'!$C$15*E11 -> 2332.9134 | F62: =E62*IF('OM Direct Materials & Direct La'!$H$41<1000,F11,IF('OM Direct Materials & Direct La'!$H$41>10000,J11,H11)) -> 303.27874 | G62: =D62+F62 -> 743.13607
B63: Light | C63: ='OM Inventory'!$C$14*E12 -> 6767.0358 | D63: =C63*IF('OM Direct Materials & Direct La'!$H$41<1000,F12,IF('OM Direct Materials & Direct La'!$H$41>10000,J12,H12)) -> 744.37394 | E63: ='OM Inventory'!$C$15*E12 -> 4665.8267 | F63: =E63*IF('OM Direct Materials & Direct La'!$H$41<1000,F12,IF('OM Direct Materials & Direct La'!$H$41>10000,J12,H12)) -> 513.24094 | G63: =D63+F63 -> 1257.6149
B64: Assembly Screws | C64: ='OM Inventory'!$C$14*E13 -> 81204.43 | D64: =C64*IF('OM Direct Materials & Direct La'!$H$41<1000,F13,IF('OM Direct Materials & Direct La'!$H$41>10000,J13,H13)) -> 1624.0886 | E64: ='OM Inventory'!$C$15*E13 -> 55989.921 | F64: =E64*IF('OM Direct Materials & Direct La'!$H$41<1000,F13,IF('OM Direct Materials & Direct La'!$H$41>10000,J13,H13)) -> 1119.7984 | G64: =D64+F64 -> 2743.887
B65: Hall Magnetic Sensor | C65: ='OM Inventory'!$C$14*E14 -> 6767.0358 | D65: =C65*IF('OM Direct Materials & Direct La'!$H$41<1000,F14,IF('OM Direct Materials & Direct La'!$H$41>10000,J14,H14)) -> 1218.0664 | E65: ='OM Inventory'!$C$15*E14 -> 4665.8267 | F65: =E65*IF('OM Direct Materials & Direct La'!$H$41<1000,F14,IF('OM Direct Materials & Direct La'!$H$41>10000,J14,H14)) -> 839.84881 | G65: =D65+F65 -> 2057.9153
B66: Pellets (lbs) | C66: ='OM Inventory'!$C$14*E15 -> 1691.759 | D66: =C66*IF('OM Direct Materials & Direct La'!$H$41<1000,F15,IF('OM Direct Materials & Direct La'!$H$41>10000,J15,H15)) -> 2537.6384 | E66: ='OM Inventory'!$C$15*E15 -> 1166.4567 | F66: =E66*IF('OM Direct Materials & Direct La'!$H$41<1000,F15,IF('OM Direct Materials & Direct La'!$H$41>10000,J15,H15)) -> 1749.685 | G66: =D66+F66 -> 4287.3235
B67: Custom Shells | C67: ='OM Inventory'!$C$14*E16 -> 6767.0358 | D67: =C67*IF('OM Direct Materials & Direct La'!$H$41<1000,F16,IF('OM Direct Materials & Direct La'!$H$41>10000,J16,H16)) -> 676.70358 | E67: ='OM Inventory'!$C$15*E16 -> 4665.8267 | F67: =E67*IF('OM Direct Materials & Direct La'!$H$41<1000,F16,IF('OM Direct Materials & Direct La'!$H$41>10000,J16,H16)) -> 466.58267 | G67: =D67+F67 -> 1143.2863
F68: TOTAL: | G68: =SUM(G54:G67) -> 76485.85
B70: YEAR 3 RAW MATERIAL INVENTORY (PRIMARY SUPPLIERS)
B71: COMPONENT | C71: CYCLE STOCK UNITS | D71: CYCLE STOCK VALUE | E71: SAFETY STOCK UNITS | F71: SAFETY STOCK VALUE | G71: TOTAL RM INVENTORY VALUE
B72: Telescope Pole | C72: ='OM Inventory'!$C$21*E4 -> 6610.2208 | D72: =C72*IF('OM Direct Materials & Direct La'!$H$58<1000,$F4,IF('OM Direct Materials & Direct La'!$H$58>10000,$J4,$H4)) -> 5618.6877 | E72: ='OM Inventory'!$C$22*E4 -> 7287.6277 | F72: =E72*IF('OM Direct Materials & Direct La'!$H$58<1000,$F4,IF('OM Direct Materials & Direct La'!$H$58>10000,$J4,$H4)) -> 6194.4835 | G72: =D72+F72 -> 11813.171
B73: Safety Flag | C73: ='OM Inventory'!$C$21*E5 -> 6610.2208 | D73: =C73*IF('OM Direct Materials & Direct La'!$H$58<1000,$F5,IF('OM Direct Materials & Direct La'!$H$58>10000,$J5,$H5)) -> 4494.9502 | E73: ='OM Inventory'!$C$22*E5 -> 7287.6277 | F73: =E73*IF('OM Direct Materials & Direct La'!$H$58<1000,$F5,IF('OM Direct Materials & Direct La'!$H$58>10000,$J5,$H5)) -> 4955.5868 | G73: =D73+F73 -> 9450.537
B74: Bike Mount | C74: ='OM Inventory'!$C$21*E6 -> 6610.2208 | D74: =C74*IF('OM Direct Materials & Direct La'!$H$58<1000,$F6,IF('OM Direct Materials & Direct La'!$H$58>10000,$J6,$H6)) -> 11898.398 | E74: ='OM Inventory'!$C$22*E6 -> 7287.6277 | F74: =E74*IF('OM Direct Materials & Direct La'!$H$58<1000,$F6,IF('OM Direct Materials & Direct La'!$H$58>10000,$J6,$H6)) -> 13117.73 | G74: =D74+F74 -> 25016.127
B75: Speaker | C75: ='OM Inventory'!$C$21*E7 -> 6610.2208 | D75: =C75*IF('OM Direct Materials & Direct La'!$H$58<1000,$F7,IF('OM Direct Materials & Direct La'!$H$58>10000,$J7,$H7)) -> 9915.3313 | E75: ='OM Inventory'!$C$22*E7 -> 7287.6277 | F75: =E75*IF('OM Direct Materials & Direct La'!$H$58<1000,$F7,IF('OM Direct Materials & Direct La'!$H$58>10000,$J7,$H7)) -> 10931.441 | G75: =D75+F75 -> 20846.773
B76: Battery Pack | C76: ='OM Inventory'!$C$21*E8 -> 6610.2208 | D76: =C76*IF('OM Direct Materials & Direct La'!$H$58<1000,$F8,IF('OM Direct Materials & Direct La'!$H$58>10000,$J8,$H8)) -> 594.91988 | E76: ='OM Inventory'!$C$22*E8 -> 7287.6277 | F76: =E76*IF('OM Direct Materials & Direct La'!$H$58<1000,$F8,IF('OM Direct Materials & Direct La'!$H$58>10000,$J8,$H8)) -> 655.88649 | G76: =D76+F76 -> 1250.8064
B77: Attachable Spoke Magnet | C77: ='OM Inventory'!$C$21*E9 -> 6610.2208 | D77: =C77*IF('OM Direct Materials & Direct La'!$H$58<1000,$F9,IF('OM Direct Materials & Direct La'!$H$58>10000,$J9,$H9)) -> 3966.1325 | E77: ='OM Inventory'!$C$22*E9 -> 7287.6277 | F77: =E77*IF('OM Direct Materials & Direct La'!$H$58<1000,$F9,IF('OM Direct Materials & Direct La'!$H$58>10000,$J9,$H9)) -> 4372.5766 | G77: =D77+F77 -> 8338.7091
B78: PCB | C78: ='OM Inventory'!$C$21*E10 -> 6610.2208 | D78: =C78*IF('OM Direct Materials & Direct La'!$H$58<1000,$F10,IF('OM Direct Materials & Direct La'!$H$58>10000,$J10,$H10)) -> 661.02208 | E78: ='OM Inventory'!$C$22*E10 -> 7287.6277 | F78: =E78*IF('OM Direct Materials & Direct La'!$H$58<1000,$F10,IF('OM Direct Materials & Direct La'!$H$58>10000,$J10,$H10)) -> 728.76277 | G78: =D78+F78 -> 1389.7849
B79: Wiring (meters) | C79: ='OM Inventory'!$C$21*E11 -> 3305.1104 | D79: =C79*IF('OM Direct Materials & Direct La'!$H$58<1000,$F11,IF('OM Direct Materials & Direct La'!$H$58>10000,$J11,$H11)) -> 429.66436 | E79: ='OM Inventory'!$C$22*E11 -> 3643.8138 | F79: =E79*IF('OM Direct Materials & Direct La'!$H$58<1000,$F11,IF('OM Direct Materials & Direct La'!$H$58>10000,$J11,$H11)) -> 473.6958 | G79: =D79+F79 -> 903.36015
B80: Light | C80: ='OM Inventory'!$C$21*E12 -> 6610.2208 | D80: =C80*IF('OM Direct Materials & Direct La'!$H$58<1000,$F12,IF('OM Direct Materials & Direct La'!$H$58>10000,$J12,$H12)) -> 727.12429 | E80: ='OM Inventory'!$C$22*E12 -> 7287.6277 | F80: =E80*IF('OM Direct Materials & Direct La'!$H$58<1000,$F12,IF('OM Direct Materials & Direct La'!$H$58>10000,$J12,$H12)) -> 801.63904 | G80: =D80+F80 -> 1528.7633
B81: Assembly Screws | C81: ='OM Inventory'!$C$21*E13 -> 79322.65 | D81: =C81*IF('OM Direct Materials & Direct La'!$H$58<1000,$F13,IF('OM Direct Materials & Direct La'!$H$58>10000,$J13,$H13)) -> 1586.453 | E81: ='OM Inventory'!$C$22*E13 -> 87451.532 | F81: =E81*IF('OM Direct Materials & Direct La'!$H$58<1000,$F13,IF('OM Direct Materials & Direct La'!$H$58>10000,$J13,$H13)) -> 1749.0306 | G81: =D81+F81 -> 3335.4836
B82: Hall Magnetic Sensor | C82: ='OM Inventory'!$C$21*E14 -> 6610.2208 | D82: =C82*IF('OM Direct Materials & Direct La'!$H$58<1000,$F14,IF('OM Direct Materials & Direct La'!$H$58>10000,$J14,$H14)) -> 1189.8398 | E82: ='OM Inventory'!$C$22*E14 -> 7287.6277 | F82: =E82*IF('OM Direct Materials & Direct La'!$H$58<1000,$F14,IF('OM Direct Materials & Direct La'!$H$58>10000,$J14,$H14)) -> 1311.773 | G82: =D82+F82 -> 2501.6127
B83: Pellets (lbs) | C83: ='OM Inventory'!$C$21*E15 -> 1652.5552 | D83: =C83*IF('OM Direct Materials & Direct La'!$H$58<1000,$F15,IF('OM Direct Materials & Direct La'!$H$58>10000,$J15,$H15)) -> 2478.8328 | E83: ='OM Inventory'!$C$22*E15 -> 1821.9069 | F83: =E83*IF('OM Direct Materials & Direct La'!$H$58<1000,$F15,IF('OM Direct Materials & Direct La'!$H$58>10000,$J15,$H15)) -> 2732.8604 | G83: =D83+F83 -> 5211.6932
B84: Custom Shells | C84: ='OM Inventory'!$C$21*E16 -> 6610.2208 | D84: =C84*IF('OM Direct Materials & Direct La'!$H$58<1000,$F16,IF('OM Direct Materials & Direct La'!$H$58>10000,$J16,$H16)) -> 661.02208 | E84: ='OM Inventory'!$C$22*E16 -> 7287.6277 | F84: =E84*IF('OM Direct Materials & Direct La'!$H$58<1000,$F16,IF('OM Direct Materials & Direct La'!$H$58>10000,$J16,$H16)) -> 728.76277 | G84: =D84+F84 -> 1389.7849
F85: TOTAL: | G85: =SUM(G71:G84) -> 92976.606
B87: YEAR 4 RAW MATERIAL INVENTORY (PRIMARY SUPPLIERS)
B88: COMPONENT | C88: CYCLE STOCK UNITS | D88: CYCLE STOCK VALUE | E88: SAFETY STOCK UNITS | F88: SAFETY STOCK VALUE | G88: TOTAL RM INVENTORY VALUE
B89: Telescope Pole | C89: ='OM Inventory'!$C$28*E4 -> 7973.6219 | D89: =C89*IF('OM Direct Materials & Direct La'!$H$75<1000,$F4,IF('OM Direct Materials & Direct La'!$H$75>10000,$J4,$H4)) -> 6777.5786 | E89: ='OM Inventory'!$C$29*E4 -> 9162.9332 | F89: =E89*IF('OM Direct Materials & Direct La'!$H$75<1000,F4,IF('OM Direct Materials & Direct La'!$H$75>9999,J4,H4)) -> 7788.4932 | G89: =D89+F89 -> 14566.072
B90: Safety Flag | C90: ='OM Inventory'!$C$28*E5 -> 7973.6219 | D90: =C90*IF('OM Direct Materials & Direct La'!$H$75<1000,$F5,IF('OM Direct Materials & Direct La'!$H$75>10000,$J5,$H5)) -> 5422.0629 | E90: ='OM Inventory'!$C$29*E5 -> 9162.9332 | F90: =E90*IF('OM Direct Materials & Direct La'!$H$75<1000,F5,IF('OM Direct Materials & Direct La'!$H$75>9999,J5,H5)) -> 6230.7946 | G90: =D90+F90 -> 11652.857
B91: Bike Mount | C91: ='OM Inventory'!$C$28*E6 -> 7973.6219 | D91: =C91*IF('OM Direct Materials & Direct La'!$H$75<1000,$F6,IF('OM Direct Materials & Direct La'!$H$75>10000,$J6,$H6)) -> 14352.519 | E91: ='OM Inventory'!$C$29*E6 -> 9162.9332 | F91: =E91*IF('OM Direct Materials & Direct La'!$H$75<1000,F6,IF('OM Direct Materials & Direct La'!$H$75>9999,J6,H6)) -> 16493.28 | G91: =D91+F91 -> 30845.799
B92: Speaker | C92: ='OM Inventory'!$C$28*E7 -> 7973.6219 | D92: =C92*IF('OM Direct Materials & Direct La'!$H$75<1000,$F7,IF('OM Direct Materials & Direct La'!$H$75>10000,$J7,$H7)) -> 11960.433 | E92: ='OM Inventory'!$C$29*E7 -> 9162.9332 | F92: =E92*IF('OM Direct Materials & Direct La'!$H$75<1000,F7,IF('OM Direct Materials & Direct La'!$H$75>9999,J7,H7)) -> 13744.4 | G92: =D92+F92 -> 25704.833
B93: Battery Pack | C93: ='OM Inventory'!$C$28*E8 -> 7973.6219 | D93: =C93*IF('OM Direct Materials & Direct La'!$H$75<1000,$F8,IF('OM Direct Materials & Direct La'!$H$75>10000,$J8,$H8)) -> 717.62597 | E93: ='OM Inventory'!$C$29*E8 -> 9162.9332 | F93: =E93*IF('OM Direct Materials & Direct La'!$H$75<1000,F8,IF('OM Direct Materials & Direct La'!$H$75>9999,J8,H8)) -> 824.66399 | G93: =D93+F93 -> 1542.29
B94: Attachable Spoke Magnet | C94: ='OM Inventory'!$C$28*E9 -> 7973.6219 | D94: =C94*IF('OM Direct Materials & Direct La'!$H$75<1000,$F9,IF('OM Direct Materials & Direct La'!$H$75>10000,$J9,$H9)) -> 4784.1731 | E94: ='OM Inventory'!$C$29*E9 -> 9162.9332 | F94: =E94*IF('OM Direct Materials & Direct La'!$H$75<1000,F9,IF('OM Direct Materials & Direct La'!$H$75>9999,J9,H9)) -> 5497.7599 | G94: =D94+F94 -> 10281.933
B95: PCB | C95: ='OM Inventory'!$C$28*E10 -> 7973.6219 | D95: =C95*IF('OM Direct Materials & Direct La'!$H$75<1000,$F10,IF('OM Direct Materials & Direct La'!$H$75>10000,$J10,$H10)) -> 797.36219 | E95: ='OM Inventory'!$C$29*E10 -> 9162.9332 | F95: =E95*IF('OM Direct Materials & Direct La'!$H$75<1000,F10,IF('OM Direct Materials & Direct La'!$H$75>9999,J10,H10)) -> 916.29332 | G95: =D95+F95 -> 1713.6555
B96: Wiring (meters) | C96: ='OM Inventory'!$C$28*E11 -> 3986.811 | D96: =C96*IF('OM Direct Materials & Direct La'!$H$75<1000,$F11,IF('OM Direct Materials & Direct La'!$H$75>10000,$J11,$H11)) -> 518.28542 | E96: ='OM Inventory'!$C$29*E11 -> 4581.4666 | F96: =E96*IF('OM Direct Materials & Direct La'!$H$75<1000,F11,IF('OM Direct Materials & Direct La'!$H$75>9999,J11,H11)) -> 595.59066 | G96: =D96+F96 -> 1113.8761
B97: Light | C97: ='OM Inventory'!$C$28*E12 -> 7973.6219 | D97: =C97*IF('OM Direct Materials & Direct La'!$H$75<1000,$F12,IF('OM Direct Materials & Direct La'!$H$75>10000,$J12,$H12)) -> 877.09841 | E97: ='OM Inventory'!$C$29*E12 -> 9162.9332 | F97: =E97*IF('OM Direct Materials & Direct La'!$H$75<1000,F12,IF('OM Direct Materials & Direct La'!$H$75>9999,J12,H12)) -> 1007.9227 | G97: =D97+F97 -> 1885.0211
B98: Assembly Screws | C98: ='OM Inventory'!$C$28*E13 -> 95683.463 | D98: =C98*IF('OM Direct Materials & Direct La'!$H$75<1000,$F13,IF('OM Direct Materials & Direct La'!$H$75>10000,$J13,$H13)) -> 1913.6693 | E98: ='OM Inventory'!$C$29*E13 -> 109955.2 | F98: =E98*IF('OM Direct Materials & Direct La'!$H$75<1000,F13,IF('OM Direct Materials & Direct La'!$H$75>9999,J13,H13)) -> 2199.104 | G98: =D98+F98 -> 4112.7732
B99: Hall Magnetic Sensor | C99: ='OM Inventory'!$C$28*E14 -> 7973.6219 | D99: =C99*IF('OM Direct Materials & Direct La'!$H$75<1000,$F14,IF('OM Direct Materials & Direct La'!$H$75>10000,$J14,$H14)) -> 1435.2519 | E99: ='OM Inventory'!$C$29*E14 -> 9162.9332 | F99: =E99*IF('OM Direct Materials & Direct La'!$H$75<1000,F14,IF('OM Direct Materials & Direct La'!$H$75>9999,J14,H14)) -> 1649.328 | G99: =D99+F99 -> 3084.5799
B100: Pellets (lbs) | C100: ='OM Inventory'!$C$28*E15 -> 1993.4055 | D100: =C100*IF('OM Direct Materials & Direct La'!$H$75<1000,$F15,IF('OM Direct Materials & Direct La'!$H$75>10000,$J15,$H15)) -> 2990.1082 | E100: ='OM Inventory'!$C$29*E15 -> 2290.7333 | F100: =E100*IF('OM Direct Materials & Direct La'!$H$75<1000,F15,IF('OM Direct Materials & Direct La'!$H$75>9999,J15,H15)) -> 3436.0999 | G100: =D100+F100 -> 6426.2082
B101: Custom Shells | C101: ='OM Inventory'!$C$28*E16 -> 7973.6219 | D101: =C101*IF('OM Direct Materials & Direct La'!$H$75<1000,$F16,IF('OM Direct Materials & Direct La'!$H$75>10000,$J16,$H16)) -> 797.36219 | E101: ='OM Inventory'!$C$29*E16 -> 9162.9332 | F101: =E101*IF('OM Direct Materials & Direct La'!$H$75<1000,F16,IF('OM Direct Materials & Direct La'!$H$75>9999,J16,H16)) -> 916.29332 | G101: =D101+F101 -> 1713.6555
F102: TOTAL: | G102: =SUM(G88:G101) -> 114643.55
B104: YEAR 5 RAW MATERIAL INVENTORY (PRIMARY SUPPLIERS)
B105: COMPONENT | C105: CYCLE STOCK UNITS | D105: CYCLE STOCK VALUE | E105: SAFETY STOCK UNITS | F105: SAFETY STOCK VALUE | G105: TOTAL RM INVENTORY VALUE
B106: Telescope Pole | C106: ='OM Inventory'!$C$35*E4 -> 5189.7108 | D106: =C106*IF('OM Direct Materials & Direct La'!$H$92<1000,$F4,IF('OM Direct Materials & Direct La'!$H$92>10000,$J4,$H4)) -> 4411.2542 | E106: ='OM Inventory'!$C$36*E4 -> 13716.708 | F106: =E106*IF('OM Direct Materials & Direct La'!$H$92<1000,$F4,IF('OM Direct Materials & Direct La'!$H$92>10000,$J4,$H4)) -> 11659.201 | G106: =D106+F106 -> 16070.456
B107: Safety Flag | C107: ='OM Inventory'!$C$35*E5 -> 5189.7108 | D107: =C107*IF('OM Direct Materials & Direct La'!$H$92<1000,$F5,IF('OM Direct Materials & Direct La'!$H$92>10000,$J5,$H5)) -> 3529.0034 | E107: ='OM Inventory'!$C$36*E5 -> 13716.708 | F107: =E107*IF('OM Direct Materials & Direct La'!$H$92<1000,$F5,IF('OM Direct Materials & Direct La'!$H$92>10000,$J5,$H5)) -> 9327.3611 | G107: =D107+F107 -> 12856.365
...

Sheet OM Direct Materials & Direct La
B2: DIRECT LABOR EXPENSES (YEARS 1-5)
C4: START-UP | D4: YEAR 1 | E4: YEAR 2 | F4: YEAR 3 | G4: YEAR 4 | H4: YEAR 5
B5: AVAILABLE TIME (Hours) | C5: 112 | D5: ='OM Assumptions'!$C$7 -> 2000 | E5: ='OM Assumptions'!$C$7 -> 2000 | F5: ='OM Assumptions'!$C$7 -> 2000 | G5: ='OM Assumptions'!$C$7 -> 2000 | H5: ='OM Assumptions'!$C$7 -> 2000
B6: YEARLY DEMAND | D6: ='MK Sales Projections'!C14 -> 47219.337 | E6: ='MK Sales Projections'!D14 -> 81204.43 | F6: ='MK Sales Projections'!E14 -> 105763.53 | G6: ='MK Sales Projections'!F14 -> 159472.44 | H6: ='MK Sales Projections'!G14 -> 238726.7
B7: TAKT TIME (SECONDS) | D7: =(D5*60*60)/D6 -> 152.4799 | E7: =(E5*60*60)/E6 -> 88.665114 | F7: =(F5*60*60)/F6 -> 68.076394 | G7: =(G5*60*60)/G6 -> 45.148868 | H7: =(H5*60*60)/H6 -> 30.160012
B8: CYCLE TIME | D8: ='OM Process Flow'!C14 -> 120 | E8: ='OM Process Flow'!C26 -> 80 | F8: ='OM Process Flow'!C38 -> 60 | G8: ='OM Process Flow'!C50 -> 40 | H8: ='OM Process Flow'!C62 -> 30
B9: TOTAL WORKERS | D9: ='OM Process Flow'!E13 -> 4 | E9: ='OM Process Flow'!E25 -> 7 | F9: ='OM Process Flow'!E37 -> 10 | G9: ='OM Process Flow'!E49 -> 12 | H9: ='OM Process Flow'!E61 -> 17
B10: LABOR RATE | D10: 12.84427 | E10: =D10*(1+'OM Assumptions'!$C$8) -> 13.229598 | F10: =E10*(1+'OM Assumptions'!$C$8) -> 13.626486 | G10: =F10*(1+'OM Assumptions'!$C$8) -> 14.035281 | H10: =G10*(1+'OM Assumptions'!$C$8) -> 14.456339
B11: DIRECT LABOR | D11: =D9*D10*'OM Assumptions'!$C$7 -> 102754.16 | E11: =E9*E10*'OM Assumptions'!$C$7 -> 185214.37 | F11: =F9*F10*'OM Assumptions'!$C$7 -> 272529.72 | G11: =G9*G10*'OM Assumptions'!$C$7 -> 336846.73 | H11: =H9*H10*'OM Assumptions'!$C$7 -> 491515.53
B12: BENEFIT COST | D12: =D11*'OM Assumptions'!$C$9 -> 30826.248 | E12: =E11*'OM Assumptions'!$C$9 -> 55564.312 | F12: =F11*'OM Assumptions'!$C$9 -> 81758.916 | G12: =G11*'OM Assumptions'!$C$9 -> 101054.02 | H12: =H11*'OM Assumptions'!$C$9 -> 147454.66
B13: TOTAL DIRECT LABOR COSTS | D13: =SUM(D11:D12) -> 133580.41 | E13: =SUM(E11:E12) -> 240778.69 | F13: =SUM(F11:F12) -> 354288.64 | G13: =SUM(G11:G12) -> 437900.76 | H13: =SUM(H11:H12) -> 638970.19
B14: PER UNIT | D14: =(D13/'MK Sales Projections'!C14) -> 2.8289344 | E14: =(E13/'MK Sales Projections'!D14) -> 2.965093 | F14: =(F13/'MK Sales Projections'!E14) -> 3.3498185 | G14: =(G13/'MK Sales Projections'!F14) -> 2.7459338 | H14: =(H13/'MK Sales Projections'!G14) -> 2.6765761
B16: DIRECT MATERIALS EXPENSES (YEARS 1-5) | K16: ORDER QUANTITY ANALYSIS
K17: YEAR 1 | L17: YEAR 2 | M17: YEAR 3 | N17: YEAR 4 | O17: YEAR 5
B18: BILL OF MATERIALS (YEAR 1) | J18: ACTUAL ORDER QUANTITY SPEND | K18: =H29 -> 347647.1 | L18: =H47 -> 597823.4 | M18: =H64 -> 778633.84 | N18: =H81 -> 1173957.7 | O18: =H98 -> 1757709.8 | P18: =sum(K18:O18) -> 4655771.8
B19: COMPONENT | C19: COUNTRY OF ORIGIN | D19: COST PER UNIT (OQ <1K UNITS) | E19: COST PER UNIT (OQ 1k-10K UNITS ) | F19: COST PER UNIT (10K+ UNITS) | H19: ORDERS PER YEAR | J19: EOQ SPEND | K19: =H32 -> 400805.03 | L19: =H50 -> 688713.82 | M19: =H50 -> 688713.82 | N19: =H84 -> 1348977.4 | O19: =H101 -> 2019389.1 | P19: =SUM(K19:O19) -> 5146599.2
B20: TELESCOPING POLE | C20: CHINA | D20: ='OM Raw Material Data'!G$4 -> 1.47 | E20: ='OM Raw Material Data'!I$4 -> 0.85 | F20: ='OM Raw Material Data'!K$4 -> 0.85 | H20: 4 | J20: ACTUAL ORDER QUANTITY | K20: =H23 -> 11804.834 | L20: =H41 -> 13534.072 | M20: =H58 -> 13220.442 | N20: =H75 -> 15947.244 | O20: =H92 -> 10379.422
B21: SAFETY FLAG | C21: CHINA | D21: ='OM Raw Material Data'!G$5 -> 0.88 | E21: ='OM Raw Material Data'!I$5 -> 0.8 | F21: ='OM Raw Material Data'!K$5 -> 0.68 | J21: EOQ | K21: =H26 -> 1372 | L21: =H44 -> 1799 | M21: =H61 -> 2053 | N21: =H78 -> 2521 | O21: =H95 -> 3085
B22: BIKE MOUNT | C22: CHINA | D22: ='OM Raw Material Data'!G$6 -> 1.8 | E22: ='OM Raw Material Data'!I$6 -> 1.8 | F22: ='OM Raw Material Data'!K$6 -> 1.8 | H22: ORDER QUANTITY | K22: =K19-K18 -> 53157.928 | L22: =L19-L18 -> 90890.419 | M22: =M19-M18 -> -89920.026 | N22: =N19-N18 -> 175019.68 | O22: =O19-O18 -> 261679.37
B23: SPEAKER | C23: CHINA | D23: ='OM Raw Material Data'!G$7 -> 1.5 | E23: ='OM Raw Material Data'!I$7 -> 1.5 | F23: ='OM Raw Material Data'!K$7 -> 1.5 | H23: =D6/H20 -> 11804.834
B24: BATTERY PACK | C24: CHINA | D24: ='OM Raw Material Data'!G$8 -> 0.35 | E24: ='OM Raw Material Data'!I$8 -> 0.22 | F24: ='OM Raw Material Data'!K$8 -> 0.09
B25: ATTACHABLE SPOKE MAGNET | C25: CHINA | D25: ='OM Raw Material Data'!G$9 -> 0.8 | E25: ='OM Raw Material Data'!I$9 -> 0.6 | F25: ='OM Raw Material Data'!K$9 -> 0.6 | H25: EOQ
B26: PCB | C26: CHINA | D26: ='OM Raw Material Data'!G$10 -> 0.5 | E26: ='OM Raw Material Data'!I$10 -> 0.3 | F26: ='OM Raw Material Data'!K$10 -> 0.1 | H26: ='OM Inventory'!J7 -> 1372
B27: WIRING | C27: CHINA | D27: ='OM Raw Material Data'!G$11 -> 0.09 | E27: ='OM Raw Material Data'!I$11 -> 0.075 | F27: ='OM Raw Material Data'!K$11 -> 0.065
B28: LIGHT | C28: CHINA | D28: ='OM Raw Material Data'!G$12 -> 0.32 | E28: ='OM Raw Material Data'!I$12 -> 0.25 | F28: ='OM Raw Material Data'!K$12 -> 0.11 | H28: ORDER QUANTITY SPEND
B29: ASSEMBLY SCREWS | C29: CHINA | D29: ='OM Raw Material Data'!G$13 -> 0.24 | E29: ='OM Raw Material Data'!I$13 -> 0.24 | F29: ='OM Raw Material Data'!K$13 -> 0.24 | H29: =($H23*($F33+$F34)+'OM Assumptions'!$F$35)*$H20 -> 347647.1
B30: HULL MAGNETIC SENSOR | C30: MALAYSIA | D30: ='OM Raw Material Data'!G$14 -> 0.21 | E30: ='OM Raw Material Data'!I$14 -> 0.18 | F30: ='OM Raw Material Data'!K$14 -> 0.18
B31: PELLETS | C31: USA | D31: ='OM Raw Material Data'!G$15 -> 0.375 | E31: ='OM Raw Material Data'!I$15 -> 0.375 | F31: ='OM Raw Material Data'!K$15 -> 0.375 | H31: EOQ SPEND
B32: CUSTOM SHELLS | C32: CHINA | D32: ='OM Raw Material Data'!G$16 -> 1 | E32: ='OM Raw Material Data'!I$16 -> 0.5 | F32: ='OM Raw Material Data'!K$16 -> 0.1 | H32: =(((sum(E20:E32)*(1+'OM Assumptions'!$F$24))*$H26)+'OM Assumptions'!F35)*(D6/H26) -> 400805.03
E33: TOTAL DM COST PER UNIT | F33: =IF(H23>10000,SUM(F20:F32),IF(H23<1000,SUM(D20:D32),SUM(E20:E32))) -> 6.69
E34: SHIPPING COST PER UNIT | F34: ='OM Assumptions'!$F$24*F33 -> 0.669
B36: BILL OF MATERIALS (YEAR 2)
B37: COMPONENT | C37: COUNTRY OF ORIGIN | D37: COST PER UNIT (OQ <1K UNITS) | E37: COST PER UNIT (OQ 1k-10K UNITS ) | F37: COST PER UNIT (10K+ UNITS) | H37: ORDERS PER YEAR
B38: TELESCOPING POLE | C38: CHINA | D38: ='OM Raw Material Data'!G$4 -> 1.47 | E38: ='OM Raw Material Data'!I$4 -> 0.85 | F38: ='OM Raw Material Data'!K$4 -> 0.85 | H38: =H20+'OM Assumptions'!C16 -> 6
B39: SAFETY FLAG | C39: CHINA | D39: ='OM Raw Material Data'!G$5 -> 0.88 | E39: ='OM Raw Material Data'!I$5 -> 0.8 | F39: ='OM Raw Material Data'!K$5 -> 0.68
B40: BIKE MOUNT | C40: CHINA | D40: ='OM Raw Material Data'!G$6 -> 1.8 | E40: ='OM Raw Material Data'!I$6 -> 1.8 | F40: ='OM Raw Material Data'!K$6 -> 1.8 | H40: ORDER QUANTITY
B41: SPEAKER | C41: CHINA | D41: ='OM Raw Material Data'!G$7 -> 1.5 | E41: ='OM Raw Material Data'!I$7 -> 1.5 | F41: ='OM Raw Material Data'!K$7 -> 1.5 | H41: =E6/H38 -> 13534.072
B42: BATTERY PACK | C42: CHINA | D42: ='OM Raw Material Data'!G$8 -> 0.35 | E42: ='OM Raw Material Data'!I$8 -> 0.22 | F42: ='OM Raw Material Data'!K$8 -> 0.09
B43: ATTACHABLE SPOKE MAGNET | C43: CHINA | D43: ='OM Raw Material Data'!G$9 -> 0.8 | E43: ='OM Raw Material Data'!I$9 -> 0.6 | F43: ='OM Raw Material Data'!K$9 -> 0.6 | H43: EOQ
B44: PCB | C44: CHINA | D44: ='OM Raw Material Data'!G$10 -> 0.5 | E44: ='OM Raw Material Data'!I$10 -> 0.3 | F44: ='OM Raw Material Data'!K$10 -> 0.1 | H44: ='OM Inventory'!J14 -> 1799
B45: WIRING | C45: CHINA | D45: ='OM Raw Material Data'!G$11 -> 0.09 | E45: ='OM Raw Material Data'!I$11 -> 0.075 | F45: ='OM Raw Material Data'!K$11 -> 0.065
B46: LIGHT | C46: CHINA | D46: ='OM Raw Material Data'!G$12 -> 0.32 | E46: ='OM Raw Material Data'!I$12 -> 0.25 | F46: ='OM Raw Material Data'!K$12 -> 0.11 | H46: ORDER QUANTITY SPEND
B47: ASSEMBLY SCREWS | C47: CHINA | D47: ='OM Raw Material Data'!G$13 -> 0.24 | E47: ='OM Raw Material Data'!I$13 -> 0.24 | F47: ='OM Raw Material Data'!K$13 -> 0.24 | H47: =($H41*($F51+$F52)+'OM Assumptions'!$F$35)*$H38 -> 597823.4
B48: HULL MAGNETIC SENSOR | C48: MALAYSIA | D48: ='OM Raw Material Data'!G$14 -> 0.21 | E48: ='OM Raw Material Data'!I$14 -> 0.18 | F48: ='OM Raw Material Data'!K$14 -> 0.18
B49: PELLETS | C49: USA | D49: ='OM Raw Material Data'!G$15 -> 0.375 | E49: ='OM Raw Material Data'!I$15 -> 0.375 | F49: ='OM Raw Material Data'!K$15 -> 0.375 | H49: EOQ SPEND
B50: CUSTOM SHELLS | C50: CHINA | D50: ='OM Raw Material Data'!G$16 -> 1 | E50: ='OM Raw Material Data'!I$16 -> 0.5 | F50: ='OM Raw Material Data'!K$16 -> 0.1 | H50: =(((sum(E38:E50)*(1+'OM Assumptions'!$F$24))*$H44)+'OM Assumptions'!F35)*(E6/$H44) -> 688713.82
E51: TOTAL DM COST PER UNIT | F51: =IF(H41>10000,SUM(F38:F50),IF(H41<1000,SUM(D38:D50),SUM(E38:E50))) -> 6.69
E52: SHIPPING COST PER UNIT | F52: ='OM Assumptions'!$F$24*F51 -> 0.669
B53: BILL OF MATERIALS (YEAR 3)
B54: COMPONENT | C54: COUNTRY OF ORIGIN | D54: COST PER UNIT (OQ <1K UNITS) | E54: COST PER UNIT (OQ 1k-10K UNITS ) | F54: COST PER UNIT (10K+ UNITS) | H54: ORDERS PER YEAR
B55: TELESCOPING POLE | C55: CHINA | D55: ='OM Raw Material Data'!G$4 -> 1.47 | E55: ='OM Raw Material Data'!I$4 -> 0.85 | F55: ='OM Raw Material Data'!K$4 -> 0.85 | H55: =H38+'OM Assumptions'!C16 -> 8
B56: SAFETY FLAG | C56: CHINA | D56: ='OM Raw Material Data'!G$5 -> 0.88 | E56: ='OM Raw Material Data'!I$5 -> 0.8 | F56: ='OM Raw Material Data'!K$5 -> 0.68
B57: BIKE MOUNT | C57: CHINA | D57: ='OM Raw Material Data'!G$6 -> 1.8 | E57: ='OM Raw Material Data'!I$6 -> 1.8 | F57: ='OM Raw Material Data'!K$6 -> 1.8 | H57: ORDER QUANTITY
B58: SPEAKER | C58: CHINA | D58: ='OM Raw Material Data'!G$7 -> 1.5 | E58: ='OM Raw Material Data'!I$7 -> 1.5 | F58: ='OM Raw Material Data'!K$7 -> 1.5 | H58: =F6/H55 -> 13220.442
B59: BATTERY PACK | C59: CHINA | D59: ='OM Raw Material Data'!G$8 -> 0.35 | E59: ='OM Raw Material Data'!I$8 -> 0.22 | F59: ='OM Raw Material Data'!K$8 -> 0.09
B60: ATTACHABLE SPOKE MAGNET | C60: CHINA | D60: ='OM Raw Material Data'!G$9 -> 0.8 | E60: ='OM Raw Material Data'!I$9 -> 0.6 | F60: ='OM Raw Material Data'!K$9 -> 0.6 | H60: EOQ
B61: PCB | C61: CHINA | D61: ='OM Raw Material Data'!G$10 -> 0.5 | E61: ='OM Raw Material Data'!I$10 -> 0.3 | F61: ='OM Raw Material Data'!K$10 -> 0.1 | H61: ='OM Inventory'!J21 -> 2053
B62: WIRING | C62: CHINA | D62: ='OM Raw Material Data'!G$11 -> 0.09 | E62: ='OM Raw Material Data'!I$11 -> 0.075 | F62: ='OM Raw Material Data'!K$11 -> 0.065
B63: LIGHT | C63: CHINA | D63: ='OM Raw Material Data'!G$12 -> 0.32 | E63: ='OM Raw Material Data'!I$12 -> 0.25 | F63: ='OM Raw Material Data'!K$12 -> 0.11 | H63: ORDER QUANTITY SPEND
B64: ASSEMBLY SCREWS | C64: CHINA | D64: ='OM Raw Material Data'!G$13 -> 0.24 | E64: ='OM Raw Material Data'!I$13 -> 0.24 | F64: ='OM Raw Material Data'!K$13 -> 0.24 | H64: =($H58*($F68+$F69)+'OM Assumptions'!$F$35)*$H55 -> 778633.84
B65: HULL MAGNETIC SENSOR | C65: MALAYSIA | D65: ='OM Raw Material Data'!G$14 -> 0.21 | E65: ='OM Raw Material Data'!I$14 -> 0.18 | F65: ='OM Raw Material Data'!K$14 -> 0.18
B66: PELLETS | C66: USA | D66: ='OM Raw Material Data'!G$15 -> 0.375 | E66: ='OM Raw Material Data'!I$15 -> 0.375 | F66: ='OM Raw Material Data'!K$15 -> 0.375 | H66: EOQ SPEND
B67: CUSTOM SHELLS | C67: CHINA | D67: ='OM Raw Material Data'!G$16 -> 1 | E67: ='OM Raw Material Data'!I$16 -> 0.5 | F67: ='OM Raw Material Data'!K$16 -> 0.1 | H67: =(((sum(E55:E67)*(1+'OM Assumptions'!$F$24))*$H61)+'OM Assumptions'!F52)*(F6/$H61) -> 894653.73
E68: TOTAL DM COST PER UNIT | F68: =IF(H58>10000,SUM(F55:F67),IF(H58<1000,SUM(D55:D67),SUM(E55:E67))) -> 6.69
E69: SHIPPING COST PER UNIT | F69: ='OM Assumptions'!$F$24*F68 -> 0.669
B70: BILL OF MATERIALS (YEAR 4)
B71: COMPONENT | C71: COUNTRY OF ORIGIN | D71: COST PER UNIT (OQ <1K UNITS) | E71: COST PER UNIT (OQ 1k-10K UNITS ) | F71: COST PER UNIT (10K+ UNITS) | H71: ORDERS PER YEAR
B72: TELESCOPING POLE | C72: CHINA | D72: ='OM Raw Material Data'!G$4 -> 1.47 | E72: ='OM Raw Material Data'!I$4 -> 0.85 | F72: ='OM Raw Material Data'!K$4 -> 0.85 | H72: =H55+'OM Assumptions'!C16 -> 10
B73: SAFETY FLAG | C73: CHINA | D73: ='OM Raw Material Data'!G$5 -> 0.88 | E73: ='OM Raw Material Data'!I$5 -> 0.8 | F73: ='OM Raw Material Data'!K$5 -> 0.68
B74: BIKE MOUNT | C74: CHINA | D74: ='OM Raw Material Data'!G$6 -> 1.8 | E74: ='OM Raw Material Data'!I$6 -> 1.8 | F74: ='OM Raw Material Data'!K$6 -> 1.8 | H74: ORDER QUANTITY
B75: SPEAKER | C75: CHINA | D75: ='OM Raw Material Data'!G$7 -> 1.5 | E75: ='OM Raw Material Data'!I$7 -> 1.5 | F75: ='OM Raw Material Data'!K$7 -> 1.5 | H75: =G6/H72 -> 15947.244
B76: BATTERY PACK | C76: CHINA | D76: ='OM Raw Material Data'!G$8 -> 0.35 | E76: ='OM Raw Material Data'!I$8 -> 0.22 | F76: ='OM Raw Material Data'!K$8 -> 0.09
B77: ATTACHABLE SPOKE MAGNET | C77: CHINA | D77: ='OM Raw Material Data'!G$9 -> 0.8 | E77: ='OM Raw Material Data'!I$9 -> 0.6 | F77: ='OM Raw Material Data'!K$9 -> 0.6 | H77: EOQ
B78: PCB | C78: CHINA | D78: ='OM Raw Material Data'!G$10 -> 0.5 | E78: ='OM Raw Material Data'!I$10 -> 0.3 | F78: ='OM Raw Material Data'!K$10 -> 0.1 | H78: ='OM Inventory'!J28 -> 2521
B79: WIRING | C79: CHINA | D79: ='OM Raw Material Data'!G$11 -> 0.09 | E79: ='OM Raw Material Data'!I$11 -> 0.075 | F79: ='OM Raw Material Data'!K$11 -> 0.065
B80: LIGHT | C80: CHINA | D80: ='OM Raw Material Data'!G$12 -> 0.32 | E80: ='OM Raw Material Data'!I$12 -> 0.25 | F80: ='OM Raw Material Data'!K$12 -> 0.11 | H80: ORDER QUANTITY SPEND
B81: ASSEMBLY SCREWS | C81: CHINA | D81: ='OM Raw Material Data'!G$13 -> 0.24 | E81: ='OM Raw Material Data'!I$13 -> 0.24 | F81: ='OM Raw Material Data'!K$13 -> 0.24 | H81: =($H75*($F85+$F86)+'OM Assumptions'!$F$35)*$H72 -> 1173957.7
B82: HULL MAGNETIC SENSOR | C82: MALAYSIA | D82: ='OM Raw Material Data'!G$14 -> 0.21 | E82: ='OM Raw Material Data'!I$14 -> 0.18 | F82: ='OM Raw Material Data'!K$14 -> 0.18
B83: PELLETS | C83: USA | D83: ='OM Raw Material Data'!G$15 -> 0.375 | E83: ='OM Raw Material Data'!I$15 -> 0.375 | F83: ='OM Raw Material Data'!K$15 -> 0.375 | H83: EOQ SPEND
B84: CUSTOM SHELLS | C84: CHINA | D84: ='OM Raw Material Data'!G$16 -> 1 | E84: ='OM Raw Material Data'!I$16 -> 0.5 | F84: ='OM Raw Material Data'!K$16 -> 0.1 | H84: =(((sum(E72:E84)*(1+'OM Assumptions'!$F$24))*$H78)+'OM Assumptions'!F69)*(G6/$H78) -> 1348977.4
E85: TOTAL DM COST PER UNIT | F85: =IF(H75>10000,SUM(F72:F84),IF(H75<1000,SUM(D72:D84),SUM(E72:E84))) -> 6.69
E86: SHIPPING COST PER UNIT | F86: ='OM Assumptions'!$F$24*F85 -> 0.669
B87: BILL OF MATERIALS (YEAR 5)
B88: COMPONENT | C88: COUNTRY OF ORIGIN | D88: COST PER UNIT (OQ <1K UNITS) | E88: COST PER UNIT (OQ 1k-10K UNITS ) | F88: COST PER UNIT (10K+ UNITS) | H88: ORDERS PER YEAR
B89: TELESCOPING POLE | C89: CHINA | D89: ='OM Raw Material Data'!G$4 -> 1.47 | E89: ='OM Raw Material Data'!I$4 -> 0.85 | F89: ='OM Raw Material Data'!K$4 -> 0.85 | H89: 23
B90: SAFETY FLAG | C90: CHINA | D90: ='OM Raw Material Data'!G$5 -> 0.88 | E90: ='OM Raw Material Data'!I$5 -> 0.8 | F90: ='OM Raw Material Data'!K$5 -> 0.68
B91: BIKE MOUNT | C91: CHINA | D91: ='OM Raw Material Data'!G$6 -> 1.8 | E91: ='OM Raw Material Data'!I$6 -> 1.8 | F91: ='OM Raw Material Data'!K$6 -> 1.8 | H91: ORDER QUANTITY
B92: SPEAKER | C92: CHINA | D92: ='OM Raw Material Data'!G$7 -> 1.5 | E92: ='OM Raw Material Data'!I$7 -> 1.5 | F92: ='OM Raw Material Data'!K$7 -> 1.5 | H92: =H6/H89 -> 10379.422
B93: BATTERY PACK | C93: CHINA | D93: ='OM Raw Material Data'!G$8 -> 0.35 | E93: ='OM Raw Material Data'!I$8 -> 0.22 | F93: ='OM Raw Material Data'!K$8 -> 0.09
B94: ATTACHABLE SPOKE MAGNET | C94: CHINA | D94: ='OM Raw Material Data'!G$9 -> 0.8 | E94: ='OM Raw Material Data'!I$9 -> 0.6 | F94: ='OM Raw Material Data'!K$9 -> 0.6 | H94: EOQ
B95: PCB | C95: CHINA | D95: ='OM Raw Material Data'!G$10 -> 0.5 | E95: ='OM Raw Material Data'!I$10 -> 0.3 | F95: ='OM Raw Material Data'!K$10 -> 0.1 | H95: ='OM Inventory'!J35 -> 3085
B96: WIRING | C96: CHINA | D96: ='OM Raw Material Data'!G$11 -> 0.09 | E96: ='OM Raw Material Data'!I$11 -> 0.075 | F96: ='OM Raw Material Data'!K$11 -> 0.065
B97: LIGHT | C97: CHINA | D97: ='OM Raw Material Data'!G$12 -> 0.32 | E97: ='OM Raw Material Data'!I$12 -> 0.25 | F97: ='OM Raw Material Data'!K$12 -> 0.11 | H97: ORDER QUANTITY SPEND
B98: ASSEMBLY SCREWS | C98: CHINA | D98: ='OM Raw Material Data'!G$13 -> 0.24 | E98: ='OM Raw Material Data'!I$13 -> 0.24 | F98: ='OM Raw Material Data'!K$13 -> 0.24 | H98: =($H92*($F102+$F103)+'OM Assumptions'!$F$35)*$H89 -> 1757709.8
B99: HULL MAGNETIC SENSOR | C99: MALAYSIA | D99: ='OM Raw Material Data'!G$14 -> 0.21 | E99: ='OM Raw Material Data'!I$14 -> 0.18 | F99: ='OM Raw Material Data'!K$14 -> 0.18
B100: PELLETS | C100: USA | D100: ='OM Raw Material Data'!G$15 -> 0.375 | E100: ='OM Raw Material Data'!I$15 -> 0.375 | F100: ='OM Raw Material Data'!K$15 -> 0.375 | H100: EOQ SPEND
B101: CUSTOM SHELLS | C101: CHINA | D101: ='OM Raw Material Data'!G$16 -> 1 | E101: ='OM Raw Material Data'!I$16 -> 0.5 | F101: ='OM Raw Material Data'!K$16 -> 0.1 | H101: =(((sum(E89:E101)*(1+'OM Assumptions'!$F$24))*$H95)+'OM Assumptions'!F86)*(H6/$H95) -> 2019389.1
E102: TOTAL DM COST PER UNIT | F102: =IF(H92>10000,SUM(F89:F101),IF(H92<1000,SUM(D89:D101),SUM(E89:E101))) -> 6.69 | H102: DM Cost/Unit Sensitivity
E103: SHIPPING COST PER UNIT | F103: ='OM Assumptions'!$F$24*F102 -> 0.669 | H103: 1

Sheet OM Inventory
B2: INVENTORY VALUE (UNIT QUANTITY)
B4: YEAR 1 INVENTORY
C6: RM | D6: WIP | E6: FG | F6: TOTAL INVENTORY | H6: DEMAND (UNITS) | J6: EOQ
B7: AVERAGE CYCLE STOCK | C7: ='OM Direct Materials & Direct La'!H23/2 -> 5902.4172 | D7: =(H7/365)*'OM Demand and Lead Time'!C24 -> 2945.6109 | E7: ='OM Demand and Lead Time'!E11/2 -> 454.03209 | F7: =SUM(C7:E7) -> 9302.0602 | H7: ='MK Sales Projections'!C14 -> 47219.337 | J7: =ROUND(SQRT((2*'MK Sales Projections'!C14*'OM Assumptions'!C17)/('OM Direct Materials & Direct La'!F33*'OM Assumptions'!C20)),0) -> 1372
B8: AVERAGE SAFETY STOCK | C8: ='OM Assumptions'!C19*SQRT(('OM Demand and Lead Time'!C24*('OM Demand and Lead Time'!F11/SQRT(7))^2)+((('OM Demand and Lead Time'!C11/365)^2)*('OM Demand and Lead Time'!D24)^2)) -> 3253.6446 | D8: - | E8: ='OM Assumptions'!C19*('OM Demand and Lead Time'!E11/SQRT(7))*SQRT(7) -> 1493.6327 | F8: =SUM(C8:E8) -> 4747.2772
B9: TOTAL INVENTORY | C9: =SUM(C7:C8) -> 9156.0617 | D9: =SUM(D7:D8) -> 2945.6109 | E9: =SUM(E7:E8) -> 1947.6647 | F9: =SUM(F7:F8) -> 14049.337
B11: YEAR 2 INVENTORY
C13: RM | D13: WIP | E13: FG | F13: TOTAL INVENTORY | H13: DEMAND (UNITS) | J13: EOQ
B14: AVERAGE CYCLE STOCK | C14: ='OM Direct Materials & Direct La'!H41/2 -> 6767.0358 | D14: =(H14/365)*'OM Demand and Lead Time'!C25 -> 5065.6504 | E14: ='OM Demand and Lead Time'!E12/2 -> 780.81182 | F14: =SUM(C14:E14) -> 12613.498 | H14: ='MK Sales Projections'!D14 -> 81204.43 | J14: =ROUND(SQRT((2*H14*'OM Assumptions'!C17)/('OM Direct Materials & Direct La'!F51*'OM Assumptions'!C20)),0) -> 1799
B15: AVERAGE SAFETY STOCK | C15: ='OM Assumptions'!C19*SQRT(('OM Demand and Lead Time'!C25*('OM Demand and Lead Time'!E12/SQRT(7))^2)+((('OM Demand and Lead Time'!C12/365)^2)*'OM Demand and Lead Time'!D25^2)) -> 4665.8267 | D15: - | E15: ='OM Assumptions'!C19*('OM Demand and Lead Time'!E12/SQRT(7))*SQRT(7) -> 2568.6423 | F15: =SUM(C15:E15) -> 7234.4691
B16: TOTAL INVENTORY | C16: =SUM(C14:C15) -> 11432.863 | D16: =SUM(D14:D15) -> 5065.6504 | E16: =SUM(E14:E15) -> 3349.4541 | F16: =SUM(F14:F15) -> 19847.967
B18: YEAR 3 INVENTORY
C20: RM | D20: WIP | E20: FG | F20: TOTAL INVENTORY | H20: DEMAND (UNITS) | J20: EOQ
B21: AVERAGE CYCLE STOCK | C21: ='OM Direct Materials & Direct La'!H58/2 -> 6610.2208 | D21: =(H21/365)*'OM Demand and Lead Time'!C26 -> 6597.683 | E21: ='OM Demand and Lead Time'!E13/2 -> 1016.9571 | F21: =SUM(C21:E21) -> 14224.861 | H21: ='MK Sales Projections'!E14 -> 105763.53 | J21: =ROUND(SQRT((2*H21*'OM Assumptions'!C17)/('OM Direct Materials & Direct La'!F68*'OM Assumptions'!C20)),0) -> 2053
B22: AVERAGE SAFETY STOCK | C22: ='OM Assumptions'!C19*SQRT(('OM Demand and Lead Time'!C26*('OM Demand and Lead Time'!F13/SQRT(7))^2)+((('OM Demand and Lead Time'!C13/365)^2)*('OM Demand and Lead Time'!D24)^2)) -> 7287.6277 | D22: - | E22: ='OM Assumptions'!C19*('OM Demand and Lead Time'!F13/SQRT(7))*SQRT(7) -> 4020.7798 | F22: =SUM(C22:E22) -> 11308.407
B23: TOTAL INVENTORY | C23: =SUM(C21:C22) -> 13897.849 | D23: =SUM(D21:D22) -> 6597.683 | E23: =SUM(E21:E22) -> 5037.7368 | F23: =SUM(C23:E23) -> 25533.268
B25: YEAR 4 INVENTORY
C27: RM | D27: WIP | E27: FG | F27: TOTAL INVENTORY | H27: DEMAND (UNITS) | J27: EOQ
B28: Average Cycle Stock | C28: ='OM Direct Materials & Direct La'!H75/2 -> 7973.6219 | D28: =(H28/365)*'OM Demand and Lead Time'!C27 -> 9948.1226 | E28: ='OM Demand and Lead Time'!E14/2 -> 1533.3888 | F28: =SUM(C28:E28) -> 19455.133 | H28: ='MK Sales Projections'!F14 -> 159472.44 | J28: =ROUND(SQRT((2*H28*'OM Assumptions'!C17)/('OM Direct Materials & Direct La'!F85*'OM Assumptions'!C20)),0) -> 2521
B29: Average Safety Stock | C29: ='OM Assumptions'!C19*SQRT(('OM Demand and Lead Time'!C27*('OM Demand and Lead Time'!E14/SQRT(7))^2)+((('OM Demand and Lead Time'!C14/365)^2)*('OM Demand and Lead Time'!D27)^2)) -> 9162.9332 | D29: - | E29: ='OM Assumptions'!C19*('OM Demand and Lead Time'!F14/SQRT(7))*SQRT(7) -> 6062.6147 | F29: =SUM(C29:E29) -> 15225.548
B30: Total Inventory | C30: =SUM(C28:C29) -> 17136.555 | D30: =SUM(D28:D29) -> 9948.1226 | E30: =SUM(E28:E29) -> 7596.0035 | F30: =SUM(C30:E30) -> 34680.681
B32: YEAR 5 INVENTORY
C34: RM | D34: WIP | E34: FG | F34: TOTAL INVENTORY | H34: DEMAND (UNITS) | J34: EOQ
B35: AVERAGE CYCLE STOCK | C35: ='OM Direct Materials & Direct La'!H92/2 -> 5189.7108 | D35: =(H35/365)*'OM Demand and Lead Time'!C28 -> 14892.119 | E35: ='OM Demand and Lead Time'!E15/2 -> 2295.449 | F35: =SUM(C35:E35) -> 22377.279 | H35: ='MK Sales Projections'!G14 -> 238726.7 | J35: =ROUND(SQRT((2*H35*'OM Assumptions'!C17)/('OM Direct Materials & Direct La'!F102*'OM Assumptions'!C20)),0) -> 3085
B36: AVERAGE SAFETY STOCK | C36: ='OM Assumptions'!C19*SQRT(('OM Demand and Lead Time'!C28*('OM Demand and Lead Time'!E15/SQRT(7))^2)+((('OM Demand and Lead Time'!C15/365)^2)*'OM Demand and Lead Time'!D28^2)) -> 13716.708 | D36: - | E36: ='OM Assumptions'!C19*('OM Demand and Lead Time'!F15/SQRT(7))*SQRT(7) -> 9075.5996 | F36: =SUM(C36:E36) -> 22792.307
B37: TOTAL INVENTORY | C37: =SUM(C35:C36) -> 18906.418 | D37: =SUM(D35:D36) -> 14892.119 | E37: =SUM(E35:E36) -> 11371.049 | F37: =SUM(C37:E37) -> 45169.586
B39: INVENTORY VALUE (USD $)
B41: YEAR 1 INVENTORY
C43: RM | D43: WIP | E43: FG | F43: TOTAL INVENTORY | H43: DM COST PER UNIT | I43: AVERAGE | J43: COGS PER UNIT | K43: COGS PER WEEK
B44: AVERAGE CYCLE STOCK | C44: =C7*H44 -> 39487.171 | D44: =D7*I44 -> 31101.637 | E44: =E7*J44 -> 6550.4455 | F44: =SUM(C44:E44) -> 77139.253 | H44: ='OM Direct Materials & Direct La'!F33 -> 6.69 | I44: =AVERAGE(H44,J44) -> 10.558637 | J44: ='FE Assumptions'!C43 -> 14.427274 | K44: ='FE Assumptions'!C42/50 -> 13624.927
B45: AVERAGE SAFETY STOCK | C45: =C8*H44 -> 21766.882 | D45: - | E45: =E8*J44 -> 21549.048 | F45: =SUM(C45:E45) -> 43315.93
B46: TOTAL INVENTORY | C46: =SUM(C44:C45) -> 61254.053 | D46: =SUM(D44:D45) -> 31101.637 | E46: =SUM(E44:E45) -> 28099.493 | F46: =SUM(F44:F45) -> 120455.18 | H46: YEAR 1 INVENTORY AS WEEKS OF SUPPLY | J46: =F46/K44 -> 8.840795
B48: YEAR 2 INVENTORY
C50: RM | D50: WIP | E50: FG | F50: TOTAL INVENTORY | H50: DM COST PER UNIT | I50: AVERAGE | J50: COGS PER UNIT | K50: COGS PER WEEK
B51: AVERAGE CYCLE STOCK | C51: =C14*H51 -> 45271.47 | D51: =D14*I51 -> 51329.372 | E51: =E14*J51 -> 10600.035 | F51: =SUM(C51:E51) -> 107200.88 | H51: ='OM Direct Materials & Direct La'!F51 -> 6.69 | I51: =AVERAGE(H51,J51) -> 10.132829 | J51: ='FE Assumptions'!D43 -> 13.575659 | K51: ='FE Assumptions'!D42/50 -> 22048.073
B52: AVERAGE SAFETY STOCK | C52: =C15*H51 -> 31214.381 | D52: - | E52: =J51*E15 -> 34871.012 | F52: =SUM(C52:E52) -> 66085.393
B53: TOTAL INVENTORY | C53: =SUM(C51:C52) -> 76485.85 | D53: =SUM(D51:D52) -> 51329.372 | E53: =SUM(E51:E52) -> 45471.047 | F53: =SUM(F51:F52) -> 173286.27 | H53: YEAR 2 INVENTORY AS WEEKS OF SUPPLY | J53: =F53/K51 -> 7.8594746
B55: YEAR 3 INVENTORY
C57: RM | D57: WIP | E57: FG | F57: TOTAL INVENTORY | H57: DM COST PER UNIT | I57: AVERAGE | J57: COGS PER UNIT | K57: COGS PER WEEK
B58: AVERAGE CYCLE STOCK | C58: =C21*H58 -> 44222.377 | D58: =D21*I58 -> 67131.383 | E58: =E21*J58 -> 13891.62 | F58: =SUM(C58:E58) -> 125245.38 | H58: ='OM Direct Materials & Direct La'!F68 -> 6.69 | I58: =AVERAGE(H58,J58) -> 10.174994 | J58: ='FE Assumptions'!E43 -> 13.659987 | K58: ='FE Assumptions'!E42/50 -> 28894.571
B59: AVERAGE SAFETY STOCK | C59: =H58*C22 -> 48754.229 | D59: - | E59: =E22*J58 -> 54923.801 | F59: =SUM(C59:E59) -> 103678.03
B60: TOTAL INVENTORY | C60: =SUM(C58:C59) -> 92976.606 | D60: =SUM(D58:D59) -> 67131.383 | E60: =SUM(E58:E59) -> 68815.421 | F60: =SUM(F58:F59) -> 228923.41 | H60: YEAR 3 INVENTORY AS WEEKS OF SUPPLY | J60: =F60/K58 -> 7.9227137
B62: YEAR 4 INVENTORY
C64: RM | D64: WIP | E64: FG | F64: TOTAL INVENTORY | H64: DM COST PER UNIT | I64: AVERAGE | J64: COGS PER UNIT | K64: COGS PER WEEK
B65: AVERAGE CYCLE STOCK | C65: =H65*C28 -> 53343.531 | D65: =I65*D28 -> 96256.029 | E65: =J65*E28 -> 19415.151 | F65: =SUM(C65:E65) -> 169014.71 | H65: ='OM Direct Materials & Direct La'!F85 -> 6.69 | I65: =AVERAGE(H65,J65) -> 9.6757984 | J65: ='FE Assumptions'!F43 -> 12.661597 | K65: ='FE Assumptions'!F42/50 -> 40383.514
B66: AVERAGE SAFETY STOCK | C66: =H65*C29 -> 61300.023 | D66: - | E66: =J65*E29 -> 76762.383 | F66: =SUM(C66:E66) -> 138062.41
B67: TOTAL INVENTORY | C67: =SUM(C65:C66) -> 114643.55 | D67: =SUM(D65:D66) -> 96256.029 | E67: =SUM(E65:E66) -> 96177.534 | F67: =SUM(F65:F66) -> 307077.12 | H67: YEAR 4 INVENTORY AS WEEKS OF SUPPLY | J67: =F67/K65 -> 7.6040216
B69: YEAR 5 INVENTORY
C71: RM | D71: WIP | E71: FG | F71: TOTAL INVENTORY | H71: DM COST PER UNIT | I71: AVERAGE | J71: COGS PER UNIT | K71: COGS PER WEEK
B72: AVERAGE CYCLE STOCK | C72: =H72*C35 -> 34719.166 | D72: =I72*D35 -> 141645.37 | E72: =J72*E35 -> 28309.458 | F72: =SUM(C72:E72) -> 204673.99 | H72: ='OM Direct Materials & Direct La'!F102 -> 6.69 | I72: =AVERAGE(H72,J72) -> 9.5114314 | J72: ='FE Assumptions'!G43 -> 12.332863 | K72: ='FE Assumptions'!G42/50 -> 58883.673
B73: AVERAGE SAFETY STOCK | C73: =H72*C36 -> 91764.773 | D73: - | E73: =J72*E36 -> 111928.13 | F73: =SUM(C73:E73) -> 203692.9
B74: TOTAL INVENTORY | C74: =SUM(C72:C73) -> 126483.94 | D74: =SUM(D72:D73) -> 141645.37 | E74: =SUM(E72:E73) -> 140237.58 | F74: =SUM(F72:F73) -> 408366.89 | H74: YEAR 5 INVENTORY AS WEEKS OF SUPPLY | J74: =F74/K72 -> 6.9351463
B76: SERVICE LEVEL
B78: SPECIFICATION | C78: YEAR 1 | D78: YEAR 2 | E78: YEAR 3 | F78: YEAR 4 | G78: YEAR 5
B79: MANUFACTURER'S SALES | C79: ='MK Sales Projections'!C16 -> 1629067.1 | D79: ='MK Sales Projections'!D16 -> 2758562.2 | E79: ='MK Sales Projections'!E16 -> 3503176.7 | F79: ='MK Sales Projections'!F16 -> 5040746.6 | G79: ='MK Sales Projections'!G16 -> 7386204.1
B80: MANUFACTURER'S PRICE | C80: ='FE Assumptions'!C35 -> 34.5 | D80: ='FE Assumptions'!D35 -> 33.970588 | E80: ='FE Assumptions'!E35 -> 33.122727 | F80: ='FE Assumptions'!F35 -> 31.608889 | G80: ='FE Assumptions'!G35 -> 30.94
B81: TOTAL UNITS | C81: ='MK Sales Projections'!C14 -> 47219.337 | D81: ='MK Sales Projections'!D14 -> 81204.43 | E81: ='MK Sales Projections'!E14 -> 105763.53 | F81: ='MK Sales Projections'!F14 -> 159472.44 | G81: ='MK Sales Projections'!G14 -> 238726.7
B82: COGS PER UNIT | C82: ='FE Assumptions'!C43 -> 14.427274 | D82: ='FE Assumptions'!D43 -> 13.575659 | E82: ='FE Assumptions'!E43 -> 13.659987 | F82: ='FE Assumptions'!F43 -> 12.661597 | G82: ='FE Assumptions'!G43 -> 12.332863
B83: TOTAL COST OF GOODS SOLD | C83: =C81*C82 -> 681246.33 | D83: =D81*D82 -> 1102403.6 | E83: =E81*E82 -> 1444728.5 | F83: =F81*F82 -> 2019175.7 | G83: =G81*G82 -> 2944183.6
B84: GROSS PROFIT | C84: =C79-C83 -> 947820.81 | D84: =D79-D83 -> 1656158.6 | E84: =E79-E83 -> 2058448.1 | F84: =F79-F83 -> 3021570.9 | G84: =G79-G83 -> 4442020.4
B85: CONTRIBUTION MARGIN | C85: =C84/C79 -> 0.58181814 | D85: =D84/D79 -> 0.60037021 | E85: =E84/E79 -> 0.58759473 | F85: =F84/F79 -> 0.59942923 | G85: =G84/G79 -> 0.60139422
B86: SHORTAGE COST | C86: =(C79-C83)/C81 -> 20.072726 | D86: =(D79-D83)/D81 -> 20.394929 | E86: =(E79-E83)/E81 -> 19.46274 | F86: =(F79-F83)/F81 -> 18.947292 | G86: =(G79-G83)/G81 -> 18.607137
B87: ANNUAL HOLDING COST RATE | C87: ='OM Assumptions'!$F$36 -> 0.3 | D87: ='OM Assumptions'!$F$36 -> 0.3 | E87: ='OM Assumptions'!$F$36 -> 0.3 | F87: ='OM Assumptions'!$F$36 -> 0.3 | G87: ='OM Assumptions'!$F$36 -> 0.3
B88: EXCESS COST | C88: =C82*C87/6 -> 0.72136371 | D88: =D82*D87/6 -> 0.67878295 | E88: =E82*E87/6 -> 0.68299937 | F88: =F82*F87/6 -> 0.63307984 | G88: =G82*G87/6 -> 0.61664314
B89: ACTUAL SERVICE LEVEL | C89: =C86/(C86+C88) -> 0.96530919 | D89: =D86/(D86+D88) -> 0.96779006 | E89: =E86/(E86+E88) -> 0.96609708 | F89: =F86/(F86+F88) -> 0.96766763 | G89: =G86/(G86+G88) -> 0.9679229
B90: Z-SCORE | C90: =NORMINV(C89,0,1) -> 1.8159267 | D90: =NORMINV(D89,0,1) -> 1.8492628 | E90: =NORMINV(E89,0,1) -> 1.826295 | F90: =NORMINV(F89,0,1) -> 1.8475688 | G90: =NORMINV(G89,0,1) -> 1.8511067
B91: TARGET SERVICE LEVEL | C91: ='OM Assumptions'!$C$18 -> 0.95 | D91: ='OM Assumptions'!$C$18 -> 0.95 | E91: ='OM Assumptions'!$C$18 -> 0.95 | F91: ='OM Assumptions'!$C$18 -> 0.95 | G91: ='OM Assumptions'!$C$18 -> 0.95
B92: ACTUAL > TARGET? | C92: =IF(C89>C91,"YES","NO") -> YES | D92: =IF(D89>D91,"YES","NO") -> YES | E92: =IF(E89>E91,"YES","NO") -> YES | F92: =IF(F89>F91,"YES","NO") -> YES | G92: =IF(G89>G91,"YES","NO") -> YES
B94: MAX STORAGE NEED INCLUDING SAFETY STOCK
B96: COMPONENT | C96: PCS NEEDED PER UNIT | D96: MAX RM INV ON HAND | E96: SPACE PER UNIT (FT^3) | F96: Total Cubic Feet
B97: Telescope Pole | C97: 1 | D97: ='OM Direct Materials & Direct La'!$H$75*C97+C29 -> 25110.177 | E97: =1*(0.5/12)*(0.5/12) -> 0.0017361111 | F97: =D97*E97 -> 43.594057
B98: Safety Flag | C98: 1 | D98: ='OM Direct Materials & Direct La'!$H$75*C98+$C$29 -> 25110.177 | E98: =1*1*(0.1/12) -> 0.0083333333 | F98: =D98*E98 -> 209.25147
B99: Bike Mount | C99: 1 | D99: ='OM Direct Materials & Direct La'!$H$75*C99+$C$29 -> 25110.177 | E99: =(1/12)*(2/12)*(1/12) -> 0.0011574074 | F99: =D99*E99 -> 29.062705
B100: Speaker | C100: 1 | D100: ='OM Direct Materials & Direct La'!$H$75*C100+$C$29 -> 25110.177 | E100: =(1/12)*(1/12)*(1/24) -> 0.00028935185 | F100: =D100*E100 -> 7.2656762
B101: Battery Pack | C101: 1 | D101: ='OM Direct Materials & Direct La'!$H$75*C101+$C$29 -> 25110.177 | E101: =(1.5/12)*(1/12)*(0.5/12) -> 0.00043402778 | F101: =D101*E101 -> 10.898514
B102: Attachable Spoke Magnet | C102: 1 | D102: ='OM Direct Materials & Direct La'!$H$75*C102+$C$29 -> 25110.177 | E102: =(0.25/12)*(0.25/12)*(0.25/12) -> 9.0422454e-06 | F102: =D102*E102 -> 0.22705238
B103: PCB | C103: 1 | D103: ='OM Direct Materials & Direct La'!$H$75*C103+$C$29 -> 25110.177 | E103: =(1/12)*(0.5/12)*(0.2/12) -> 5.787037e-05 | F103: =D103*E103 -> 1.4531352
B104: Wiring (meters) | C104: 0.5 | D104: ='OM Direct Materials & Direct La'!$H$75*C104+($C$29*C104) -> 12555.088 | E104: =(3.2)*(0.1/12)*(0.1/12) -> 0.00022222222 | F104: =D104*E104 -> 2.7900197
B105: Light | C105: 1 | D105: ='OM Direct Materials & Direct La'!$H$75*C105+$C$29 -> 25110.177 | E105: =(1/12)*(1/12)*(0.2/12) -> 0.00011574074 | F105: =D105*E105 -> 2.9062705
B106: Assembly Screws | C106: 12 | D106: ='OM Direct Materials & Direct La'!$H$75*C106+($C$29*C106) -> 301322.12 | E106: =(1/12)*(0.1/12)*(0.1/12) -> 5.787037e-06 | F106: =D106*E106 -> 1.7437623
B107: Hall Magnetic Sensor | C107: 1 | D107: ='OM Direct Materials & Direct La'!$H$75*C107+$C$29 -> 25110.177 | E107: =(1/12)*(1/12)*(0.5/12) -> 0.00028935185 | F107: =D107*E107 -> 7.2656762
B108: Pellets (lbs) | C108: 0.25 | D108: =10000+($C$29*C108) -> 12290.733 | E108: 0.03 | F108: =D108*E108 -> 368.722
B109: Custom Shells | C109: 1 | D109: ='OM Direct Materials & Direct La'!$H$75*C109 -> 15947.244 | E109: =(2.1/12)*(2.1/12)*(4.1/12) -> 0.010463542 | F109: =D109*E109 -> 166.86465
E110: MAX RM STORAGE NEED | F110: =sum(F97:F109) -> 852.04499
D112: MAX FG ON HAND | E112: FG UNIT (FT^3) | F112: Total Cubic Feet
D113: =E36+E35 -> 11371.049 | E113: =(2/12)*(2/12)*(4/12) -> 0.0092592593 | F113: =D113*E113 -> 105.28749
E114: MAX STORAGE NEED | F114: =F110+F113 -> 957.33248
E115: MAX CAPACITY | F115: ='OM Assumptions'!C35+('OM Assumptions'!C36*'OM Capital Expenditures'!I7) -> 1103.3333
E116: ENOUGH? | F116: =IF(F115>F114,"YES","NO") -> YES

Sheet OM Demand and Lead Time
B2: DEMAND AND LEAD TIME
B4: DEMAND VARIABILITY
B5: OPTIMISTIC | C5: 1.5
B6: MOST LIKELY | C6: 1
B7: PESSIMISTIC | C7: 0.5
B9: DEMAND
B10: YEAR | C10: DEMAND | D10: STANDARD DEVIATION | E10: WEEKLY MEAN | F10: WEEKLY STANDARD DEVIATION
B11: YEAR 1 | C11: ='MK Sales Projections'!C14 -> 47219.337 | D11: =((C11*C$5)-(C11*C$7))/6 -> 7869.8895 | E11: =C11/52 -> 908.06418 | F11: =D11/SQRT(52) -> 1091.3573
B12: YEAR 2 | C12: ='MK Sales Projections'!D14 -> 81204.43 | D12: =((C12*C$5)-(C12*C$7))/6 -> 13534.072 | E12: =C12/52 -> 1561.6236 | F12: =D12/SQRT(52) -> 1876.838
B13: YEAR 3 | C13: ='MK Sales Projections'!E14 -> 105763.53 | D13: =((C13*C$5)-(C13*C$7))/6 -> 17627.256 | E13: =C13/52 -> 2033.9141 | F13: =D13/SQRT(52) -> 2444.4605
B14: YEAR 4 | C14: ='MK Sales Projections'!F14 -> 159472.44 | D14: =((C14*C$5)-(C14*C$7))/6 -> 26578.74 | E14: =C14/52 -> 3066.7777 | F14: =D14/SQRT(52) -> 3685.808
B15: YEAR 5 | C15: ='MK Sales Projections'!G14 -> 238726.7 | D15: =((C15*C$5)-(C15*C$7))/6 -> 39787.783 | E15: =C15/52 -> 4590.8981 | F15: =D15/SQRT(52) -> 5517.5728
B17: LEAD TIME VARIABILITY
B18: MAXIMUM LEAD TIME | C18: 1.2
B19: BASE LEAD TIME | C19: 1
B20: MINIMUM LEAD TIME | C20: 0.8
B22: LEAD TIME (PRIMARY SUPPLIERS)
B23: YEAR | C23: AVERAGE LEAD TIME | D23: STANDARD DEVIATION | E23: WEEKLY MEAN | F23: WEEKLY STANDARD DEVIATION
B24: YEAR 1 | C24: ='OM Raw Material Data'!$D$17 -> 22.769231 | D24: =((C24*C$18)-(C$20*C24))/6 -> 1.5179487 | E24: =C24/7 -> 3.2527473 | F24: =D24/SQRT(7) -> 0.57373069
B25: YEAR 2 | C25: ='OM Raw Material Data'!$D$17 -> 22.769231 | D25: =((C25*C$18)-(C$20*C25))/6 -> 1.5179487 | E25: =C25/7 -> 3.2527473 | F25: =D25/SQRT(7) -> 0.57373069
B26: YEAR 3 | C26: ='OM Raw Material Data'!$D$17 -> 22.769231 | D26: =((C26*C$18)-(C$20*C26))/6 -> 1.5179487 | E26: =C26/7 -> 3.2527473 | F26: =D26/SQRT(7) -> 0.57373069
B27: YEAR 4 | C27: ='OM Raw Material Data'!$D$17 -> 22.769231 | D27: =((C27*C$18)-(C$20*C27))/6 -> 1.5179487 | E27: =C27/7 -> 3.2527473 | F27: =D27/SQRT(7) -> 0.57373069
B28: YEAR 5 | C28: ='OM Raw Material Data'!$D$17 -> 22.769231 | D28: =((C28*C$18)-(C$20*C28))/6 -> 1.5179487 | E28: =C28/7 -> 3.2527473 | F28: =D28/SQRT(7) -> 0.57373069

Sheet OM G&A Expenses
D2: GENERAL & ADMINISTRATIVE EXPENSES
D4: FIRM EMPLOYEES (YEAR 1) | I4: https://www.bls.gov/oes/2023/may/oes_tx.htm
C5: FUNCTION | D5: ROLE | E5: # OF EMPLOYEES | F5: TOTAL SALARY | G5: SALARY PER EMPLOYEE | H5: HOURS WORKED | I5: HOURLY WAGE | K5: LEGEND
D6: Chief Executive Officer | E6: 1 | F6: =E6*G6 -> 16290.671 | G6: ='MK Sales Projections'!C16*'OM Assumptions'!$F$3 -> 16290.671 | H6: ='OM Assumptions'!$C$7 -> 2000 | I6: =G6/H6 -> 8.1453357 | K6: EXECUTIVE
D7: Chief Financial Officer | E7: 1 | F7: =E7*G7 -> 16290.671 | G7: ='MK Sales Projections'!C16*'OM Assumptions'!$F$3 -> 16290.671 | H7: ='OM Assumptions'!$C$7 -> 2000 | I7: =G7/H7 -> 8.1453357 | K7: OPERATIONS
D8: Logistics & Purchasing Manager | E8: 1 | F8: =E8*G8 -> 78000 | G8: =I8*H8 -> 78000 | H8: ='OM Assumptions'!$C$7 -> 2000 | I8: 39 | K8: MARKETING
D9: Operations Manager | E9: 1 | F9: =E9*G9 -> 78000 | G9: =I9*H9 -> 78000 | H9: ='OM Assumptions'!$C$7 -> 2000 | I9: 39 | K9: FINANCE
D10: Mechanical Engineer | E10: 1 | F10: =E10*G10 -> 70000 | G10: =I10*H10 -> 70000 | H10: ='OM Assumptions'!$C$7 -> 2000 | I10: 35 | K10: ANALYTICS
D11: Information Systems Manager | E11: 1 | F11: =E11*G11 -> 70000 | G11: =I11*H11 -> 70000 | H11: ='OM Assumptions'!$C$7 -> 2000 | I11: 35
D12: Janitor | E12: 1 | F12: =E12*G12 -> 40000 | G12: =I12*H12 -> 40000 | H12: ='OM Assumptions'!$C$7 -> 2000 | I12: 20
D13: Customer Service Representative | E13: 1 | F13: =E13*G13 -> 50000 | G13: =I13*H13 -> 50000 | H13: ='OM Assumptions'!$C$7 -> 2000 | I13: 25
D14: Public Relations | E14: 1 | F14: =E14*G14 -> 50000 | G14: =I14*H14 -> 50000 | H14: ='OM Assumptions'!$C$7 -> 2000 | I14: 25
D15: Social Media Manager | E15: 1 | F15: =E15*G15 -> 50000 | G15: =I15*H15 -> 50000 | H15: ='OM Assumptions'!$C$7 -> 2000 | I15: 25
D16: Accountant | E16: 1 | F16: =E16*G16 -> 50000 | G16: =I16*H16 -> 50000 | H16: ='OM Assumptions'!$C$7 -> 2000 | I16: 25
D17: Inspector and Tester | E17: 1 | F17: =E17*G17 -> 59800 | G17: =I17*H17 -> 59800 | H17: ='OM Assumptions'!$C$7 -> 2000 | I17: 29.9
C18: Total C-Suite | D18: Total Employees | E18: TOTAL G&A YEAR 1 | F18: =SUM(F6:F17) -> 628381.34
C19: =SUM(E6+E7) -> 2 | D19: =SUM(E6:E17) -> 12 | E19: PER UNIT | F19: =F18/'MK Sales Projections'!C14 -> 13.307712
C20: Total Managers
C21: =SUM(E8,E9,E15) -> 3
C22: Total Direct Workers
C23: =SUM(E10,E11,E12,E13,E14,E16,E17) -> 7
D25: FIRM EMPLOYEES (YEAR 2) | I25: https://www.bls.gov/oes/2023/may/oes_tx.htm
C26: FUNCTION | D26: ROLE | E26: # OF EMPLOYEES | F26: TOTAL SALARY | G26: SALARY PER EMPLOYEE | H26: HOURS WORKED | I26: HOURLY WAGE
D27: Chief Executive Officer | E27: 1 | F27: =E27*G27 -> 27585.622 | G27: ='MK Sales Projections'!D16*'OM Assumptions'!$F$3 -> 27585.622 | H27: ='OM Assumptions'!$C$7 -> 2000 | I27: =G27/H27 -> 13.792811
D28: Chief Financial Officer | E28: 1 | F28: =E28*G28 -> 27585.622 | G28: ='MK Sales Projections'!D16*'OM Assumptions'!$F$3 -> 27585.622 | H28: ='OM Assumptions'!$C$7 -> 2000 | I28: =G28/H28 -> 13.792811
D29: Logistics & Purchasing Manager | E29: 1 | F29: =E29*G29 -> 80340 | G29: =I29*H29 -> 80340 | H29: ='OM Assumptions'!$C$7 -> 2000 | I29: =I8*(1+'OM Assumptions'!$F$4) -> 40.17
D30: Operations Manager | E30: 1 | F30: =E30*G30 -> 80340 | G30: =I30*H30 -> 80340 | H30: ='OM Assumptions'!$C$7 -> 2000 | I30: =I9*(1+'OM Assumptions'!$F$4) -> 40.17
D31: Mechanical Engineer | E31: 1 | F31: =E31*G31 -> 72100 | G31: =I31*H31 -> 72100 | H31: ='OM Assumptions'!$C$7 -> 2000 | I31: =I10*(1+'OM Assumptions'!$F$4) -> 36.05
D32: Information Systems Manager | E32: 1 | F32: =E32*G32 -> 72100 | G32: =I32*H32 -> 72100 | H32: ='OM Assumptions'!$C$7 -> 2000 | I32: =I11*(1+'OM Assumptions'!$F$4) -> 36.05
D33: Janitor | E33: 1 | F33: =E33*G33 -> 41200 | G33: =I33*H33 -> 41200 | H33: ='OM Assumptions'!$C$7 -> 2000 | I33: =I12*(1+'OM Assumptions'!$F$4) -> 20.6
D34: Customer Service Representative | E34: 1 | F34: =E34*G34 -> 51500 | G34: =I34*H34 -> 51500 | H34: ='OM Assumptions'!$C$7 -> 2000 | I34: =I13*(1+'OM Assumptions'!$F$4) -> 25.75
D35: Public Relations | E35: 1 | F35: =E35*G35 -> 51500 | G35: =I35*H35 -> 51500 | H35: ='OM Assumptions'!$C$7 -> 2000 | I35: =I14*(1+'OM Assumptions'!$F$4) -> 25.75
D36: Social Media Manager | E36: 1 | F36: =E36*G36 -> 51500 | G36: =I36*H36 -> 51500 | H36: ='OM Assumptions'!$C$7 -> 2000 | I36: =I15*(1+'OM Assumptions'!$F$4) -> 25.75
D37: Accountant | E37: 1 | F37: =E37*G37 -> 51500 | G37: =I37*H37 -> 51500 | H37: ='OM Assumptions'!$C$7 -> 2000 | I37: =I16*(1+'OM Assumptions'!$F$4) -> 25.75
D38: Inspector and Tester | E38: 1 | F38: =E38*G38 -> 61594 | G38: =I38*H38 -> 61594 | H38: ='OM Assumptions'!$C$7 -> 2000 | I38: =I17*(1+'OM Assumptions'!$F$4) -> 30.797
C39: Total C-Suite | D39: Total Employees | E39: TOTAL G&A YEAR 2 | F39: =SUM(F27:F38) -> 668845.24
C40: =SUM(E27+E28) -> 2 | D40: =SUM(E27:E38) -> 12 | E40: PER UNIT | F40: =F39/'MK Sales Projections'!D14 -> 8.2365611
C41: Total Managers
C42: =SUM(E29,E30,E36,E32) -> 4
C43: Total General Workers
C44: =SUM(E31,E33,E34,E35,E37,E38) -> 6
D46: FIRM EMPLOYEES (YEAR 3) | I46: https://www.bls.gov/oes/2023/may/oes_tx.htm
C47: FUNCTION | D47: ROLE | E47: # OF EMPLOYEES | F47: TOTAL SALARY | G47: SALARY PER EMPLOYEE | H47: HOURS WORKED | I47: HOURLY WAGE
D48: Chief Executive Officer | E48: 1 | F48: =E48*G48 -> 35031.767 | G48: ='MK Sales Projections'!E16*'OM Assumptions'!$F$3 -> 35031.767 | H48: ='OM Assumptions'!$C$7 -> 2000 | I48: =G48/H48 -> 17.515883
D49: Chief Operating Officer | E49: 1 | F49: =E49*G49 -> 35031.767 | G49: ='MK Sales Projections'!E16*'OM Assumptions'!$F$3 -> 35031.767 | H49: ='OM Assumptions'!$C$7 -> 2000 | I49: =G49/H49 -> 17.515883
D50: Chief Financial Officer | E50: 1 | F50: =E50*G50 -> 35031.767 | G50: ='MK Sales Projections'!E16*'OM Assumptions'!$F$3 -> 35031.767 | H50: ='OM Assumptions'!$C$7 -> 2000 | I50: =G50/H50 -> 17.515883
D51: Logistics & Purchasing Manager | E51: 1 | F51: =E51*G51 -> 82750.2 | G51: =I51*H51 -> 82750.2 | H51: ='OM Assumptions'!$C$7 -> 2000 | I51: =I29*(1+'OM Assumptions'!$F$4) -> 41.3751
D52: Operations Manager | E52: 1 | F52: =E52*G52 -> 82750.2 | G52: =I52*H52 -> 82750.2 | H52: ='OM Assumptions'!$C$7 -> 2000 | I52: =I30*(1+'OM Assumptions'!$F$4) -> 41.3751
D53: Mechanical Engineer | E53: 1 | F53: =E53*G53 -> 74263 | G53: =I53*H53 -> 74263 | H53: ='OM Assumptions'!$C$7 -> 2000 | I53: =I31*(1+'OM Assumptions'!$F$4) -> 37.1315
D54: IT Specialist | E54: 1 | F54: =E54*G54 -> 63000 | G54: =I54*H54 -> 63000 | H54: ='OM Assumptions'!$C$7 -> 2000 | I54: 31.5
D55: Janitor | E55: 1 | F55: =E55*G55 -> 42436 | G55: =I55*H55 -> 42436 | H55: ='OM Assumptions'!$C$7 -> 2000 | I55: =I33*(1+'OM Assumptions'!$F$4) -> 21.218
D56: Customer Service Representative | E56: 1 | F56: =E56*G56 -> 53045 | G56: =I56*H56 -> 53045 | H56: ='OM Assumptions'!$C$7 -> 2000 | I56: =I34*(1+'OM Assumptions'!$F$4) -> 26.5225
D57: Public Relations | E57: 1 | F57: =E57*G57 -> 53045 | G57: =I57*H57 -> 53045 | H57: ='OM Assumptions'!$C$7 -> 2000 | I57: =I35*(1+'OM Assumptions'!$F$4) -> 26.5225
D58: Social Media Manager | E58: 1 | F58: =E58*G58 -> 53045 | G58: =I58*H58 -> 53045 | H58: ='OM Assumptions'!$C$7 -> 2000 | I58: =I36*(1+'OM Assumptions'!$F$4) -> 26.5225
D59: Accountant | E59: 2 | F59: =E59*G59 -> 106090 | G59: =I59*H59 -> 53045 | H59: ='OM Assumptions'!$C$7 -> 2000 | I59: =I37*(1+'OM Assumptions'!$F$4) -> 26.5225
D60: Inspector and Tester | E60: 1 | F60: =E60*G60 -> 63441.82 | G60: =I60*H60 -> 63441.82 | H60: ='OM Assumptions'!$C$7 -> 2000 | I60: =I38*(1+'OM Assumptions'!$F$4) -> 31.72091
D61: Data Analyst | E61: 1 | F61: =E61*G61 -> 71000 | G61: =I61*H61 -> 71000 | H61: ='OM Assumptions'!$C$7 -> 2000 | I61: 35.5
C62: Total C-Suite | D62: Total Employees | E62: TOTAL G&A YEAR 3 | F62: =SUM(F48:F61) -> 849961.52
C63: =SUM(E48:E50) -> 3 | D63: =SUM(E48:E61) -> 15 | E63: PER UNIT | F63: =F62/'MK Sales Projections'!F14 -> 5.3298334
C64: Total Managers
C65: =SUM(E51,E52,E58) -> 3
C66: Total General Workers
C67: =SUM(E53,E54,E55,E56,E57,E59,E60,E61) -> 9
D69: FIRM EMPLOYEES (YEAR 4) | I69: https://www.bls.gov/oes/2023/may/oes_tx.htm
C70: FUNCTION | D70: ROLE | E70: # OF EMPLOYEES | F70: TOTAL SALARY | G70: SALARY PER EMPLOYEE | H70: HOURS WORKED | I70: HOURLY WAGE
D71: Chief Executive Officer | E71: 1 | F71: =E71*G71 -> 50407.466 | G71: ='MK Sales Projections'!F16*'OM Assumptions'!$F$3 -> 50407.466 | H71: ='OM Assumptions'!$C$7 -> 2000 | I71: =G71/H71 -> 25.203733
D72: Chief Operating Officer | E72: 1 | F72: =E72*G72 -> 50407.466 | G72: ='MK Sales Projections'!F16*'OM Assumptions'!$F$3 -> 50407.466 | H72: ='OM Assumptions'!$C$7 -> 2000 | I72: =G72/H72 -> 25.203733
D73: Chief Financial Officer | E73: 1 | F73: =E73*G73 -> 50407.466 | G73: ='MK Sales Projections'!F16*'OM Assumptions'!$F$3 -> 50407.466 | H73: ='OM Assumptions'!$C$7 -> 2000 | I73: =G73/H73 -> 25.203733
D74: Logistics & Purchasing Manager | E74: 1 | F74: =E74*G74 -> 85232.706 | G74: =I74*H74 -> 85232.706 | H74: ='OM Assumptions'!$C$7 -> 2000 | I74: =I51*(1+'OM Assumptions'!$F$4) -> 42.616353
D75: Operations Manager | E75: 1 | F75: =E75*G75 -> 85232.706 | G75: =I75*H75 -> 85232.706 | H75: ='OM Assumptions'!$C$7 -> 2000 | I75: =I52*(1+'OM Assumptions'!$F$4) -> 42.616353
D76: Mechanical Engineer | E76: 1 | F76: =E76*G76 -> 76490.89 | G76: =I76*H76 -> 76490.89 | H76: ='OM Assumptions'!$C$7 -> 2000 | I76: =I53*(1+'OM Assumptions'!$F$4) -> 38.245445
D77: IT Specialist | E77: 1 | F77: =E77*G77 -> 64890 | G77: =I77*H77 -> 64890 | H77: ='OM Assumptions'!$C$7 -> 2000 | I77: =I54*(1+'OM Assumptions'!$F$4) -> 32.445
D78: Janitor | E78: 2 | F78: =E78*G78 -> 87418.16 | G78: =I78*H78 -> 43709.08 | H78: ='OM Assumptions'!$C$7 -> 2000 | I78: =I55*(1+'OM Assumptions'!$F$4) -> 21.85454
D79: Customer Service Representative | E79: 1 | F79: =E79*G79 -> 54636.35 | G79: =I79*H79 -> 54636.35 | H79: ='OM Assumptions'!$C$7 -> 2000 | I79: =I56*(1+'OM Assumptions'!$F$4) -> 27.318175
D80: Public Relations | E80: 1 | F80: =E80*G80 -> 54636.35 | G80: =I80*H80 -> 54636.35 | H80: ='OM Assumptions'!$C$7 -> 2000 | I80: =I57*(1+'OM Assumptions'!$F$4) -> 27.318175
D81: Human Resources Manager | E81: 1 | F81: =E81*G81 -> 64400 | G81: =I81*H81 -> 64400 | H81: ='OM Assumptions'!$C$7 -> 2000 | I81: 32.2
D82: Social Media Manager | E82: 1 | F82: =E82*G82 -> 54636.35 | G82: =I82*H82 -> 54636.35 | H82: ='OM Assumptions'!$C$7 -> 2000 | I82: =I58*(1+'OM Assumptions'!$F$4) -> 27.318175
D83: Accountant | E83: 2 | F83: =E83*G83 -> 109272.7 | G83: =I83*H83 -> 54636.35 | H83: ='OM Assumptions'!$C$7 -> 2000 | I83: =I59*(1+'OM Assumptions'!$F$4) -> 27.318175
D84: Inspector and Tester | E84: 1 | F84: =E84*G84 -> 65345.075 | G84: =I84*H84 -> 65345.075 | H84: ='OM Assumptions'!$C$7 -> 2000 | I84: =I60*(1+'OM Assumptions'!$F$4) -> 32.672537
D85: Data Analyst | E85: 1 | F85: =E85*G85 -> 73130 | G85: =I85*H85 -> 73130 | H85: ='OM Assumptions'!$C$7 -> 2000 | I85: =I61*(1+'OM Assumptions'!$F$4) -> 36.565
C86: Total C-Suite | D86: Total Employees | E86: TOTAL G&A YEAR 4 | F86: =SUM(F71:F85) -> 1026543.7
C87: =SUM(E71:E73) -> 3 | D87: =SUM(E71:E85) -> 17 | E87: PER UNIT | F87: =F86/'MK Sales Projections'!F14 -> 6.4371229
C88: Total Managers
C89: =SUM(E74,E75,E81,E82) -> 4
C90: Total General Workers
C91: =SUM(E76,E77,E78,E79,E80,E83,E84,E85) -> 10
D93: FIRM EMPLOYEES (YEAR 5) | I93: https://www.bls.gov/oes/2023/may/oes_tx.htm
C94: FUNCTION | D94: ROLE | E94: # OF EMPLOYEES | F94: TOTAL SALARY | G94: SALARY PER EMPLOYEE | H94: HOURS WORKED | I94: HOURLY WAGE
D95: Chief Executive Officer | E95: 1 | F95: =E95*G95 -> 73862.041 | G95: ='MK Sales Projections'!$G$16*'OM Assumptions'!$F$3 -> 73862.041 | H95: ='OM Assumptions'!$C$7 -> 2000 | I95: =G95/H95 -> 36.93102
D96: Chief Operating Officer | E96: 1 | F96: =E96*G96 -> 73862.041 | G96: ='MK Sales Projections'!$G$16*'OM Assumptions'!$F$3 -> 73862.041 | H96: ='OM Assumptions'!$C$7 -> 2000 | I96: =G96/H96 -> 36.93102
D97: Chief Marketing Officer | E97: 1 | F97: =E97*G97 -> 73862.041 | G97: ='MK Sales Projections'!$G$16*'OM Assumptions'!$F$3 -> 73862.041 | H97: ='OM Assumptions'!$C$7 -> 2000 | I97: =G97/H97 -> 36.93102
D98: Chief Financial Officer | E98: 1 | F98: =E98*G98 -> 73862.041 | G98: ='MK Sales Projections'!$G$16*'OM Assumptions'!$F$3 -> 73862.041 | H98: ='OM Assumptions'!$C$7 -> 2000 | I98: =G98/H98 -> 36.93102
D99: Logistics & Purchasing Manager | E99: 1 | F99: =E99*G99 -> 87789.687 | G99: =I99*H99 -> 87789.687 | H99: ='OM Assumptions'!$C$7 -> 2000 | I99: =I74*(1+'OM Assumptions'!$F$4) -> 43.894844
D100: Operations Manager | E100: 1 | F100: =E100*G100 -> 87789.687 | G100: =I100*H100 -> 87789.687 | H100: ='OM Assumptions'!$C$7 -> 2000 | I100: =I75*(1+'OM Assumptions'!$F$4) -> 43.894844
D101: Mechanical Engineer | E101: 1 | F101: =E101*G101 -> 78785.617 | G101: =I101*H101 -> 78785.617 | H101: ='OM Assumptions'!$C$7 -> 2000 | I101: =I76*(1+'OM Assumptions'!$F$4) -> 39.392808
D102: IT Specialist | E102: 1 | F102: =E102*G102 -> 66836.7 | G102: =I102*H102 -> 66836.7 | H102: ='OM Assumptions'!$C$7 -> 2000 | I102: =I77*(1+'OM Assumptions'!$F$4) -> 33.41835
D103: Computer Programmer | E103: 1 | F103: =E103*G103 -> 63000 | G103: =I103*H103 -> 63000 | H103: ='OM Assumptions'!$C$7 -> 2000 | I103: 31.5
D104: Information Systems Manager | E104: 1 | F104: =E104*G104 -> 65000 | G104: =I104*H104 -> 65000 | H104: ='OM Assumptions'!$C$7 -> 2000 | I104: 32.5
D105: Janitor | E105: 2 | F105: =E105*G105 -> 90040.705 | G105: =I105*H105 -> 45020.352 | H105: ='OM Assumptions'!$C$7 -> 2000 | I105: =I78*(1+'OM Assumptions'!$F$4) -> 22.510176
D106: Customer Service Representative | E106: 2 | F106: =E106*G106 -> 112550.88 | G106: =I106*H106 -> 56275.44 | H106: ='OM Assumptions'!$C$7 -> 2000 | I106: =I79*(1+'OM Assumptions'!$F$4) -> 28.13772
...

Sheet OM Process Flow
B2: OM PROCESS FLOW (YEARS 1-5)
B4: YEAR 1
B5: TASK | C5: TIME (SECONDS) | D5: WORKSTATIONS | E5: WORKERS PER WORKSTATION | F5: WORKSTATION TIME (SEC) | G5: EXCEEDS TAKT TIME?
B6: INJECTION MOLDING | C6: 30 | E6: 1 | F6: =SUM(C6:C7) -> 150 | G6: =IF(F6>$I$7,"YES","NO") -> NO | I6: TAKT TIME | K6: LEGEND
B7: ELECTRONIC ASSEMBLY | C7: 120 | I7: ='OM Direct Materials & Direct La'!D7 -> 152.4799 | K7: WORKSTATION 1
B8: ELECTRONIC INSTALLATION | C8: 80 | E8: 1 | F8: =SUM(C8:C9) -> 120 | G8: =IF(F8>$I$7,"YES","NO") -> NO | K8: WORKSTATION 2
B9: FLAG ASSEMBLY | C9: 40 | K9: WORKSTATION 3
B10: SECURING CHASSIS | C10: 40 | E10: 1 | F10: =SUM(C10:C11) -> 120 | G10: =IF(F10>$I$7,"YES","NO") -> NO | I10: # OF WORKSTATIONS | K10: WORKSTATION 4
B11: QUALITY CHECK | C11: 80 | I11: 4 | K11: WORKSTATION 5
B12: PACKAGING WITH SHELLS | C12: 60 | E12: 1 | F12: =C12/E12 -> 60 | G12: =IF(F12>$I$7,"YES","NO") -> NO | K12: WORKSTATION 6
B13: THROUGHPUT TIME | C13: =SUM(C6:C12) -> 450 | D13: TOTAL WORKERS | E13: =SUM(E6:E12) -> 4 | F13: =SUM(F6:F12) -> 450 | I13: EFFICIENCY | K13: WORKSTATION 7
B14: CYCLE TIME | C14: =MAX(C6:C12) -> 120 | I14: =F13/(I7*I11) -> 0.73780214
B16: YEAR 2
B17: TASK | C17: TIME (SECONDS) | D17: WORKSTATIONS | E17: WORKERS PER WORKSTATION | F17: WORKSTATION TIME (SEC) | G17: EXCEEDS TAKT TIME?
B18: INJECTION MOLDING | C18: 30 | E18: 1 | F18: =C18/E18 -> 30 | G18: =IF(F18>$I$19,"YES","NO") -> NO | I18: TAKT TIME
B19: ELECTRONIC ASSEMBLY | C19: 120 | E19: 2 | F19: =C19/E19 -> 60 | G19: =IF(F19>$I$19,"YES","NO") -> NO | I19: ='OM Direct Materials & Direct La'!E7 -> 88.665114
B20: ELECTRONIC INSTALLATION | C20: 80 | E20: 1 | F20: =SUM(C20)/E20 -> 80 | G20: =IF(F20>$I$19,"YES","NO") -> NO
B21: FLAG ASSEMBLY | C21: 40 | E21: 1 | F21: =SUM(C21:C22)/E21 -> 80 | G21: =IF(F21>$I$19,"YES","NO") -> NO
B22: SECURING CHASSIS | C22: 40 | I22: # OF WORKSTATIONS
B23: QUALITY CHECK | C23: 80 | E23: 1 | F23: =C23/E23 -> 80 | G23: =IF(F23>$I$19,"YES","NO") -> NO | I23: 6
B24: PACKAGING WITH SHELLS | C24: 60 | E24: 1 | F24: =SUM(C24)/E24 -> 60 | G24: =IF(F24>$I$19,"YES","NO") -> NO
B25: THROUGHPUT TIME | C25: =SUM(C18:C24) -> 450 | D25: TOTAL | E25: =SUM(E18:E24) -> 7 | F25: =SUM(F18:F24) -> 390 | I25: EFFICIENCY
B26: CYCLE TIME | C26: =C20 -> 80 | I26: =F25/(I19*I23) -> 0.73309555
B28: YEAR 3
B29: TASK | C29: TIME (SECONDS) | D29: WORKSTATIONS | E29: WORKERS PER WORKSTATION | F29: WORKSTATION TIME (SEC) | G29: EXCEEDS TAKT TIME?
B30: INJECTION MOLDING | C30: 30 | E30: 1 | F30: =C30/E30 -> 30 | G30: =IF(F30>$I$31,"YES","NO") -> NO | I30: TAKT TIME
B31: ELECTRONIC ASSEMBLY | C31: 120 | E31: 2 | F31: =C31/E31 -> 60 | G31: =IF(F31>$I$31,"YES","NO") -> NO | I31: ='OM Direct Materials & Direct La'!F7 -> 68.076394
B32: ELECTRONIC INSTALLATION | C32: 80 | E32: 2 | F32: =C32/E32 -> 40 | G32: =IF(F32>$I$31,"YES","NO") -> NO
B33: FLAG ASSEMBLY | C33: 40 | E33: 1 | F33: =SUM(C33)/E33 -> 40 | G33: =IF(F33>$I$31,"YES","NO") -> NO
B34: SECURING CHASSIS | C34: 40 | E34: 1 | F34: =C34/E34 -> 40 | G34: =IF(F34>$I$31,"YES","NO") -> NO | I34: # OF WORKSTATIONS
B35: QUALITY CHECK | C35: 80 | E35: 2 | F35: =C35/E35 -> 40 | G35: =IF(F35>$I$31,"YES","NO") -> NO | I35: 7
B36: PACKAGING WITH SHELLS | C36: 60 | E36: 1 | F36: =C36/E36 -> 60 | G36: =IF(F36>$I$31,"YES","NO") -> NO
B37: THROUGHPUT TIME | C37: =SUM(C30:C36) -> 450 | D37: TOTAL WORKERS | E37: =SUM(E30:E36) -> 10 | F37: =SUM(F30:F36) -> 310 | I37: EFFICIENCY
B38: CYCLE TIME | C38: =MAX(F30:F36) -> 60 | I38: =F37/(I31*I35) -> 0.65052967
B40: YEAR 4
B41: TASK | C41: TIME (SECONDS) | D41: WORKSTATIONS | E41: WORKERS PER WORKSTATION | F41: WORKSTATION TIME (SEC) | G41: EXCEEDS TAKT TIME?
B42: INJECTION MOLDING | C42: 30 | E42: 1 | F42: =C42/E42 -> 30 | G42: =IF(F42>$I$43,"YES","NO") -> NO | I42: TAKT TIME
B43: ELECTRONIC ASSEMBLY | C43: 120 | E43: 3 | F43: =C43/E43 -> 40 | G43: =IF(F43>$I$43,"YES","NO") -> NO | I43: ='OM Direct Materials & Direct La'!G7 -> 45.148868
B44: ELECTRONIC INSTALLATION | C44: 80 | E44: 2 | F44: =C44/E44 -> 40 | G44: =IF(F44>$I$43,"YES","NO") -> NO
B45: FLAG ASSEMBLY | C45: 40 | E45: 1 | F45: =C45/E45 -> 40 | G45: =IF(F45>$I$43,"YES","NO") -> NO
B46: SECURING CHASSIS | C46: 40 | E46: 1 | F46: =C46/E46 -> 40 | G46: =IF(F46>$I$43,"YES","NO") -> NO | I46: # OF WORKSTATIONS
B47: QUALITY CHECK | C47: 80 | E47: 2 | F47: =C47/E47 -> 40 | G47: =IF(F47>$I$43,"YES","NO") -> NO | I47: 7
B48: PACKAGING WITH SHELLS | C48: 60 | E48: 2 | F48: =C48/E48 -> 30 | G48: =IF(F48>$I$43,"YES","NO") -> NO
B49: THROUGHPUT TIME | C49: =SUM(C42:C48) -> 450 | D49: TOTAL WORKERS | E49: =SUM(E42:E48) -> 12 | F49: =SUM(F42:F48) -> 260 | I49: EFFICIENCY
B50: CYCLE TIME | C50: =MAX(F41:F48) -> 40 | I50: =F49/(I43*I47) -> 0.82267528
B52: YEAR 5
B53: TASK | C53: TIME (SECONDS) | D53: WORKSTATIONS | E53: WORKERS PER WORKSTATION | F53: WORKSTATION TIME (SEC) | G53: EXCEEDS TAKT TIME?
B54: INJECTION MOLDING | C54: 30 | E54: 1 | F54: =C54/E54 -> 30 | G54: =IF(F54>$I$55,"YES","NO") -> NO | I54: TAKT TIME
B55: ELECTRONIC ASSEMBLY | C55: 120 | E55: 4 | F55: =C55/E55 -> 30 | G55: =IF(F55>$I$55,"YES","NO") -> NO | I55: ='OM Direct Materials & Direct La'!H7 -> 30.160012
B56: ELECTRONIC INSTALLATION | C56: 80 | E56: 3 | F56: =C56/E56 -> 26.666667 | G56: =IF(F56>$I$55,"YES","NO") -> NO
B57: FLAG ASSEMBLY | C57: 40 | E57: 2 | F57: =C57/E57 -> 20 | G57: =IF(F57>$I$55,"YES","NO") -> NO
B58: SECURING CHASSIS | C58: 40 | E58: 2 | F58: =C58/E58 -> 20 | G58: =IF(F58>$I$55,"YES","NO") -> NO | I58: # OF WORKSTATIONS
B59: QUALITY CHECK | C59: 80 | E59: 3 | F59: =C59/E59 -> 26.666667 | G59: =IF(F59>$I$55,"YES","NO") -> NO | I59: 7
B60: PACKAGING WITH SHELLS | C60: 60 | E60: 2 | F60: =C60/E60 -> 30 | G60: =IF(F60>$I$55,"YES","NO") -> NO
B61: THROUGHPUT TIME | C61: =SUM(C54:C60) -> 450 | D61: TOTAL WORKERS | E61: =SUM(E54:E60) -> 17 | F61: =SUM(F54:F60) -> 183.33333 | I61: EFFICIENCY
B62: CYCLE TIME | C62: =MAX(F54:F60) -> 30 | I62: =F61/(I55*I59) -> 0.86838416

Sheet OM Process Layout
B2: YEAR 1 PROCESS LAYOUT | K2: LEGEND
K3: WORKSTATION 1
K4: WORKSTATION 2
K5: WORKSTATION 3
K6: WORKSTATION 4
K8: YEAR 1
K9: TASK | L9: TIME (SECONDS) | M9: WORKSTATIONS | N9: WORKERS PER WORKSTATION | O9: WORKSTATION TIME (SEC)
K10: INJECTION MOLDING | L10: 30 | N10: 1 | O10: 150
K11: ELECTRONIC ASSEMBLY | L11: 120
K12: ELECTRONIC INSTALLATION | L12: 80 | N12: 1 | O12: 120
K13: FLAG ASSEMBLY | L13: 40
K14: SECURING CHASSIS | L14: 40 | N14: 1 | O14: 120
K15: QUALITY CHECK | L15: 80
K16: PACKAGING WITH SHELLS | L16: 60 | N16: 1 | O16: 60
K17: THROUGHPUT TIME | L17: 450 | M17: TOTAL WORKERS | N17: 4 | O17: 450
K18: CYCLE TIME | L18: 120
K20: TAKT TIME
K21: ='OM Process Flow'!I7 -> 152.4799
K24: # OF WORKSTATIONS
K25: ='OM Process Flow'!I11 -> 4
K27: EFFICIENCY
K28: ='OM Process Flow'!I14 -> 0.73780214
B34: YEAR 2 PROCESS LAYOUT | K34: LEGEND
K35: WORKSTATION 1
K36: WORKSTATION 2
K37: WORKSTATION 3
K38: WORKSTATION 4
K39: WORKSTATION 5
K40: WORKSTATION 6
K42: YEAR 2
K43: TASK | L43: TIME (SECONDS) | M43: WORKSTATIONS | N43: WORKERS PER WORKSTATION | O43: WORKSTATION TIME (SEC)
K44: INJECTION MOLDING | L44: 30 | N44: 1 | O44: 30
K45: ELECTRONIC ASSEMBLY | L45: 120 | N45: 2 | O45: 60
K46: ELECTRONIC INSTALLATION | L46: 80 | N46: 1 | O46: 80
K47: FLAG ASSEMBLY | L47: 40 | N47: 1 | O47: 80
K48: SECURING CHASSIS | L48: 40
K49: QUALITY CHECK | L49: 80 | N49: 1 | O49: 80
K50: PACKAGING WITH SHELLS | L50: 60 | N50: 1 | O50: 60
K51: THROUGHPUT TIME | L51: 450 | M51: TOTAL | N51: 7 | O51: 390
K52: CYCLE TIME | L52: 120
K54: TAKT TIME
K55: ='OM Process Flow'!I19 -> 88.665114
K58: # OF WORKSTATIONS
K59: ='OM Process Flow'!I23 -> 6
K61: EFFICIENCY
K62: ='OM Process Flow'!I26 -> 0.73309555
B66: YEAR 3 PROCESS FLOW LAYOUT | K66: LEGEND
K67: WORKSTATION 1
K68: WORKSTATION 2
K69: WORKSTATION 3
K70: WORKSTATION 4
K71: WORKSTATION 5
K72: WORKSTATION 6
K73: WORKSTATION 7
K75: YEAR 3
K76: TASK | L76: TIME (SECONDS) | M76: WORKSTATIONS | N76: WORKERS PER WORKSTATION | O76: WORKSTATION TIME (SEC)
K77: INJECTION MOLDING | L77: 30 | N77: 1 | O77: 30
K78: ELECTRONIC ASSEMBLY | L78: 120 | N78: 2 | O78: 60
K79: ELECTRONIC INSTALLATION | L79: 80 | N79: 1 | O79: 80
K80: FLAG ASSEMBLY | L80: 40 | N80: 1 | O80: 40
K81: SECURING CHASSIS | L81: 40 | N81: 1 | O81: 40
K82: QUALITY CHECK | L82: 80 | N82: 2 | O82: 40
K83: PACKAGING WITH SHELLS | L83: 60 | N83: 1 | O83: 60
K84: THROUGHPUT TIME | L84: 450 | M84: TOTAL WORKERS | N84: 9 | O84: 350
K85: CYCLE TIME | L85: 80
K87: TAKT TIME
K88: ='OM Process Flow'!I31 -> 68.076394
K91: # OF WORKSTATIONS
K92: ='OM Process Flow'!I35 -> 7
K94: EFFICIENCY
K95: ='OM Process Flow'!I38 -> 0.65052967
B98: YEAR 4 PROCESS FLOW LAYOUT | K98: LEGEND
K99: WORKSTATION 1
K100: WORKSTATION 2
K101: WORKSTATION 3
K102: WORKSTATION 4
K103: WORKSTATION 5
K104: WORKSTATION 6
K105: WORKSTATION 7
K107: YEAR 4
K108: TASK | L108: TIME (SECONDS) | M108: WORKSTATIONS | N108: WORKERS PER WORKSTATION | O108: WORKSTATION TIME (SEC)
K109: INJECTION MOLDING | L109: 30 | N109: 1 | O109: 30
K110: ELECTRONIC ASSEMBLY | L110: 120 | N110: 3 | O110: 40
K111: ELECTRONIC INSTALLATION | L111: 80 | N111: 2 | O111: 40
K112: FLAG ASSEMBLY | L112: 40 | N112: 1 | O112: 40
K113: SECURING CHASSIS | L113: 40 | N113: 1 | O113: 40
K114: QUALITY CHECK | L114: 80 | N114: 2 | O114: 40
K115: PACKAGING WITH SHELLS | L115: 60 | N115: 2 | O115: 30
K116: THROUGHPUT TIME | L116: 450 | M116: TOTAL WORKERS | N116: 12 | O116: 260
K117: CYCLE TIME | L117: 40
K119: TAKT TIME
K120: ='OM Process Flow'!I43 -> 45.148868
K123: # OF WORKSTATIONS
K124: ='OM Process Flow'!I47 -> 7
K126: EFFICIENCY
K127: ='OM Process Flow'!I50 -> 0.82267528
B130: YEAR 5 PROCESS FLOW LAYOUT | K130: LEGEND
K131: WORKSTATION 1
K132: WORKSTATION 2
K133: WORKSTATION 3
...

Sheet OM Capacity Analysis
B2: CAPACITY ANALYSIS
B4: CAPACITY UTILIZATION
B6: YEAR 1
B7: TASK | C7: TIME (SECONDS) | D7: WORKERS PER TASK | E7: CYCLE TIME | F7: CAPACITY UTILIZATION | H7: AVAILABLE TIME
B8: INJECTION MOLDING | C8: ='OM Process Flow'!C6/D8 -> 30 | D8: 1 | E8: ='OM Process Flow'!$C$14 -> 120 | F8: =C8/E8 -> 0.25 | H8: ='OM Assumptions'!$C$7 -> 2000
B9: ELECTRONIC ASSEMBLY | C9: ='OM Process Flow'!C7/D9 -> 120 | D9: 1 | E9: ='OM Process Flow'!$C$14 -> 120 | F9: =C9/E9 -> 1
B10: ELECTRONIC INSTALLATION | C10: ='OM Process Flow'!C8/D10 -> 80 | D10: 1 | E10: ='OM Process Flow'!$C$14 -> 120 | F10: =C10/E10 -> 0.66666667 | H10: MAXIMUM CAPACITY
B11: FLAG ASSEMBLY | C11: ='OM Process Flow'!C9/D11 -> 40 | D11: 1 | E11: ='OM Process Flow'!$C$14 -> 120 | F11: =C11/E11 -> 0.33333333 | H11: =((8*60*60)/E8)*250 -> 60000
B12: SECURING CHASSIS | C12: ='OM Process Flow'!C10/D12 -> 40 | D12: 1 | E12: ='OM Process Flow'!$C$14 -> 120 | F12: =C12/E12 -> 0.33333333
B13: QUALITY CHECK | C13: ='OM Process Flow'!C11/D13 -> 80 | D13: 1 | E13: ='OM Process Flow'!$C$14 -> 120 | F13: =C13/E13 -> 0.66666667 | H13: DEMAND UTILIZATION
B14: PACKAGING WITH SHELLS | C14: ='OM Process Flow'!C12/D14 -> 60 | D14: 1 | E14: ='OM Process Flow'!$C$14 -> 120 | F14: =C14/E14 -> 0.5 | H14: ='MK Sales Projections'!C14/H11 -> 0.78698895
E15: AVERAGE CAPACITY UTILIZATION | F15: =AVERAGE(F8:F14) -> 0.53571429
B16: YEAR 2
B17: TASK | C17: TIME (SECONDS) | D17: WORKERS PER TASK | E17: CYCLE TIME | F17: CAPACITY UTILIZATION | H17: AVAILABLE TIME
B18: INJECTION MOLDING | C18: ='OM Process Flow'!C18/D18 -> 30 | D18: ='OM Process Flow'!E18 -> 1 | E18: ='OM Process Flow'!$C$26 -> 80 | F18: =C18/E18 -> 0.375 | H18: ='OM Assumptions'!$C$7 -> 2000
B19: ELECTRONIC ASSEMBLY | C19: ='OM Process Flow'!C19/D19 -> 60 | D19: ='OM Process Flow'!E19 -> 2 | E19: ='OM Process Flow'!$C$26 -> 80 | F19: =C19/E19 -> 0.75
B20: ELECTRONIC INSTALLATION | C20: ='OM Process Flow'!C20/D20 -> 80 | D20: ='OM Process Flow'!E20 -> 1 | E20: ='OM Process Flow'!$C$26 -> 80 | F20: =C20/E20 -> 1 | H20: MAXIMUM CAPACITY
B21: FLAG ASSEMBLY | C21: ='OM Process Flow'!C21/D21 -> 40 | D21: ='OM Process Flow'!E21 -> 1 | E21: ='OM Process Flow'!$C$26 -> 80 | F21: =C21/E21 -> 0.5 | H21: =((8*60*60)/E18)*250 -> 90000
B22: SECURING CHASSIS | C22: ='OM Process Flow'!C22/D22 -> 40 | D22: 1 | E22: ='OM Process Flow'!$C$26 -> 80 | F22: =C22/E22 -> 0.5
B23: QUALITY CHECK | C23: ='OM Process Flow'!C23/D23 -> 80 | D23: ='OM Process Flow'!E23 -> 1 | E23: ='OM Process Flow'!$C$26 -> 80 | F23: =C23/E23 -> 1 | H23: DEMAND UTILIZATION
B24: PACKAGING WITH SHELLS | C24: ='OM Process Flow'!C24/D24 -> 60 | D24: ='OM Process Flow'!E24 -> 1 | E24: ='OM Process Flow'!$C$26 -> 80 | F24: =C24/E24 -> 0.75 | H24: ='MK Sales Projections'!D14/'OM Capacity Analysis'!H21 -> 0.90227144
E25: AVERAGE CAPACITY UTILIZATION | F25: =AVERAGE(F18:F24) -> 0.69642857
B26: YEAR 3
B27: TASK | C27: TIME (SECONDS) | D27: WORKERS PER TASK | E27: CYCLE TIME | F27: CAPACITY UTILIZATION | H27: AVAILABLE TIME
B28: INJECTION MOLDING | C28: ='OM Process Flow'!C30/D28 -> 30 | D28: ='OM Process Flow'!E30 -> 1 | E28: ='OM Process Flow'!C38 -> 60 | F28: =C28/E28 -> 0.5 | H28: ='OM Assumptions'!$C$7 -> 2000
B29: ELECTRONIC ASSEMBLY | C29: ='OM Process Flow'!C31/D29 -> 60 | D29: ='OM Process Flow'!E31 -> 2 | E29: ='OM Process Flow'!$C$38 -> 60 | F29: =C29/E29 -> 1
B30: ELECTRONIC INSTALLATION | C30: ='OM Process Flow'!C32/D30 -> 40 | D30: ='OM Process Flow'!E32 -> 2 | E30: ='OM Process Flow'!$C$38 -> 60 | F30: =C30/E30 -> 0.66666667 | H30: MAXIMUM CAPACITY
B31: FLAG ASSEMBLY | C31: ='OM Process Flow'!C33/D31 -> 40 | D31: ='OM Process Flow'!E33 -> 1 | E31: ='OM Process Flow'!$C$38 -> 60 | F31: =C31/E31 -> 0.66666667 | H31: =((8*60*60)/E28)*250 -> 120000
B32: SECURING CHASSIS | C32: ='OM Process Flow'!C34/D32 -> 40 | D32: ='OM Process Flow'!E34 -> 1 | E32: ='OM Process Flow'!$C$38 -> 60 | F32: =C32/E32 -> 0.66666667
B33: QUALITY CHECK | C33: ='OM Process Flow'!C35/D33 -> 40 | D33: ='OM Process Flow'!E35 -> 2 | E33: ='OM Process Flow'!$C$38 -> 60 | F33: =C33/E33 -> 0.66666667 | H33: DEMAND UTILIZATION
B34: PACKAGING WITH SHELLS | C34: ='OM Process Flow'!C36/D34 -> 60 | D34: ='OM Process Flow'!E36 -> 1 | E34: ='OM Process Flow'!$C$38 -> 60 | F34: =C34/E34 -> 1 | H34: ='MK Sales Projections'!E14/'OM Capacity Analysis'!H31 -> 0.88136278
E35: AVERAGE CAPACITY UTILIZATION | F35: =AVERAGE(F28:F34) -> 0.73809524
B36: YEAR 4
B37: TASK | C37: TIME (SECONDS) | D37: WORKERS PER TASK | E37: CYCLE TIME | F37: CAPACITY UTILIZATION | H37: AVAILABLE TIME
B38: INJECTION MOLDING | C38: ='OM Process Flow'!C42/D38 -> 30 | D38: 1 | E38: ='OM Process Flow'!$C$50 -> 40 | F38: =C38/E38 -> 0.75 | H38: ='OM Assumptions'!$C$7 -> 2000
B39: ELECTRONIC ASSEMBLY | C39: ='OM Process Flow'!C43/D39 -> 40 | D39: 3 | E39: ='OM Process Flow'!$C$50 -> 40 | F39: =C39/E39 -> 1
B40: ELECTRONIC INSTALLATION | C40: ='OM Process Flow'!C44/D40 -> 40 | D40: 2 | E40: ='OM Process Flow'!$C$50 -> 40 | F40: =C40/E40 -> 1 | H40: MAXIMUM CAPACITY
B41: FLAG ASSEMBLY | C41: ='OM Process Flow'!C45/D41 -> 40 | D41: 1 | E41: ='OM Process Flow'!$C$50 -> 40 | F41: =C41/E41 -> 1 | H41: =((8*60*60)/E38)*250 -> 180000
B42: SECURING CHASSIS | C42: ='OM Process Flow'!C46/D42 -> 40 | D42: 1 | E42: ='OM Process Flow'!$C$50 -> 40 | F42: =C42/E42 -> 1
B43: QUALITY CHECK | C43: ='OM Process Flow'!C47/D43 -> 40 | D43: 2 | E43: ='OM Process Flow'!$C$50 -> 40 | F43: =C43/E43 -> 1 | H43: DEMAND UTILIZATION
B44: PACKAGING WITH SHELLS | C44: ='OM Process Flow'!C48/D44 -> 30 | D44: 2 | E44: ='OM Process Flow'!$C$50 -> 40 | F44: =C44/E44 -> 0.75 | H44: ='MK Sales Projections'!F14/'OM Capacity Analysis'!H41 -> 0.88595799
E45: AVERAGE CAPACITY UTILIZATION | F45: =AVERAGE(F38:F44) -> 0.92857143
B46: YEAR 5
B47: TASK | C47: TIME (SECONDS) | D47: WORKERS PER TASK | E47: CYCLE TIME | F47: CAPACITY UTILIZATION | H47: AVAILABLE TIME
B48: INJECTION MOLDING | C48: ='OM Process Flow'!C54/D48 -> 30 | D48: 1 | E48: ='OM Process Flow'!$C$62 -> 30 | F48: =C48/E48 -> 1 | H48: ='OM Assumptions'!$C$7 -> 2000
B49: ELECTRONIC ASSEMBLY | C49: ='OM Process Flow'!C55/D49 -> 30 | D49: 4 | E49: ='OM Process Flow'!$C$62 -> 30 | F49: =C49/E49 -> 1
B50: ELECTRONIC INSTALLATION | C50: ='OM Process Flow'!C56/D50 -> 26.666667 | D50: 3 | E50: ='OM Process Flow'!$C$62 -> 30 | F50: =C50/E50 -> 0.88888889 | H50: MAXIMUM CAPACITY
B51: FLAG ASSEMBLY | C51: ='OM Process Flow'!C57/D51 -> 20 | D51: 2 | E51: ='OM Process Flow'!$C$62 -> 30 | F51: =C51/E51 -> 0.66666667 | H51: =((8*60*60)/E48)*250 -> 240000
B52: SECURING CHASSIS | C52: ='OM Process Flow'!C58/D52 -> 20 | D52: 2 | E52: ='OM Process Flow'!$C$62 -> 30 | F52: =C52/E52 -> 0.66666667
B53: QUALITY CHECK | C53: ='OM Process Flow'!C59/D53 -> 26.666667 | D53: 3 | E53: ='OM Process Flow'!$C$62 -> 30 | F53: =C53/E53 -> 0.88888889 | H53: DEMAND UTILIZATION
B54: PACKAGING WITH SHELLS | C54: ='OM Process Flow'!C60/D54 -> 30 | D54: 2 | E54: ='OM Process Flow'!$C$62 -> 30 | F54: =C54/E54 -> 1 | H54: ='MK Sales Projections'!G14/'OM Capacity Analysis'!H51 -> 0.99469458
E55: AVERAGE CAPACITY UTILIZATION | F55: =AVERAGE(F48:F54) -> 0.87301587

Sheet OM MOH Expenses
B2: MANFACTURING OVERHEAD (YEARS 1-5)
B4: TOTAL OVERHEAD PER YEAR
B5: OVERHEAD EXPENSE | C5: YEAR 1 | D5: YEAR 2 | E5: YEAR 3 | F5: YEAR 4 | G5: YEAR 5
B6: MANUFACTURING SPACE (SQFT) | C6: ='OM Location Analysis '!C7 -> 4940 | D6: ='OM Location Analysis '!D7 -> 4989.4 | E6: ='OM Location Analysis '!E7 -> 5039.294 | F6: ='OM Location Analysis '!F7 -> 5089.6869 | G6: ='OM Location Analysis '!G7 -> 5140.5838
B7: PRICE PER SQFT PER YEAR | C7: ='OM Location Analysis '!C10 -> 11.04 | D7: ='OM Location Analysis '!D10 -> 11.2608 | E7: ='OM Location Analysis '!E10 -> 11.486016 | F7: ='OM Location Analysis '!F10 -> 11.715736 | G7: ='OM Location Analysis '!G10 -> 11.950051
B8: TOTAL MANUFACTURING RENT | C8: =C6*C7 -> 54537.6 | D8: =D6*D7 -> 56184.636 | E8: =E6*E7 -> 57881.412 | F8: =F6*F7 -> 59629.43 | G8: =G6*G7 -> 61430.239
B9: TOTAL ELECTRICITY COST | C9: =C22 -> 65771.16 | D9: =D22 -> 67757.449 | E9: =E22 -> 69803.724 | F9: =F22 -> 71911.796 | G9: =G22 -> 74083.533
B10: TOTAL WATER COST | C10: =C30 -> 301.34 | D10: =D30 -> 325.96249 | E10: =E30 -> 352.59689 | F10: =F30 -> 381.40758 | G10: =G30 -> 412.57239
B11: TOTAL UTILITIES COST | C11: =SUM(C8:C10) -> 120610.1 | D11: =SUM(D8:D10) -> 124268.05 | E11: =SUM(E8:E10) -> 128037.73 | F11: =SUM(F8:F10) -> 131922.63 | G11: =SUM(G8:G10) -> 135926.34
B12: TOTAL UTILITIES COST PER UNIT | C12: =C11/'MK Sales Projections'!C14 -> 2.5542523 | D12: =D11/'MK Sales Projections'!D14 -> 1.5303112 | E12: =E11/'MK Sales Projections'!E14 -> 1.2106038 | F12: =F11/'MK Sales Projections'!F14 -> 0.8272441 | G12: =G11/'MK Sales Projections'!G14 -> 0.56938057
B13: INDIRECT MATERIALS | C13: ='OM Direct Materials & Direct La'!F33*'OM Assumptions'!$F$25 -> 1.5314447 | D13: ='OM Direct Materials & Direct La'!F51*'OM Assumptions'!$F$25 -> 1.5314447 | E13: ='OM Direct Materials & Direct La'!F68*'OM Assumptions'!$F$25 -> 1.5314447 | F13: ='OM Direct Materials & Direct La'!F85*'OM Assumptions'!$F$25 -> 1.5314447 | G13: ='OM Direct Materials & Direct La'!F102*'OM Assumptions'!$F$25 -> 1.5314447
B14: MANUFACTURING OVERHEAD PER UNIT | C14: =SUM(C12:C13) -> 4.085697 | D14: =SUM(D12:D13) -> 3.0617559 | E14: =SUM(E12:E13) -> 2.7420485 | F14: =SUM(F12:F13) -> 2.3586888 | G14: =SUM(G12:G13) -> 2.1008253
B15: TOTAL MANUFACTURING OVERHEAD | C15: =C14*'MK Sales Projections'!C14 -> 192923.91 | D15: =D14*'MK Sales Projections'!D14 -> 248628.14 | E15: =E14*'MK Sales Projections'!E14 -> 290008.74 | F15: =F14*'MK Sales Projections'!F14 -> 376145.86 | G15: =G14*'MK Sales Projections'!G14 -> 501523.09
B17: ELECTRICITY
C18: YEAR 1 | D18: YEAR 2 | E18: YEAR 3 | F18: YEAR 4 | G18: YEAR 5
B19: COST PER KWH | C19: ='OM Assumptions'!F18 -> 0.14 | D19: =C19*(1+'OM Assumptions'!$F$19) -> 0.1428 | E19: =D19*(1+'OM Assumptions'!$F$19) -> 0.145656 | F19: =E19*(1+'OM Assumptions'!$F$19) -> 0.14856912 | G19: =F19*(1+'OM Assumptions'!$F$19) -> 0.1515405
B20: TOTAL ELECTRICITY USE (KWH) | C20: =C21*C6 -> 469794 | D20: =D21*D6 -> 474491.94 | E20: =E21*E6 -> 479236.86 | F20: =F21*F6 -> 484029.23 | G20: =G21*G6 -> 488869.52
B21: KWH USE PER SQFT | C21: 95.1 | D21: 95.1 | E21: 95.1 | F21: 95.1 | G21: 95.1
B22: TOTAL ELECTRICITY COST | C22: =C20*C19 -> 65771.16 | D22: =D20*D19 -> 67757.449 | E22: =E20*E19 -> 69803.724 | F22: =F20*F19 -> 71911.796 | G22: =G20*G19 -> 74083.533
B23: PER UNIT | C23: =C22/'MK Sales Projections'!$C$14 -> 1.3928861 | D23: =D22/'MK Sales Projections'!$C$14 -> 1.4349513 | E23: =E22/'MK Sales Projections'!$C$14 -> 1.4782868 | F23: =F22/'MK Sales Projections'!$C$14 -> 1.5229311 | G23: =G22/'MK Sales Projections'!$C$14 -> 1.5689236
B25: WATER
B26: UTILITY EXPENSE | C26: YEAR 1 | D26: YEAR 2 | E26: YEAR 3 | F26: YEAR 4 | G26: YEAR 5
B27: COST PER GALLON | C27: ='OM Assumptions'!$F$17 -> 0.00305 | D27: =C27*(1+('OM Assumptions'!$F$21)) -> 0.003111 | E27: =D27*(1+('OM Assumptions'!$F$21)) -> 0.00317322 | F27: =E27*(1+('OM Assumptions'!$F$21)) -> 0.0032366844 | G27: =F27*(1+('OM Assumptions'!$F$21)) -> 0.0033014181
B28: GALLONS USED PER SQT | C28: 20 | D28: =C28*((1+('OM Assumptions'!$F$22))) -> 21 | E28: =D28*((1+('OM Assumptions'!$F$22))) -> 22.05 | F28: =E28*((1+('OM Assumptions'!$F$22))) -> 23.1525 | G28: =F28*((1+('OM Assumptions'!$F$22))) -> 24.310125
B29: TOTAL GALLONS USED | C29: =C28*C6 -> 98800 | D29: =D28*D6 -> 104777.4 | E29: =E28*E6 -> 111116.43 | F29: =F28*F6 -> 117838.98 | G29: =G28*G6 -> 124968.24
B30: TOTAL WATER COST | C30: =C29*C27 -> 301.34 | D30: =D29*D27 -> 325.96249 | E30: =E29*E27 -> 352.59689 | F30: =F29*F27 -> 381.40758 | G30: =G29*G27 -> 412.57239
B31: PER UNIT | C31: =C30/'MK Sales Projections'!$C$14 -> 0.0063817075 | D31: =D30/'MK Sales Projections'!$C$14 -> 0.0069031569 | E31: =E30/'MK Sales Projections'!$C$14 -> 0.0074672138 | F31: =F30/'MK Sales Projections'!$C$14 -> 0.0080773598 | G31: =G30/'MK Sales Projections'!$C$14 -> 0.0087373609

Sheet OM Location Analysis 
B2: LOCATION ANALYSIS
B4: 8800 SOUTH FREEWAY, FORT WORTH, TX 76140
B5: WAREHOUSE SPECIFICATION | C5: YEAR 1 | D5: YEAR 2 | E5: YEAR 3 | F5: YEAR 4 | G5: YEAR 5
B6: TOTAL WAREHOUSE SIZE (SQFT) | C6: 5200 | D6: =C6*(1+'OM Assumptions'!$F$13) -> 5252 | E6: =D6*(1+'OM Assumptions'!$F$13) -> 5304.52 | F6: =E6*(1+'OM Assumptions'!$F$13) -> 5357.5652 | G6: =F6*(1+'OM Assumptions'!$F$13) -> 5411.1409
B7: MANUFACTURING SPACE PER YEAR | C7: =C6-C8 -> 4940 | D7: =D6-D8 -> 4989.4 | E7: =E6-E8 -> 5039.294 | F7: =F6-F8 -> 5089.6869 | G7: =G6-G8 -> 5140.5838
B8: OFFICE SPACE | C8: =C6*'OM Assumptions'!$F$14 -> 260 | D8: =D6*'OM Assumptions'!$F$14 -> 262.6 | E8: =E6*'OM Assumptions'!$F$14 -> 265.226 | F8: =F6*'OM Assumptions'!$F$14 -> 267.87826 | G8: =G6*'OM Assumptions'!$F$14 -> 270.55704
B9: COST PER SQFT PER MONTH | C9: ='OM Assumptions'!F15 -> 0.92 | D9: =C9*(1+'OM Assumptions'!$F$16) -> 0.9384 | E9: =D9*(1+'OM Assumptions'!$F$16) -> 0.957168 | F9: =E9*(1+'OM Assumptions'!$F$16) -> 0.97631136 | G9: =F9*(1+'OM Assumptions'!$F$16) -> 0.99583759
B10: COST PER SQFT PER YEAR | C10: =C9*12 -> 11.04 | D10: =D9*12 -> 11.2608 | E10: =E9*12 -> 11.486016 | F10: =F9*12 -> 11.715736 | G10: =G9*12 -> 11.950051
B11: TOTAL MANUFACTURING RENT PER YEAR | C11: =C7*C10 -> 54537.6 | D11: =D7*D10 -> 56184.636 | E11: =E7*E10 -> 57881.412 | F11: =F7*F10 -> 59629.43 | G11: =G7*G10 -> 61430.239
B12: TOTAL OFFICE RENT PER YEAR | C12: =C8*C10 -> 2870.4 | D12: =D8*D10 -> 2957.0861 | E12: =E8*E10 -> 3046.3901 | F12: =F8*F10 -> 3138.3911 | G12: =G8*G10 -> 3233.1705 | I12: Rent Sensitivity
B13: TOTAL RENT PER YEAR | C13: =SUM(C11:C12)*$I$13 -> 57408 | D13: =SUM(D11:D12)*$I$13 -> 59141.722 | E13: =SUM(E11:E12)*$I$13 -> 60927.802 | F13: =SUM(F11:F12)*$I$13 -> 62767.821 | G13: =SUM(G11:G12)*$I$13 -> 64663.409 | I13: 1
B15: CENTER OF GRAVITY ANALYSIS
B16: Locations | C16: X | D16: Y | E16: Revenue | F16: Revenue % | G16: Year 1 Sales | H16: Demand At Location
B17: OOH Advertising Locations | G17: ='MK Sales Projections'!C14 -> 47219.337
B18: California (SF) | C18: -122.4194 | D18: 37.7749 | E18: =740*1000000 -> 740000000 | F18: 0.094 | H18: =F18*$G$17 -> 4438.6177
B19: New york city | C19: -74.006 | D19: 40.7128 | E19: =317.1*1000000 -> 317100000 | F19: 0.04 | H19: =F19*$G$17 -> 1888.7735
B20: Minnesota (Minneapolis) | C20: -93.265 | D20: 44.9778 | E20: =210*1000000 -> 210000000 | F20: 0.027 | H20: =F20*$G$17 -> 1274.9221
B21: Maryland (DC) | C21: -77.0369 | D21: 38.9072 | E21: =151.2*1000000 -> 151200000 | F21: 0.019 | H21: =F21*$G$17 -> 897.16741
B22: Massachusetts (Boston) | C22: -71.0565 | D22: 42.3555 | E22: =143.3*1000000 -> 143300000 | F22: 0.018 | H22: =F22*$G$17 -> 849.94807
B23: Austin, TX | C23: -97.7431 | D23: 30.2672 | E23: =581.2*1000000 -> 581200000 | F23: 0.074 | H23: =F23*$G$17 -> 3494.231
B24: Chicago, IL | C24: -87.6324 | D24: 41.8832 | E24: =188.6*1000000 -> 188600000 | F24: 0.024 | H24: =F24*$G$17 -> 1133.2641
B25: Denver, CO | C25: -104.9903 | D25: 39.7392 | E25: =137*1000000 -> 137000000 | F25: 0.017 | H25: =F25*$G$17 -> 802.72873
B26: Philadelphia, PA | C26: -75.1652 | D26: 39.9526 | E26: =246.6*1000000 -> 246600000 | F26: 0.031 | H26: =F26*$G$17 -> 1463.7995
B27: Los Angeles, CA | C27: -118.2426 | D27: 34.0549 | E27: =740*1000000 -> 740000000 | F27: 0.094 | H27: =F27*$G$17 -> 4438.6177
B28: OOH Center of Gravity | C28: =SUMPRODUCT(C$18:C$27,$H$18:$H$27)/SUM($H$18:$H$27) -> -101.12891 | D28: =SUMPRODUCT(D$18:D$27,$H$18:$H$27)/SUM($H$18:$H$27) -> 37.113279
B29: Distribution Locations
B30: Mass Merchants
B31: Walmart: Indiana | C31: -85.9198 | D31: 39.8943 | E31: =159*1000000 -> 159000000 | F31: 0.02 | H31: =F31*$G$17 -> 944.38675
B32: Target: Georgia | C32: -81.264 | D32: 32.136 | E32: =191.9*1000000 -> 191900000 | F32: 0.024 | H32: =F32*$G$17 -> 1133.2641
B33: Mass Merchants Center of Gravity | C33: =SUMPRODUCT(C$31:C$32,$H$31:$H$32)/SUM($H$31:$H$32) -> -83.380273 | D33: =SUMPRODUCT(D$31:D$32,$H$31:$H$32)/SUM($H$31:$H$32) -> 35.6625
B34: Chains
B35: REI: Tennessee | C35: -86.2911 | D35: 36.20811 | E35: =173.2*1000000 -> 173200000 | F35: 0.022 | H35: =F35*$G$17 -> 1038.8254
B36: TREK: Wisconscin | C36: -89.5 | D36: 44.5 | E36: =202.3*1000000 -> 202300000 | F36: 0.026 | H36: =F36*$G$17 -> 1227.7028
B37: Scheels: Minnesota | C37: -94.6362 | D37: 46.3924 | E37: =210*1000000 -> 210000000 | F37: 0.027 | H37: =F37*$G$17 -> 1274.9221
B38: Chains Center of Gravity | C38: =SUMPRODUCT(C$35:C$37,$H$35:$H$37)/SUM($H$35:$H$37) -> -90.407755 | D38: =SUMPRODUCT(D$35:D$37,$H$35:$H$37)/SUM($H$35:$H$37) -> 42.748976
B39: Independent
B40: Bicycle Habitat: NYC | C40: -73.9966 | D40: 40.7449 | E40: =317.1*1000000 -> 317100000 | F40: 0.04 | H40: =F40*$G$17 -> 1888.7735
